Workbook

Sheet tmpA1A6
A1: KANE-JONES
A2: SALES REGISTER
A3: 7/1/2026 TO 7/15/2026
A4: VOUCHER DATE | B4: PARTICULARS | C4: VCHNO | D4: Purchase Order No | E4: TRANSACTION VALUE | F4: RECEIVED AMOUNT | G4: OUTSTANDING AMOUNT | H4: GROSS REVENUE | I4: COST | J4: GROSS PROFIT | K4: % PROFIT | L4: NARRATION
A5: 46204 | B5: Walk in Customer | C5: ann-INV142 | E5: 18500 | F5: 18500 | G5: 0 | H5: 18500 | I5: 16759 | J5: 1741 | K5: 9
B6: ITEM/SERVICE | C6: QUANTITY | D6: RATE | E6: COST | F6: DESCRIPTION
B7: Trophy | C7: 1 | D7: 9000 | E7: 8122
B8: Goldberg 60cl | C8: 1 | D8: 9500 | E8: 8637
A10: 46204 | B10: Walk in Customer | C10: ann-INV143 | E10: 5400 | F10: 5400 | G10: 0 | H10: 5400 | I10: 5200 | J10: 200 | K10: 4
B11: ITEM/SERVICE | C11: QUANTITY | D11: RATE | E11: COST | F11: DESCRIPTION
B12: Maltina Pet 33cl | C12: 1 | D12: 5400 | E12: 5200
A14: 46204 | B14: Eniola Marketer | C14: ann-INV144 | E14: 1533700 | F14: 1533700 | G14: 0 | H14: 1533700 | I14: 1579003 | J14: -45303 | K14: -3
B15: ITEM/SERVICE | C15: QUANTITY | D15: RATE | E15: COST | F15: DESCRIPTION
B16: Maltina Pet 33cl | C16: 200 | D16: 4950 | E16: 1040000
B17: Maltina Pet 50cl | C17: 35 | D17: 8020 | E17: 268975
B18: Maltina Can | C18: 20 | D18: 13150 | E18: 270028 | J18: =SUM(J5:J14) -> -43362
A20: 46205 | B20: Ameh Mathew | C20: ann-INV145 | E20: 821130 | F20: 821130 | G20: 0 | H20: 821130 | I20: 811313 | J20: 9817 | K20: 1
B21: ITEM/SERVICE | C21: QUANTITY | D21: RATE | E21: COST | F21: DESCRIPTION
B22: Maltina Pet 33cl | C22: 40 | D22: 4900 | E22: 208000
B23: Heineken Sleek Can | C23: 15 | D23: 17845 | E23: 256500
B24: Goldberg Can 50cl | C24: 3 | D24: 16145 | E24: 45746
B25: 33 Export Can | C25: 2 | D25: 16145 | E25: 31110
B26: Maltina Can | C26: 5 | D26: 13200 | E26: 67507
B27: Desperados Can | C27: 2 | D27: 22740 | E27: 43190
B28: Legend Can 44cl | C28: 2 | D28: 21170 | E28: 40810
B29: Tiger Bottle | C29: 6 | D29: 15525 | E29: 89400
B30: Turbo King Bottle 60cl | C30: 2 | D30: 8880 | E30: 17050
B31: NB Empties | C31: 8 | D31: 1500 | E31: 12000
A33: 46205 | B33: Ameh Mathew | C33: ann-INV146 | E33: 256500 | F33: 256500 | G33: 0 | H33: 256500 | I33: 256500 | J33: 0 | K33: 0
B34: ITEM/SERVICE | C34: QUANTITY | D34: RATE | E34: COST | F34: DESCRIPTION
B35: Heineken Sleek Can | C35: 15 | D35: 17100 | E35: 256500
A37: 46205 | B37: TD Odiolowo | C37: ann-INV147 | E37: 86000 | F37: 86000 | G37: 0 | H37: 86000 | I37: 86374 | J37: -374 | K37: 0
B38: ITEM/SERVICE | C38: QUANTITY | D38: RATE | E38: COST | F38: DESCRIPTION
B39: Goldberg 60cl | C39: 10 | D39: 8600 | E39: 86374
A41: 46205 | B41: Ameh Mathew | C41: ann-INV148 | E41: 62070 | F41: 62070 | G41: 0 | H41: 62070 | I41: 59758 | J41: 2312 | K41: 4
B42: ITEM/SERVICE | C42: QUANTITY | D42: RATE | E42: COST | F42: DESCRIPTION
B43: Medium Stout | C43: 1 | D43: 17700 | E43: 17150
B44: Trophy | C44: 1 | D44: 8500 | E44: 8122
B45: 33 Export 60cl | C45: 1 | D45: 9200 | E45: 8990
B46: Heineken Bottle 60cl | C46: 2 | D46: 13335 | E46: 25496
A48: 46205 | B48: TD Odiolowo | C48: ann-INV149 | E48: 15000 | F48: 15000 | G48: 0 | H48: 15000 | I48: 15000 | J48: 0 | K48: 0
B49: ITEM/SERVICE | C49: QUANTITY | D49: RATE | E49: COST | F49: DESCRIPTION
B50: NB Empties | C50: 10 | D50: 1500 | E50: 15000
A52: 46205 | B52: Ameh Mathew | C52: ann-INV150 | E52: 11100 | F52: 11100 | G52: 0 | H52: 11100 | I52: 8109 | J52: 2991 | K52: 27
B53: ITEM/SERVICE | C53: QUANTITY | D53: RATE | E53: COST | F53: DESCRIPTION
B54: NB Empties | C54: 3 | D54: 1500 | E54: 4500
B55: IB Empties | C55: 1 | D55: 1600 | E55: 1600
B56: GNS EMPTIES | C56: 1 | D56: 5000 | E56: 2009
A58: 46205 | B58: Rita SR | C58: ann-INV152 | E58: 1421000 | F58: 1421000 | G58: 0 | H58: 1421000 | I58: 1426855 | J58: -5855 | K58: 0
B59: ITEM/SERVICE | C59: QUANTITY | D59: RATE | E59: COST | F59: DESCRIPTION
B60: 33 Export Can | C60: 25 | D60: 15655 | E60: 388875
B61: Goldberg Can 50cl | C61: 30 | D61: 15655 | E61: 457456
B62: Maltina Can | C62: 35 | D62: 12900 | E62: 472549
B63: Desperados Can | C63: 5 | D63: 21695 | E63: 107975
A65: 46205 | B65: Ameh Mathew | C65: ann-INV153 | E65: 56940 | F65: 56940 | G65: 0 | H65: 56940 | I65: 55795 | J65: 1145 | K65: 2
B66: ITEM/SERVICE | C66: QUANTITY | D66: RATE | E66: COST | F66: DESCRIPTION
B67: Heineken Sleek Can | C67: 2 | D67: 17100 | E67: 34200
B68: Desperados Can | C68: 1 | D68: 22740 | E68: 21595
A70: 46205 | B70: TD Odiolowo | C70: ann-INV154 | E70: 17200 | F70: 17200 | G70: 0 | H70: 17200 | I70: 17275 | J70: -75 | K70: 0
B71: ITEM/SERVICE | C71: QUANTITY | D71: RATE | E71: COST | F71: DESCRIPTION
B72: Goldberg 60cl | C72: 2 | D72: 8600 | E72: 17275
A74: 46205 | B74: Ameh Mathew | C74: ann-INV155 | E74: 8880 | F74: 8880 | G74: 0 | H74: 8880 | I74: 8525 | J74: 355 | K74: 4
B75: ITEM/SERVICE | C75: QUANTITY | D75: RATE | E75: COST | F75: DESCRIPTION
B76: Turbo King Bottle 60cl | C76: 1 | D76: 8880 | E76: 8525
A78: 46205 | B78: Eniola Marketer | C78: ann-INV156 | E78: 1324235 | F78: 1324235 | G78: 0 | H78: 1324235 | I78: 1374250 | J78: -50015 | K78: -4
B79: ITEM/SERVICE | C79: QUANTITY | D79: RATE | E79: COST | F79: DESCRIPTION
B80: Maltina Pet 33cl | C80: 260 | D80: 5000 | E80: 1352000
B81: 4th Street wine | C81: 1 | D81: 24235 | E81: 22250
A83: 46205 | B83: Eniola Marketer | C83: ann-INV157 | E83: 40100 | F83: 40100 | G83: 0 | H83: 40100 | I83: 38425 | J83: 1675 | K83: 4
B84: ITEM/SERVICE | C84: QUANTITY | D84: RATE | E84: COST | F84: DESCRIPTION
B85: Maltina Pet 50cl | C85: 5 | D85: 8020 | E85: 38425
A87: 46205 | B87: Eniola Marketer | C87: ann-INV158 | E87: 80200 | F87: 80200 | G87: 0 | H87: 80200 | I87: 76850 | J87: 3350 | K87: 4
B88: ITEM/SERVICE | C88: QUANTITY | D88: RATE | E88: COST | F88: DESCRIPTION
B89: Maltina Pet 50cl | C89: 10 | D89: 8020 | E89: 76850
A91: 46205 | B91: Mr Lekan Ojifini | C91: ann-INV159 | E91: 67080 | F91: 67080 | G91: 0 | H91: 67080 | I91: 62850 | J91: 4230 | K91: 6
B92: ITEM/SERVICE | C92: QUANTITY | D92: RATE | E92: COST | F92: DESCRIPTION
B93: CLIMAX CAN | C93: 2 | D93: 12885 | E93: 24240
B94: ACE BITTERS | C94: 2 | D94: 20655 | E94: 38610
J95: =SUM(J20:J91) -> -30444
A96: 46206 | B96: WURAOLA | C96: ann-INV160 | E96: 4026260 | F96: 4026260 | G96: 0 | H96: 4026260 | I96: 3965433 | J96: 60827 | K96: 2
B97: ITEM/SERVICE | C97: QUANTITY | D97: RATE | E97: COST | F97: DESCRIPTION
B98: Goldberg 60cl | C98: 140 | D98: 8990 | E98: 1209241
B99: Heineken Bottle 60cl | C99: 140 | D99: 12830 | E99: 1784732
B100: Gulder Bottle | C100: 84 | D100: 11315 | E100: 950460
B101: NB Empties | C101: 14 | D101: 1500 | E101: 21000
A103: 46206 | B103: Abbey Illisan | C103: ann-INV161 | E103: 8796760 | F103: 2575760 | G103: 6221000 | H103: 8796760 | I103: 8663386 | J103: 133374 | K103: 2
B104: ITEM/SERVICE | C104: QUANTITY | D104: RATE | E104: COST | F104: DESCRIPTION
B105: Heineken Bottle 60cl | C105: 280 | D105: 12930 | E105: 3569464
B106: Goldberg 60cl | C106: 210 | D106: 8990 | E106: 1813862
B107: 33 Export 60cl | C107: 140 | D107: 8990 | E107: 1258600
B108: Gulder Bottle | C108: 84 | D108: 11415 | E108: 950460
B109: NB Empties | C109: 714 | D109: 1500 | E109: 1071000
A111: 46206 | B111: Ameh Mathew | C111: ann-INV162 | E111: 491680 | F111: 491680 | G111: 0 | H111: 491680 | I111: 475441 | J111: 16239 | K111: 3
B112: ITEM/SERVICE | C112: QUANTITY | D112: RATE | E112: COST | F112: DESCRIPTION
B113: 33 Export 60cl | C113: 15 | D113: 9200 | E113: 134850
B114: Heineken Bottle 60cl | C114: 10 | D114: 13335 | E114: 127481
B115: Amstel Bottle | C115: 1 | D115: 14450 | E115: 13780
B116: Fayrouz Can | C116: 1 | D116: 13460 | E116: 12855
B117: Turbo King Bottle 60cl | C117: 5 | D117: 8880 | E117: 42625
B118: Tiger Bottle | C118: 1 | D118: 15525 | E118: 14900
...

Sheet tmp32C7
A1: KANE-JONES
A2: SALES REGISTER
A3: 7/16/2026 TO 7/31/2026
A4: VOUCHER DATE | B4: PARTICULARS | C4: VCHNO | D4: Purchase Order No | E4: QUANTITY | F4: TRANSACTION VALUE | G4: RECEIVED AMOUNT | H4: OUTSTANDING AMOUNT | I4: GROSS REVENUE | J4: COST | K4: GROSS PROFIT | L4: % PROFIT | M4: NARRATION
A5: 46219 | B5: Taiwo SR | C5: ann-INV283 | E5: 10 | F5: 178125 | G5: 178125 | H5: 0 | I5: 178125 | J5: 168575 | K5: 9550 | L5: 5
B6: ITEM/SERVICE | C6: QUANTITY | D6: RATE | E6: COST | F6: DESCRIPTION
B7: Desperados Can | C7: 5 cans | D7: 22740 | E7: 107975
B8: CLIMAX CAN | C8: 5 cans | D8: 12885 | E8: 60600
A10: 46219 | B10: Walk in Customer | C10: ann-INV284 | E10: 1 | F10: 5300 | G10: 5300 | H10: 0 | I10: 5300 | J10: 5200 | K10: 100 | L10: 2
B11: ITEM/SERVICE | C11: QUANTITY | D11: RATE | E11: COST | F11: DESCRIPTION
B12: Maltina Pet 33cl | C12: 1 pets | D12: 5300 | E12: 5200
A14: 46219 | B14: Rita SR | C14: ann-INV285 | E14: 190 | F14: 1877025 | G14: 1000000 | H14: 877025 | I14: 1877025 | J14: 1892820 | K14: -15795 | L14: -1
B15: ITEM/SERVICE | C15: QUANTITY | D15: RATE | E15: COST | F15: DESCRIPTION
B16: Maltina Pet 33cl | C16: 100 pets | D16: 5000 | E16: 520000
B17: Goldberg Can 50cl | C17: 30 cans | D17: 15655 | E17: 457417
B18: Heineken Sleek Can | C18: 15 cans | D18: 17200 | E18: 256500
B19: 33 Export Can | C19: 25 cans | D19: 15655 | E19: 388875
B20: Maltina Can | C20: 20 cans | D20: 12900 | E20: 270028
A22: 46219 | B22: Walk in Customer | C22: ann-INV286 | E22: 3 | F22: 24060 | G22: 24060 | H22: 0 | I22: 24060 | J22: 23255 | K22: 805 | L22: 3
B23: ITEM/SERVICE | C23: QUANTITY | D23: RATE | E23: COST | F23: DESCRIPTION
B24: Maltina Pet 33cl | C24: 2 pets | D24: 5300 | E24: 10400
B25: Fayrouz Can | C25: 1 cans | D25: 13460 | E25: 12855
A27: 46219 | B27: Walk in Customer | C27: ann-INV287 | E27: 1 | F27: 5300 | G27: 0 | H27: 5300 | I27: 5300 | J27: 5200 | K27: 100 | L27: 2
B28: ITEM/SERVICE | C28: QUANTITY | D28: RATE | E28: COST | F28: DESCRIPTION
B29: Maltina Pet 33cl | C29: 1 pets | D29: 5300 | E29: 5200
A31: 46219 | B31: Eniola Marketer | C31: ann-INV288 | E31: 110 | F31: 575000 | G31: 575000 | H31: 0 | I31: 575000 | J31: 549837 | K31: 25163 | L31: 4
B32: ITEM/SERVICE | C32: QUANTITY | D32: RATE | E32: COST | F32: DESCRIPTION
B33: Goldberg 60cl | C33: 25 crt | D33: 9200 | E33: 216419
B34: Trophy | C34: 25 crt | D34: 8200 | E34: 203047
B35: 33 Export 60cl | C35: 5 crt | D35: 9200 | E35: 44950
B36: NB Empties | C36: 30 Empty | D36: 1800 | E36: 45421
B37: IB Empties | C37: 25 Empty | D37: 1600 | E37: 40000
A39: 46219 | B39: MRS IK. | C39: ann-INV289 | E39: 3 | F39: 27400 | G39: 27400 | H39: 0 | I39: 27400 | J39: 25435 | K39: 1965 | L39: 7
B40: ITEM/SERVICE | C40: QUANTITY | D40: RATE | E40: COST | F40: DESCRIPTION
B41: Goldberg 60cl | C41: 2 crt | D41: 9200 | E41: 17313
B42: Trophy | C42: 1 crt | D42: 9000 | E42: 8122
A44: 46219 | B44: Walk in Customer | C44: ann-INV290 | E44: 2 | F44: 24950 | G44: 0 | H44: 24950 | I44: 24950 | J44: 23877 | K44: 1073 | L44: 4
B45: ITEM/SERVICE | C45: QUANTITY | D45: RATE | E45: COST | F45: DESCRIPTION
B46: Heineken Bottle 60cl | C46: 1 crt | D46: 13350 | E46: 12747
B47: Star Bottle 60cl | C47: 1 crt | D47: 11600 | E47: 11130
A49: 46219 | B49: Walk in Customer | C49: ann-INV291 | E49: 1 | F49: 9200 | G49: 0 | H49: 9200 | I49: 9200 | J49: 8657 | K49: 543 | L49: 6
B50: ITEM/SERVICE | C50: QUANTITY | D50: RATE | E50: COST | F50: DESCRIPTION
B51: Goldberg 60cl | C51: 1 crt | D51: 9200 | E51: 8657
A53: 46219 | B53: Remilekun | C53: ann-INV292 | E53: 1 | F53: 9500 | G53: 9500 | H53: 0 | I53: 9500 | J53: 8990 | K53: 510 | L53: 5
B54: ITEM/SERVICE | C54: QUANTITY | D54: RATE | E54: COST | F54: DESCRIPTION
B55: 33 Export 60cl | C55: 1 crt | D55: 9500 | E55: 8990
A57: 46220 | B57: Rita SR | C57: ann-INV293 | E57: 60 | F57: 780000 | G57: 780000 | H57: 0 | I57: 780000 | J57: 790692 | K57: -10692 | L57: -1
B58: ITEM/SERVICE | C58: QUANTITY | D58: RATE | E58: COST | F58: DESCRIPTION
B59: Maltina Can | C59: 30 cans | D59: 12900 | E59: 405042
B60: Fayrouz Can | C60: 30 cans | D60: 13100 | E60: 385650
A62: 46220 | B62: Rita SR | C62: ann-INV296 | E62: 25 | F62: 322500 | G62: 322500 | H62: 0 | I62: 322500 | J62: 337535 | K62: -15035 | L62: -5
B63: ITEM/SERVICE | C63: QUANTITY | D63: RATE | E63: COST | F63: DESCRIPTION
B64: Maltina Can | C64: 25 cans | D64: 12900 | E64: 337535
A66: 46220 | B66: Mr Godswill | C66: ann-INV297 | E66: 1 | F66: 13460 | G66: 0 | H66: 13460 | I66: 13460 | J66: 12855 | K66: 605 | L66: 4
B67: ITEM/SERVICE | C67: QUANTITY | D67: RATE | E67: COST | F67: DESCRIPTION
B68: Fayrouz Can | C68: 1 cans | D68: 13460 | E68: 12855
A70: 46220 | B70: Ameh Mathew | C70: ann-INV294 | E70: 157 | F70: 866210 | G70: 866210 | H70: 0 | I70: 866210 | J70: 836885 | K70: 29325 | L70: 3
B71: ITEM/SERVICE | C71: QUANTITY | D71: RATE | E71: COST | F71: DESCRIPTION
B72: Goldberg 60cl | C72: 22 crt | D72: 8800 | E72: 190448
B73: Heineken Bottle 60cl | C73: 6 crt | D73: 13335 | E73: 76481
B74: Turbo King Bottle 60cl | C74: 9 crt | D74: 8880 | E74: 76725
B75: 33 Export 60cl | C75: 14 crt | D75: 9200 | E75: 125860
B76: Maltina Pet 33cl | C76: 50 pets | D76: 5000 | E76: 260000
B77: Fayrouz Can | C77: 1 cans | D77: 13460 | E77: 12855
B78: Gulder Bottle | C78: 2 crt | D78: 11910 | E78: 22630
B79: NB Empties | C79: 47 Empty | D79: 1800 | E79: 71159
B80: Empties Premium | C80: 6 Empty | D80: 2000 | E80: 727
A82: 46220 | B82: Walk in Customer | C82: ann-INV295 | E82: 4 | F82: 48720 | G82: 48720 | H82: 0 | I82: 48720 | J82: 44894 | K82: 3826 | L82: 8
B83: ITEM/SERVICE | C83: QUANTITY | D83: RATE | E83: COST | F83: DESCRIPTION
B84: Budweiser | C84: 1 crt | D84: 11320 | E84: 10410
B85: Heineken Bottle 60cl | C85: 2 crt | D85: 13950 | E85: 25494
B86: 33 Export 60cl | C86: 1 crt | D86: 9500 | E86: 8990
A88: 46220 | B88: MRS IK. | C88: ann-INV298 | E88: 13 | F88: 134460 | G88: 134460 | H88: 0 | I88: 134460 | J88: 125041 | K88: 9419 | L88: 7
B89: ITEM/SERVICE | C89: QUANTITY | D89: RATE | E89: COST | F89: DESCRIPTION
B90: Goldberg 60cl | C90: 1 crt | D90: 9200 | E90: 8657
B91: 33 Export 60cl | C91: 1 crt | D91: 9200 | E91: 8990
B92: Turbo King Bottle 60cl | C92: 1 crt | D92: 9200 | E92: 8525
B93: Trophy | C93: 1 crt | D93: 9000 | E93: 8122
B94: Medium Stout | C94: 1 crt | D94: 18300 | E94: 17150
B95: Heineken Bottle 60cl | C95: 1 crt | D95: 13950 | E95: 12747
B96: Gulder Bottle | C96: 1 crt | D96: 11910 | E96: 11315
B97: Desperados Bottle | C97: 1 crt | D97: 21400 | E97: 20440
B98: Star Bottle 60cl | C98: 2 crt | D98: 11600 | E98: 22260
B99: Maltina Pet 33cl | C99: 1 pets | D99: 5300 | E99: 5200
B100: NB Empties | C100: 1 Empty | D100: 1800 | E100: 1514
B101: Empties Premium | C101: 1 Empty | D101: 2000 | E101: 121
A103: 46220 | B103: OGUNDE SR | C103: ann-INV299 | E103: 384 | F103: 2976000 | G103: 2968250 | H103: 7750 | I103: 2976000 | J103: 2951040 | K103: 24960 | L103: 1
B104: ITEM/SERVICE | C104: QUANTITY | D104: RATE | E104: COST | F104: DESCRIPTION
B105: Maltina Pet 50cl | C105: 384 pets | D105: 7750 | E105: 2951040
A107: 46220 | B107: Ola SR | C107: ann-INV300 | E107: 1 | F107: 13200 | G107: 13200 | H107: 0 | I107: 13200 | J107: 13501 | K107: -301 | L107: -2
B108: ITEM/SERVICE | C108: QUANTITY | D108: RATE | E108: COST | F108: DESCRIPTION
B109: Maltina Can | C109: 1 cans | D109: 13200 | E109: 13501
A111: 46220 | B111: Eniola Marketer | C111: ann-INV301 | E111: 200 | F111: 1000000 | G111: 1000000 | H111: 0 | I111: 1000000 | J111: 1040000 | K111: -40000 | L111: -4
B112: ITEM/SERVICE | C112: QUANTITY | D112: RATE | E112: COST | F112: DESCRIPTION
B113: Maltina Pet 33cl | C113: 200 pets | D113: 5000 | E113: 1040000
A115: 46220 | B115: Ola SR | C115: ann-INV302 | E115: 12 | F115: 84625 | G115: 73825 | H115: 10800 | I115: 84625 | J115: 79894 | K115: 4731 | L115: 6
B116: ITEM/SERVICE | C116: QUANTITY | D116: RATE | E116: COST | F116: DESCRIPTION
B117: Star Bottle 60cl | C117: 4 crt | D117: 11600 | E117: 44520
B118: Legend Bottle 60cl | C118: 1 crt | D118: 11480 | E118: 10915
B119: Legend 45cl | C119: 1 crt | D119: 15945 | E119: 15375
...

Sheet tmp3F5D
A1: KANE-JONES
A2: Inventory Summary
A3: 7/1/2026 To 7/31/2026
A4: ITEM | B4: NO. OF UNITS | C4: UOM | D4: RATE PER UNIT | E4: VALUE | F4: DEFAULT PURCHASE PRICE
A5: Guiness | B5: 2419 | E5: 30129450
A6: Can | B6: 2144 | E6: 25728000
A7: Malta Gns Can. | B7: 2144 | C7: cans | D7: 12000 | E7: 25728000 | F7: 0
A8: RGB | B8: 275 | E8: 4401450
A9: Big Stout | B9: 140 | C9: crt | D9: 15330 | E9: 2146200 | F9: 15330
A10: Medium Stout | B10: 60 | C10: crt | D10: 17150 | E10: 1029000 | F10: 17150
A11: ORIJIN BT | B11: 0 | C11: crt | D11: 0 | E11: 0 | F11: 0
A12: Small Guinness Stout | B12: 0 | C12: crt | D12: 0 | E12: 0 | F12: 0
A13: Smirnoff Ice. | B13: 75 | C13: crt | D13: 16350 | E13: 1226250 | F13: 0
A14: IntlB | B14: 192 | E14: 1784215
A15: Can | B15: 0 | E15: 0
A16: TROPHY CAN | B16: 0 | C16: cans | D16: 0 | E16: 0 | F16: 0
A17: RGB | B17: 192 | E17: 1784215
A18: Budweiser | B18: 68 | C18: crt | D18: 10410 | E18: 707880 | F18: 0
A19: Castle Lite | B19: 60 | C19: crt | D19: 9280 | E19: 556800 | F19: 0
A20: Trophy | B20: 64 | C20: crt | D20: 8118 | E20: 519535 | F20: 8200
A21: NB PLC | B21: 28790 | E21: 260434163
A22: Can | B22: 2071 | E22: 35138079
A23: 33 Export Can | B23: 345 | C23: cans | D23: 15555 | E23: 5366475 | F23: 15555
A24: Amstel Can | B24: 2 | C24: cans | D24: 13911 | E24: 27821 | F24: 140750
A25: CLIMAX CAN | B25: 14 | C25: cans | D25: 12120 | E25: 169680 | F25: 0
A26: Desperados Can | B26: 92 | C26: cans | D26: 21595 | E26: 1986740 | F26: 21595
A27: Fayrouz Can | B27: 176 | C27: cans | D27: 12855 | E27: 2262480 | F27: 12855
A28: Goldberg Can 50cl | B28: 5 | C28: cans | D28: 15247 | E28: 76236 | F28: 15555
A29: Heineken Can 50cl | B29: 65 | C29: cans | D29: 22775 | E29: 1480375 | F29: 22775
A30: Heineken Sleek Can | B30: 1277 | C30: cans | D30: 17100 | E30: 21836700 | F30: 17100
A31: Legend Can 44cl | B31: 94 | C31: cans | D31: 20405 | E31: 1918070 | F31: 20405
A32: Maltina Can | B32: 1 | C32: cans | D32: 13501 | E32: 13501 | F32: 14070
A33: Pet | B33: 12269 | E33: 64180370
A34: ACE BITTERS | B34: 23 | C34: pets | D34: 19305 | E34: 444015 | F34: 0
A35: Fayrouz Pet | B35: 0 | C35: pets | D35: 0 | E35: 0 | F35: 4720
A36: Maltina Pet 25cl | B36: 0 | C36: pets | D36: 0 | E36: 0 | F36: 4000
A37: Maltina Pet 33cl | B37: 12223 | C37: pets | D37: 5200 | E37: 63559600 | F37: 5200
A38: Maltina Pet 50cl | B38: 23 | C38: pets | D38: 7685 | E38: 176755 | F38: 7685
A39: RGB | B39: 12430 | E39: 119702397
A40: 33 Export 60cl | B40: 2705 | C40: crt | D40: 8990 | E40: 24317950 | F40: 8990
A41: Amstel Bottle | B41: 117 | C41: crt | D41: 13780 | E41: 1612260 | F41: 13780
A42: Fayrouz Bottle | B42: 90 | C42: crt | D42: 9925 | E42: 893250 | F42: 9925
A43: Goldberg 60cl | B43: 4850 | C43: crt | D43: 8657 | E43: 41985217 | F43: 8990
A44: Goldberg Black 45cl | B44: 196 | C44: crt | D44: 13520 | E44: 2649920 | F44: 13520
A45: Goldberg Black Promo | B45: 4 | C45: crt | D45: 0 | E45: 0 | F45: 0
A46: Gulder Bottle | B46: 528 | C46: crt | D46: 11315 | E46: 5974320 | F46: 11315
A47: Legend 45cl | B47: 57 | C47: crt | D47: 15375 | E47: 876375 | F47: 15375
A48: Legend Bottle 60cl | B48: 463 | C48: crt | D48: 10915 | E48: 5053645 | F48: 10915
A49: Maltina Bottle | B49: 904 | C49: crt | D49: 12920 | E49: 11679680 | F49: 12920
A50: STK 33cl | B50: 338 | C50: crt | D50: 12390 | E50: 4187820 | F50: 12390
A51: Star Bottle 60cl | B51: 24 | C51: crt | D51: 11130 | E51: 267120 | F51: 11130
... A55: Williams Bottle 60cl | B55: 87 | C55: crt | D55: 8970 | E55: 780390 | F55: 8970
A56: RGB Premium | B56: 1889 | E56: 38281447
A57: Desperados Bottle | B57: 1788 | C57: crt | D57: 20440 | E57: 36546720 | F57: 20440
A58: Heineken Bottle 45cl | B58: 99 | C58: crt | D58: 17265 | E58: 1709235 | F58: 17265
A59: Heineken Bottle 60cl | B59: 2 | C59: crt | D59: 12746 | E59: 25492 | F59: 12730
A60: Wines | B60: 131 | E60: 3131870
A61: 4th Street wine | B61: 72 | C61: W&S | D61: 22250 | E61: 1602000 | F61: 22250
A62: Chamdor 75cl | B62: 59 | C62: W&S | D62: 25930 | E62: 1529870 | F62: 25930
A63: default | B63: 23604 | E63: 27619305
A64: default | B64: 23604 | E64: 27619305
A65: Empties Premium | B65: 3844 | C65: Empty | D65: 28 | E65: 107447 | F65: 2000
A66: GNS EMPTIES | B66: 277 | C66: Empty | D66: -7186 | E66: -1990644 | F66: 5000
A67: IB Empties | B67: 836 | C67: Empty | D67: 1575 | E67: 1316427 | F67: 1600
A68: NB Empties | B68: 18466 | C68: Empty | D68: 1520 | E68: 28075665 | F68: 2000
A69: NB Loose Crate | B69: 181 | C69: Empty | D69: 610 | E69: 110410 | F69: 750
A70: TOTAL VALUE | B70: 55005 | E70: NGN319,967,133

Sheet tmpCEF3
A1: KANE-JONES
A2: DAY BOOK
A3: 7/1/2026 TO 7/31/2026
A4: VOUCHER DATE | B4: DEBIT | C4: CREDIT | D4: VCH TYPE | E4: VCHNO | F4: DEBIT AMOUNT | G4: CREDIT AMOUNT
A5: 46205 | B5: Sales Return | C5: Ameh Mathew | D5: Credit Note | E5: ann-SLR17 | G5: 267675
B6: ITEM/SERVICE | C6: QUANTITY | D6: RATE | E6: DESCRIPTION
B7: Heineken Sleek Can | C7: 15 cans | D7: 17845
A9: 46205 | B9: Sales Return | C9: Ameh Mathew | D9: Credit Note | E9: ann-SLR20 | G9: 11100
B10: ITEM/SERVICE | C10: QUANTITY | D10: RATE | E10: DESCRIPTION
B11: NB Empties | C11: 3 Empty | D11: 1500
B12: IB Empties | C12: 1 Empty | D12: 1600
B13: GNS EMPTIES | C13: 1 Empty | D13: 5000
A15: 46205 | B15: Sales Return | C15: TD Odiolowo | D15: Credit Note | E15: ann-SLR18 | G15: 15000
B16: ITEM/SERVICE | C16: QUANTITY | D16: RATE | E16: DESCRIPTION
B17: NB Empties | C17: 10 Empty | D17: 1500
A19: 46205 | B19: Sales Return | C19: Ameh Mathew | D19: Credit Note | E19: ann-SLR19 | G19: 12000
B20: ITEM/SERVICE | C20: QUANTITY | D20: RATE | E20: DESCRIPTION
B21: NB Empties | C21: 8 Empty | D21: 1500
A23: 46206 | B23: Sales Return | C23: DESOLA STORE | D23: Credit Note | E23: ann-SLR21 | G23: 835000
B24: ITEM/SERVICE | C24: QUANTITY | D24: RATE | E24: DESCRIPTION
B25: Maltina Pet 33cl | C25: 148 pets | D25: 5100
B26: Maltina Pet 50cl | C26: 10 pets | D26: 8020
A28: 46206 | B28: Sales Return | C28: Ameh Mathew | D28: Credit Note | E28: ann-SLR23 | G28: 57000
B29: ITEM/SERVICE | C29: QUANTITY | D29: RATE | E29: DESCRIPTION
B30: NB Empties | C30: 38 Empty | D30: 1500
A32: 46206 | B32: Sales Return | C32: Abbey Illisan | D32: Credit Note | E32: ann-SLR22 | G32: 630000
B33: ITEM/SERVICE | C33: QUANTITY | D33: RATE | E33: DESCRIPTION
B34: NB Empties | C34: 420 Empty | D34: 1500
A36: 46206 | B36: Sales Return | C36: TD Odiolowo | D36: Credit Note | E36: ann-SLR24 | G36: 45000
B37: ITEM/SERVICE | C37: QUANTITY | D37: RATE | E37: DESCRIPTION
B38: NB Empties | C38: 30 Empty | D38: 1500
A40: 46207 | B40: Sales Return | C40: XXIII LOUNGE | D40: Credit Note | E40: ann-SLR25 | G40: 43500
B41: ITEM/SERVICE | C41: QUANTITY | D41: RATE | E41: DESCRIPTION
B42: NB Empties | C42: 29 Empty | D42: 1500
A44: 46207 | B44: Sales Return | C44: Abbey Illisan | D44: Credit Note | E44: ann-SLR26 | G44: 441000
B45: ITEM/SERVICE | C45: QUANTITY | D45: RATE | E45: DESCRIPTION
B46: NB Empties | C46: 294 Empty | D46: 1500
A48: 46209 | B48: Sales Return | C48: Eniola Marketer | D48: Credit Note | E48: ann-SLR27 | G48: 72000
B49: ITEM/SERVICE | C49: QUANTITY | D49: RATE | E49: DESCRIPTION
B50: IB Empties | C50: 45 Empty | D50: 1600
A52: 46209 | B52: Sales Return | C52: Looking Good | D52: Credit Note | E52: ann-SLR28 | G52: 324000
B53: ITEM/SERVICE | C53: QUANTITY | D53: RATE | E53: DESCRIPTION
B54: NB Empties | C54: 216 Empty | D54: 1500
A56: 46209 | B56: Sales Return | C56: Ameh Mathew | D56: Credit Note | E56: ann-SLR31 | G56: 45000
B57: ITEM/SERVICE | C57: QUANTITY | D57: RATE | E57: DESCRIPTION
B58: NB Empties | C58: 30 Empty | D58: 1500
A60: 46209 | B60: Sales Return | C60: Tmoney NB | D60: Credit Note | E60: ann-SLR30 | G60: 36000
B61: ITEM/SERVICE | C61: QUANTITY | D61: RATE | E61: DESCRIPTION
B62: NB Empties | C62: 24 Empty | D62: 1500
A64: 46209 | B64: Sales Return | C64: Mr Godswill | D64: Credit Note | E64: ann-SLR32 | G64: 750
B65: ITEM/SERVICE | C65: QUANTITY | D65: RATE | E65: DESCRIPTION
B66: NB Loose Crate | C66: 1 Empty | D66: 750
A68: 46210 | B68: Sales Return | C68: Eniola Marketer | D68: Credit Note | E68: ann-SLR33 | G68: 8000
B69: ITEM/SERVICE | C69: QUANTITY | D69: RATE | E69: DESCRIPTION
B70: IB Empties | C70: 5 Empty | D70: 1600
A72: 46210 | B72: Sales Return | C72: Eniola Marketer | D72: Credit Note | E72: ann-SLR34 | G72: 185000
B73: ITEM/SERVICE | C73: QUANTITY | D73: RATE | E73: DESCRIPTION
B74: NB Empties | C74: 102 Empty | D74: 1500
B75: IB Empties | C75: 20 Empty | D75: 1600
A77: 46210 | B77: Sales Return | C77: Rita SR | D77: Credit Note | E77: ann-SLR35 | G77: 86000
B78: ITEM/SERVICE | C78: QUANTITY | D78: RATE | E78: DESCRIPTION
B79: Heineken Sleek Can | C79: 5 cans | D79: 17200
A81: 46210 | B81: Sales Return | C81: Tmoney NB | D81: Credit Note | E81: ann-SLR36 | G81: 105000
B82: ITEM/SERVICE | C82: QUANTITY | D82: RATE | E82: DESCRIPTION
B83: NB Empties | C83: 70 Empty | D83: 1500
A85: 46210 | B85: Sales Return | C85: WURAOLA | D85: Credit Note | E85: ann-SLR37 | G85: 261000
B86: ITEM/SERVICE | C86: QUANTITY | D86: RATE | E86: DESCRIPTION
B87: NB Empties | C87: 174 Empty | D87: 1500
A89: 46210 | B89: Sales Return | C89: Ameh Mathew | D89: Credit Note | E89: ann-SLR38 | G89: 63000
B90: ITEM/SERVICE | C90: QUANTITY | D90: RATE | E90: DESCRIPTION
B91: NB Empties | C91: 42 Empty | D91: 1500
A93: 46210 | B93: Sales Return | C93: TD Odiolowo | D93: Credit Note | E93: ann-SLR39 | G93: 16500
B94: ITEM/SERVICE | C94: QUANTITY | D94: RATE | E94: DESCRIPTION
B95: NB Empties | C95: 11 Empty | D95: 1500
A97: 46211 | B97: Sales Return | C97: Rukky bee | D97: Credit Note | E97: ann-SLR40 | G97: 525000
B98: ITEM/SERVICE | C98: QUANTITY | D98: RATE | E98: DESCRIPTION
B99: NB Empties | C99: 280 Empty | D99: 1500
B100: Empties Premium | C100: 70 Empty | D100: 1500
A102: 46211 | B102: Sales Return | C102: Tmoney NB | D102: Credit Note | E102: ann-SLR41 | G102: 90000
B103: ITEM/SERVICE | C103: QUANTITY | D103: RATE | E103: DESCRIPTION
B104: NB Empties | C104: 60 Empty | D104: 1500
A106: 46211 | B106: Sales Return | C106: Eniola Marketer | D106: Credit Note | E106: ann-SLR42 | G106: 93000
B107: ITEM/SERVICE | C107: QUANTITY | D107: RATE | E107: DESCRIPTION
B108: NB Empties | C108: 62 Empty | D108: 1500
A110: 46211 | B110: Sales Return | C110: Solomon | D110: Credit Note | E110: ann-SLR43 | G110: 22000
B111: ITEM/SERVICE | C111: QUANTITY | D111: RATE | E111: DESCRIPTION
B112: NB Empties | C112: 10 Empty | D112: 1800
B113: Empties Premium | C113: 2 Empty | D113: 2000
A115: 46211 | B115: Sales Return | C115: Emmycee | D115: Credit Note | E115: ann-SLR44 | G115: 628000
B116: ITEM/SERVICE | C116: QUANTITY | D116: RATE | E116: DESCRIPTION
B117: NB Empties | C117: 235 Empty | D117: 2000
B118: Empties Premium | C118: 79 Empty | D118: 2000
A120: 46211 | B120: Sales Return | C120: Mr Musefiu | D120: Credit Note | E120: ann-SLR45 | G120: 106200
B121: ITEM/SERVICE | C121: QUANTITY | D121: RATE | E121: DESCRIPTION
B122: NB Empties | C122: 59 Empty | D122: 1800
A124: 46211 | B124: Sales Return | C124: Amandla | D124: Credit Note | E124: ann-SLR46 | G124: 34400
B125: ITEM/SERVICE | C125: QUANTITY | D125: RATE | E125: DESCRIPTION
B126: Empties Premium | C126: 10 Empty | D126: 2000
B127: NB Empties | C127: 8 Empty | D127: 1800
A129: 46211 | B129: Sales Return | C129: Delayers | D129: Credit Note | E129: ann-SLR47 | G129: 20000
...

Sheet July 1st Sales Report
A1: Date | B1: Product | C1: Cases_Sold | D1: Unit_Price_NGN | E1: Amount_NGN | F1: Customer | G1: Invoice No | I1: Product | J1: Quantity | K1: Revenue | L1: % of Total Revenue | N1: Total Revnue | O1: Total Cases Sold | P1: Total transaction
A2: 46204 | B2: Trophy | C2: 1 | D2: 9000 | E2: =C2*D2 -> 9000 | F2: Walk in Customer 1 | G2: ann-INV142 | I2: Trophy | J2: 1 | K2: 9000 | L2: =K2/K$7 -> 0.0057781202 | N2: =K7 -> 1557600 | O2: =J7 -> 258 | P2: =COUNT(I2:I6,J2:J6) -> 5
A3: 46204 | B3: Goldberg 60cl | C3: 1 | D3: 9500 | E3: =C3*D3 -> 9500 | F3: Walk in Customer 1 | G3: ann-INV142 | I3: Goldberg 60cl | J3: 1 | K3: 9500 | L3: =K3/K$7 -> 0.0060991269
A4: 46204 | B4: Maltina Pet 33cl | C4: 1 | D4: 5400 | E4: =C4*D4 -> 5400 | F4: Walk in Customer 2 | G4: ann-INV143 | I4: Maltina Pet 33cl | J4: 201 | K4: =SUM(E4+E5) -> 995400 | L4: =K4/K$7 -> 0.63906009
A5: 46204 | B5: Maltina Pet 33cl | C5: 200 | D5: 4950 | E5: =C5*D5 -> 990000 | F5: Eniola Marketer | G5: ann-INV144 | I5: Maltina Pet 50cl | J5: 35 | K5: =E6 -> 280700 | L5: =K5/K$7 -> 0.18021315
A6: 46204 | B6: Maltina Pet 50cl | C6: 35 | D6: 8020 | E6: =C6*D6 -> 280700 | F6: Eniola Marketer | G6: ann-INV144 | I6: Maltina Can | J6: 20 | K6: =E7 -> 263000 | L6: =K6/K$7 -> 0.16884951
A7: 46204 | B7: Maltina Can | C7: 20 | D7: 13150 | E7: =C7*D7 -> 263000 | F7: Eniola Marketer | G7: ann-INV144 | I7: Grand Total | J7: =C8 -> 258 | K7: =SUM(K2:K6) -> 1557600 | L7: =SUM(L2:L6) -> 1
B8: Grand Total | C8: =SUM(C2:C7) -> 258 | D8: =SUM(D2:D7) -> 50020 | E8: =SUM(E2:E7) -> 1557600
I20: Customer | J20: Amount_NGN | K20: % of Total Revenue | L20: Gross Profit
I21: Walk in Customer 1 | J21: =E2+E3 -> 18500 | K21: =J21/E$8 -> 0.011877247 | L21: 0.09
I22: Walk in Customer 2 | J22: =E4 -> 5400 | K22: =J22/E$8 -> 0.0034668721 | L22: 0.04
I23: Eniola Marketer | J23: =SUM(E5:E7) -> 1533700 | K23: =J23/E8 -> 0.98465588 | L23: -0.03
I24: Total | J24: =SUM(J21:J23) -> 1557600 | K24: 1
I28: Invoice No | J28: Amount_NGN | K28: Gross Profit
I29: ann-INV142 | J29: 18500 | K29: 0.09
I30: ann-INV143 | J30: 5400 | K30: 0.04
I31: ann-INV144 | J31: 1533700 | K31: -0.03
I32: Total | J32: =SUM(J29:J31) -> 1557600

Sheet July 2nd Sales Report
A1: Date | B1: Product | C1: Cases_Sold | D1: Unit_Price_NGN | E1: Amount_NGN | F1: Customer | G1: Invoice No | I1: Product | J1: Quantity | K1: Revenue | L1: % of Total Revenue | N1: Total Revnue | O1: Total Cases Sold | P1: Total transaction
A2: 46205 | B2: Maltina Pet 33cl | C2: 40 | D2: 4900 | E2: =C2*D2 -> 196000 | F2: Ameh Mathew | G2: ann-INV145 | I2: Maltina Pet 33cl | J2: =C2+C25 -> 300 | K2: =SUM(E2+E25) -> 1496000 | L2: =K2/K$20 -> 0.35371991 | N2: =K20 -> 4229335 | O2: =J20 -> 488 | P2: =COUNT(I2:I19,J2:J19) -> 18
A3: 46205 | B3: Heineken Sleek Can | C3: 15 | D3: 17845 | E3: =C3*D3 -> 267675 | F3: Ameh Mathew | G3: ann-INV145 | I3: Heineken Sleek Can | J3: =C3+C11+C21 -> 32 | K3: =E3+E11+E21 -> 558375 | L3: =K3/K$20 -> 0.1320243
A4: 46205 | B4: Goldberg Can 50cl | C4: 3 | D4: 16145 | E4: =C4*D4 -> 48435 | F4: Ameh Mathew | G4: ann-INV145 | I4: Goldberg Can 50cl | J4: =C4+C18 -> 33 | K4: =SUM(E4+E18) -> 518085 | L4: =K4/K$20 -> 0.12249798
A5: 46205 | B5: 33 Export Can | C5: 2 | D5: 16145 | E5: =C5*D5 -> 32290 | F5: Ameh Mathew | G5: ann-INV145 | I5: 4th Street wine | J5: 1 | K5: =E26 -> 24235 | L5: =K5/K$20 -> 0.0057302153
A6: 46205 | B6: Maltina Can | C6: 5 | D6: 13200 | E6: =C6*D6 -> 66000 | F6: Ameh Mathew | G6: ann-INV145 | I6: Maltina Can | J6: =C6+C19 -> 40 | K6: =SUM(E6+E19) -> 517500 | L6: =K6/K$20 -> 0.12235966
A7: 46205 | B7: Desperados Can | C7: 2 | D7: 22740 | E7: =C7*D7 -> 45480 | F7: Ameh Mathew | G7: ann-INV145 | I7: Desperados Can | J7: =C7+C20+C22 -> 8 | K7: =SUM(E7+E20+E22) -> 176695 | L7: =K7/K$20 -> 0.041778436
A8: 46205 | B8: Legend Can 44cl | C8: 2 | D8: 21170 | E8: =C8*D8 -> 42340 | F8: Ameh Mathew | G8: ann-INV145 | I8: Legend Can 44cl | J8: 2 | K8: =E8 -> 42340 | L8: =K8/K$20 -> 0.01001103
A9: 46205 | B9: Tiger Bottle | C9: 6 | D9: 15525 | E9: =C9*D9 -> 93150 | F9: Ameh Mathew | G9: ann-INV145 | I9: Tiger Bottle | J9: 6 | K9: =E9 -> 93150 | L9: =K9/K$20 -> 0.022024739
A10: 46205 | B10: Turbo King Bottle 60cl | C10: 2 | D10: 8880 | E10: =C10*D10 -> 17760 | F10: Ameh Mathew | G10: ann-INV145 | I10: Turbo King Bottle 60cl | J10: 2 | K10: =E10 -> 17760 | L10: =K10/K$20 -> 0.0041992417
A11: 46205 | B11: Heineken Sleek Can | C11: 15 | D11: 17100 | E11: =C11*D11 -> 256500 | F11: Ameh Mathew | G11: ann-INV146 | I11: Goldberg 60cl | J11: =C12+C23 -> 12 | K11: =E12+E23 -> 103200 | L11: =K11/K$20 -> 0.024400999
A12: 46205 | B12: Goldberg 60cl | C12: 10 | D12: 8600 | E12: =C12*D12 -> 86000 | F12: TD Odiolowo | G12: ann-INV147 | I12: Medium Stout | J12: 1 | K12: =E13 -> 17700 | L12: =K12/K$20 -> 0.0041850551
A13: 46205 | B13: Medium Stout | C13: 1 | D13: 17700 | E13: =C13*D13 -> 17700 | F13: Ameh Mathew | G13: ann-INV148 | I13: Trophy | J13: 1 | K13: =E14 -> 8500 | L13: =K13/K$20 -> 0.0020097722
A14: 46205 | B14: Trophy | C14: 1 | D14: 8500 | E14: =C14*D14 -> 8500 | F14: Ameh Mathew | G14: ann-INV148 | I14: 33 Export 60cl | J14: 1 | K14: =E15 -> 9200 | L14: =K14/K$20 -> 0.0021752829
A15: 46205 | B15: 33 Export 60cl | C15: 1 | D15: 9200 | E15: =C15*D15 -> 9200 | F15: Ameh Mathew | G15: ann-INV148 | I15: Heineken Bottle 60cl | J15: 2 | K15: =E16 -> 26670 | L15: =K15/K$20 -> 0.0063059559
A16: 46205 | B16: Heineken Bottle 60cl | C16: 2 | D16: 13335 | E16: =C16*D16 -> 26670 | F16: Ameh Mathew | G16: ann-INV148 | I16: 33 Export Can | J16: =C5+C17 -> 27 | K16: =E5+E17 -> 423665 | L16: =K16/K$20 -> 0.10017296
A17: 46205 | B17: 33 Export Can | C17: 25 | D17: 15655 | E17: =C17*D17 -> 391375 | F17: Rita SR | G17: ann-INV152 | I17: Maltina Pet 50cl | J17: =C27+C28 -> 15 | K17: =E27+E28 -> 120300 | L17: =K17/K$20 -> 0.028444188
A18: 46205 | B18: Goldberg Can 50cl | C18: 30 | D18: 15655 | E18: =C18*D18 -> 469650 | F18: Rita SR | G18: ann-INV152 | I18: CLIMAX CAN | J18: 2 | K18: =E29 -> 25770 | L18: =K18/K$20 -> 0.0060931565
A19: 46205 | B19: Maltina Can | C19: 35 | D19: 12900 | E19: =C19*D19 -> 451500 | F19: Rita SR | G19: ann-INV152 | I19: ACE BITTERS | J19: 2 | K19: =E30 -> 41310 | L19: =K19/K$20 -> 0.009767493
A20: 46205 | B20: Desperados Can | C20: 5 | D20: 21695 | E20: =C20*D20 -> 108475 | F20: Rita SR | G20: ann-INV152 | I20: Grand Total | J20: =C31 -> 488 | K20: =E31 -> 4229335 | L20: =K20/K$20 -> 1
A21: 46205 | B21: Heineken Sleek Can | C21: 2 | D21: 17100 | E21: =C21*D21 -> 34200 | F21: Ameh Mathew | G21: ann-INV153
A22: 46205 | B22: Desperados Can | C22: 1 | D22: 22740 | E22: =C22*D22 -> 22740 | F22: Ameh Mathew | G22: ann-INV153
A23: 46205 | B23: Goldberg 60cl | C23: 2 | D23: 8600 | E23: =C23*D23 -> 17200 | F23: TD Odiolowo | G23: ann-INV154
A24: 46205 | B24: Turbo King Bottle 60cl | C24: 1 | D24: 8880 | E24: =C24*D24 -> 8880 | F24: Ameh Mathew | G24: ann-INV155
A25: 46205 | B25: Maltina Pet 33cl | C25: 260 | D25: 5000 | E25: =C25*D25 -> 1300000 | F25: Eniola Marketer | G25: ann-INV156
A26: 46205 | B26: 4th Street wine | C26: 1 | D26: 24235 | E26: =C26*D26 -> 24235 | F26: Eniola Marketer | G26: ann-INV156
A27: 46205 | B27: Maltina Pet 50cl | C27: 5 | D27: 8020 | E27: =C27*D27 -> 40100 | F27: Eniola Marketer | G27: ann-INV157
A28: 46205 | B28: Maltina Pet 50cl | C28: 10 | D28: 8020 | E28: =C28*D28 -> 80200 | F28: Eniola Marketer | G28: ann-INV158
A29: 46205 | B29: CLIMAX CAN | C29: 2 | D29: 12885 | E29: =C29*D29 -> 25770 | F29: Mr Lekan Ojifini | G29: ann-INV159
A30: 46205 | B30: ACE BITTERS | C30: 2 | D30: 20655 | E30: =C30*D30 -> 41310 | F30: Mr Lekan Ojifini | G30: ann-INV159
B31: Grand Total | C31: =SUM(C2:C30) -> 488 | D31: =SUM(D2:D30) -> 413025 | E31: =SUM(E2:E30) -> 4229335
E36: =SUM(E2:E11) -> 1065630
E37: =SUM(E13:E16) -> 62070
E38: =+E21+E22 -> 56940 | I38: Customer | J38: Amount_NGN | K38: % of Total Revenue | L38: Gross Profit
I39: Ameh Mathew | J39: =E36+E37+E38+E24 -> 1193520 | K39: =J39/E$31 -> 0.28220039 | L39: %
I40: TD Odiolowo | J40: =E12+E23 -> 103200 | K40: =J40/E$31 -> 0.024400999 | L40: 0.09
I41: Rita SR | J41: =SUM(E17:E20) -> 1421000 | K41: =J41/E$31 -> 0.33598663 | L41: 0
I42: Eniola Marketer | J42: =SUM(E25:E28) -> 1444535 | K42: =J42/E$31 -> 0.34155133
I43: Mr Lekan Ojifini | J43: =E29+E30 -> 67080 | K43: =J43/E$31 -> 0.015860649 | L43: 0.06
I44: Total | J44: =SUM(J39:J43) -> 4229335 | K44: =J44/E$31 -> 1
I47: Invoice No | J47: Amount_NGN | K47: Gross Profit
I48: ann-INV145 | J48: 821130 | K48: 0.01
I49: ann-INV146 | J49: 256500 | K49: 0
I50: ann-INV147 | J50: 86000 | K50: 0
I51: ann-INV148 | J51: 62070 | K51: 0.04
I52: ann-INV152 | J52: 1421000 | K52: 0
I53: ann-INV153 | J53: 56940 | K53: 0.02
I54: ann-INV154 | J54: 17200 | K54: 0
I55: ann-INV155 | J55: 8880 | K55: 0.04
I56: ann-INV156 | J56: 1324235 | K56: -0.04
I57: ann-INV157 | J57: 40100 | K57: 0.04
I58: ann-INV158 | J58: 80200 | K58: 0.04
I59: ann-INV159 | J59: 67080 | K59: 0.06
I60: Total | J60: =SUM(J48:J59) -> 4241335

Sheet July 3rd Sales Report
A1: Date | B1: Product | C1: Cases_Sold | D1: Unit_Price_NGN | E1: Amount_NGN | F1: Customer | G1: Invoice No | I1: Product | J1: Quantity | K1: Revenue | L1: % of Total Revenue | N1: Total Revnue | O1: Total Cases Sold | P1: Total transaction
A2: 46204 | B2: Heineken Bottle 60cl | C2: 280 | D2: 12930 | E2: =C2*D2 -> 3620400 | F2: Abbey Illisan | G2: ann-INV161 | I2: Heineken Bottle 60cl | J2: =SUM(C2+C7+C26+C30) -> 432 | K2: =E2+E7+E26+E30 -> 5577850 | L2: =K2/K$18 -> 0.3611955 | N2: =E32 -> 15442745 | O2: =J18 -> 1474 | P2: =COUNT(I2:I17,J2:J17) -> 16
A3: 46206 | B3: Goldberg 60cl | C3: 210 | D3: 8990 | E3: =C3*D3 -> 1887900 | F3: Abbey Illisan | G3: ann-INV162 | I3: Goldberg 60cl | J3: =C3+C14+C23+C27 -> 252 | K3: =E3+E14+E23+E27 -> 2627755 | L3: =K3/K$18 -> 0.17016113
A4: 46206 | B4: 33 Export 60cl | C4: 140 | D4: 8990 | E4: =C4*D4 -> 1258600 | F4: Abbey Illisan | G4: ann-INV163 | I4: 33 Export 60cl | J4: =C4+C6+C21+C29 -> 296 | K4: =SUM(E4+E6+E21+E29) -> 2664400 | L4: =K4/K$18 -> 0.17253409
A5: 46206 | B5: Gulder Bottle | C5: 84 | D5: 11415 | E5: =C5*D5 -> 958860 | F5: Abbey Illisan | G5: ann-INV164 | I5: Gulder Bottle | J5: =C5+C13+C31 -> 173 | K5: =E5+E13+E31 -> 1968870 | L5: =K5/K$18 -> 0.12749482
A6: 46206 | B6: 33 Export 60cl | C6: 15 | D6: 9200 | E6: =C6*D6 -> 138000 | F6: Ameh Mathew | G6: ann-INV162 | I6: Amstel Bottle | J6: 1 | K6: =E8 -> 14450 | L6: =K6/K$18 -> 0.00093571447
A7: 46206 | B7: Heineken Bottle 60cl | C7: 10 | D7: 13335 | E7: =C7*D7 -> 133350 | F7: Ameh Mathew | G7: ann-INV162 | I7: Fayrouz Can | J7: =C9 -> 1 | K7: =E9 -> 13460 | L7: =K7/K$18 -> 0.0008716067
A8: 46206 | B8: Amstel Bottle | C8: 1 | D8: 14450 | E8: =C8*D8 -> 14450 | F8: Ameh Mathew | G8: ann-INV162 | I8: Turbo King Bottle 60cl | J8: =C10+C22 -> 6 | K8: =E10+E22 -> 53600 | L8: =K8/K$18 -> 0.0034708855
A9: 46206 | B9: Fayrouz Can | C9: 1 | D9: 13460 | E9: =C9*D9 -> 13460 | F9: Ameh Mathew | G9: ann-INV162 | I9: Tiger Bottle | J9: =C11 -> 1 | K9: =E11 -> 15525 | L9: =K9/K$18 -> 0.0010053264
A10: 46206 | B10: Turbo King Bottle 60cl | C10: 5 | D10: 8880 | E10: =C10*D10 -> 44400 | F10: Ameh Mathew | G10: ann-INV162 | I10: Legend 45cl | J10: =C12 -> 1 | K10: =E12 -> 15945 | L10: =K10/K$18 -> 0.0010325237
A11: 46206 | B11: Tiger Bottle | C11: 1 | D11: 15525 | E11: =C11*D11 -> 15525 | F11: Ameh Mathew | G11: ann-INV162 | I11: Heineken Sleek Can | J11: =C24+C28 -> 31 | K11: =E24+E28 -> 525300 | L11: =K11/K$18 -> 0.034015973
A12: 46206 | B12: Legend 45cl | C12: 1 | D12: 15945 | E12: =C12*D12 -> 15945 | F12: Ameh Mathew | G12: ann-INV162 | I12: Desperados Bottle | J12: =C25 -> 2 | K12: =E25 -> 45130 | L12: =K12/K$18 -> 0.0029224079
A13: 46206 | B13: Gulder Bottle | C13: 5 | D13: 11910 | E13: =C13*D13 -> 59550 | F13: Ameh Mathew | G13: ann-INV162 | I13: ACE BITTERS | J13: =C15 -> 30 | K13: =E15 -> 258000 | L13: =K13/K$18 -> 0.016706874
A14: 46206 | B14: ACE BITTERS | C14: 1 | D14: 20655 | E14: 20655 | F14: Ameh Mathew | G14: ann-INV164 | I14: Maltina Pet 33cl | J14: =C16+C19 -> 202 | K14: =E16+E19 -> 1010800 | L14: =K14/K$18 -> 0.065454684
A15: 46206 | B15: Goldberg 60cl | C15: 30 | D15: 8600 | E15: 258000 | F15: TD Odiolowo | G15: ann-INV163 | I15: Heineken Bottle 45cl | J15: =C17 -> 24 | K15: =E17 -> 428160 | L15: =K15/K$18 -> 0.027725641
A16: 46206 | B16: Maltina Pet 33cl | C16: 200 | D16: 5000 | E16: =C16*D16 -> 1000000 | F16: Eniola Marketer | G16: ann-INV167 | I16: Williams Bottle 60cl | J16: =C18 -> 20 | K16: =E18 -> 186900 | L16: =K16/K$18 -> 0.012102771
A17: 46206 | B17: Heineken Bottle 45cl | C17: 24 | D17: 17840 | E17: =C17*D17 -> 428160 | F17: ATW | G17: ann-INV165 | I17: Medium Stout | J17: =C20 -> 2 | K17: =E20 -> 36600 | L17: =K17/K$18 -> 0.002370045
A18: 46206 | B18: Williams Bottle 60cl | C18: 20 | D18: 9345 | E18: =C18*D18 -> 186900 | F18: Tmoney NB | G18: ann-INV166 | I18: Grand Total | J18: =C32 -> 1474 | K18: =SUM(K2:K17) -> 15442745 | L18: =K18/K$18 -> 1
A19: 46206 | B19: Maltina Pet 33cl | C19: 2 | D19: 5400 | E19: =C19*D19 -> 10800 | F19: tomaco | G19: ann-INV169
A20: 46206 | B20: Medium Stout | C20: 2 | D20: 18300 | E20: =C20*D20 -> 36600 | F20: tomaco | G20: ann-INV169
A21: 46206 | B21: 33 Export 60cl | C21: 1 | D21: 9200 | E21: =C21*D21 -> 9200 | F21: tomaco | G21: ann-INV169
A22: 46206 | B22: Turbo King Bottle 60cl | C22: 1 | D22: 9200 | E22: =C22*D22 -> 9200 | F22: tomaco | G22: ann-INV169
A23: 46206 | B23: Goldberg 60cl | C23: 1 | D23: 9200 | E23: =C23*D23 -> 9200 | F23: tomaco | G23: ann-INV169
A24: 46206 | B24: Goldberg 60cl | C24: 1 | D24: 9300 | E24: 9300 | F24: XXIII LOUNGE | G24: ann-INV168
A25: 46206 | B25: Desperados Bottle | C25: 2 | D25: 22565 | E25: =C25*D25 -> 45130 | F25: XXIII LOUNGE | G25: ann-INV168
A26: 46206 | B26: Heineken Bottle 60cl | C26: 2 | D26: 13950 | E26: =C26*D26 -> 27900 | F26: XXIII LOUNGE | G26: ann-INV168
A27: 46206 | B27: Heineken Sleek Can | C27: 40 | D27: 17750 | E27: 710000 | F27: Rita SR | G27: ann-INV171
A28: 46206 | B28: Heineken Sleek Can | C28: 30 | D28: 17200 | E28: =C28*D28 -> 516000 | F28: Rita SR | G28: ann-INV172
A29: 46206 | B29: Goldberg 60cl | C29: 140 | D29: 8990 | E29: =C29*D29 -> 1258600 | F29: WURAOLA | G29: ann-INV160
A30: 46206 | B30: Heineken Bottle 60cl | C30: 140 | D30: 12830 | E30: =C30*D30 -> 1796200 | F30: WURAOLA | G30: ann-INV160
A31: 46206 | B31: Gulder Bottle | C31: 84 | D31: 11315 | E31: =C31*D31 -> 950460 | F31: WURAOLA | G31: ann-INV160 | I31: Customer | J31: Amount_NGN | K31: % of Total Revenue | L31: Gross Profit
B32: Grand Total | C32: =SUM(C2:C31) -> 1474 | D32: =SUM(D2:D31) -> 371670 | E32: =SUM(E2:E31) -> 15442745 | I32: Abbey Illisan | J32: =SUM(E2:E5) -> 7725760 | K32: =J32/E$32 -> 0.50028411
I33: Ameh Mathew | J33: =SUM(E6:E14) -> 455335 | K33: =J33/E$32 -> 0.029485367
I34: TD Odiolowo | J34: =E15 -> 258000 | K34: =J34/E$32 -> 0.016706874
I35: Eniola Marketer | J35: =E16 -> 1000000 | K35: =J35/E$32 -> 0.064755327
I36: ATW | J36: =E17 -> 428160 | K36: =J36/E$32 -> 0.027725641
I37: Tmoney NB | J37: =E18 -> 186900 | K37: =J37/E$32 -> 0.012102771
I38: tomaco | J38: =SUM(E19:E23) -> 75000 | K38: =J38/E$32 -> 0.0048566495
I39: Rita SR | J39: =E27+E28 -> 1226000 | K39: =J39/E$32 -> 0.079390031
I40: XXIII LOUNGE | J40: =SUM(E24:E26) -> 82330 | K40: =J40/E$32 -> 0.0053313061
I41: WURAOLA | J41: =SUM(E29:E31) -> 4005260 | K41: =J41/E$32 -> 0.25936192
I42: Total | J42: =SUM(J32:J41) -> 15442745 | K42: =J42/E$32 -> 1
I45: Invoice No | J45: Amount_NGN | K45: Gross Profit
I46: ann-INV160 | J46: 4026260 | K46: 0.02
I47: ann-INV161 | J47: 8796760 | K47: 0.02
I48: ann-INV162 | J48: 491680 | K48: 0.03
I49: ann-INV163 | J49: 303000 | K49: 0
I50: ann-INV164 | J50: 20655 | K50: 0.07
I51: ann-INV165 | J51: 428160 | K51: 0.03
I52: ann-INV166 | J52: 216900 | K52: 0.03
I53: ann-INV167 | J53: 1000000 | K53: -0.04
I54: ann-INV168 | J54: 89830 | K54: 0.08
I55: ann-INV169 | J55: 75000 | K55: 0.06
I57: ann-INV171 | J57: 710000 | K57: 0.04
I58: ann-INV172 | J58: 516000 | K58: 0.01
I59: Total | J59: =SUM(J46:J58) -> 16674245

Sheet July 4th Sales Report 
A1: Date | B1: Product | C1: Cases_Sold | D1: Unit_Price_NGN | E1: Amount_NGN | F1: Customer | G1: Invoice No | I1: Product | J1: Quantity | K1: Revenue | L1: % of Total Revenue | N1: Total Revnue | O1: Total Cases Sold | P1: Total transaction
A2: 46207 | B2: Trophy | C2: 3 | D2: 9000 | E2: =C2*D2 -> 27000 | F2: Walk in Customer | G2: ann-INV173 | I2: Trophy | J2: =C2+C10 -> 53 | K2: =E2+E10 -> 442000 | L2: =K2/K$13 -> 0.060803905 | N2: =K13 -> 7269270 | O2: =J13 -> 756 | P2: =COUNT(I2:I4,J2:J6) -> 5
A3: 46207 | B3: Maltina Pet 33cl | C3: 30 | D3: 5000 | E3: =C3*D3 -> 150000 | F3: Walk in Customer | G3: ann-INV174 | I3: Maltina Pet 33cl | J3: =C3+C4+C16 -> 283 | K3: =E3+E4+E16 -> 1416500 | L3: =K3/K$13 -> 0.19486138
A4: 46207 | B4: Maltina Pet 33cl | C4: 248 | D4: 5000 | E4: =C4*D4 -> 1240000 | F4: Rita SR | G4: ann-INV175 | I4: Star Bottle 60cl | J4: =C6 -> 5 | K4: =E6 -> 56150 | L4: =K4/K$13 -> 0.0077242969
A5: 46207 | B5: Heineken Sleek Can | C5: 5 | D5: 17200 | E5: =C5*D5 -> 86000 | F5: Rita SR | G5: ann-INV175 | I5: 33 Export Can | J5: =C8 -> 20 | K5: =E8 -> 313100 | L5: =K5/K$13 -> 0.043071725
A6: 46207 | B6: Star Bottle 60cl | C6: 5 | D6: 11230 | E6: =C6*D6 -> 56150 | F6: Rita SR | G6: ann-INV176 | I6: Maltina Can | J6: =C9 -> 30 | K6: =E9 -> 387000 | L6: =K6/K$13 -> 0.053237808
A7: 46207 | B7: Heineken Sleek Can | C7: 5 | D7: 17200 | E7: =C7*D7 -> 86000 | F7: Rita SR | G7: ann-INV176 | I7: Fayrouz Can | J7: =C11 -> 3 | K7: =E11 -> 40380 | L7: =K7/K$13 -> 0.0055548907
A8: 46207 | B8: 33 Export Can | C8: 20 | D8: 15655 | E8: =C8*D8 -> 313100 | F8: Rita SR | G8: ann-INV176 | I8: Heineken Bottle 60cl | J8: =C12 -> 300 | K8: =E12 -> 3849000 | L8: =K8/K$13 -> 0.52948921
A9: 46207 | B9: Maltina Can | C9: 30 | D9: 12900 | E9: =C9*D9 -> 387000 | F9: Rita SR | G9: ann-INV176 | I9: Legend Bottle 60cl | J9: =C13 -> 40 | K9: =E13 -> 436600 | L9: =K9/K$13 -> 0.060061052
A10: 46207 | B10: Trophy | C10: 50 | D10: 8300 | E10: =C10*D10 -> 415000 | F10: Eniola Marketer | G10: ann-INV178 | I10: Maltina Bottle | J10: =C14 -> 10 | K10: =E14 -> 129200 | L10: =K10/K$13 -> 0.017773449
A11: 46207 | B11: Fayrouz Can | C11: 3 | D11: 13460 | E11: =C11*D11 -> 40380 | F11: Jeff SR | G11: ann-INV179 | I11: Goldberg 60cl | J11: =C15 -> 1 | K11: =E15 -> 9500 | L11: =K11/K$13 -> 0.0013068713
A12: 46207 | B12: Heineken Bottle 60cl | C12: 300 | D12: 12830 | E12: =C12*D12 -> 3849000 | F12: Looking Good | G12: ann-INV177 | I12: Heineken Sleek Can | J12: =C5+C7+C17 -> 11 | K12: =E5+E7+E17 -> 189840 | L12: =K12/K$13 -> 0.026115415
A13: 46207 | B13: Legend Bottle 60cl | C13: 40 | D13: 10915 | E13: =C13*D13 -> 436600 | F13: Looking Good | G13: ann-INV177 | I13: Grand Total | J13: =C18 -> 756 | K13: =SUM(K2:K12) -> 7269270 | L13: =SUM(L2:L12) -> 1
A14: 46207 | B14: Maltina Bottle | C14: 10 | D14: 12920 | E14: =C14*D14 -> 129200 | F14: Looking Good | G14: ann-INV177
A15: 46207 | B15: Goldberg 60cl | C15: 1 | D15: 9500 | E15: =C15*D15 -> 9500 | F15: Remilekun | G15: ann-INV180
A16: 46207 | B16: Maltina Pet 33cl | C16: 5 | D16: 5300 | E16: =C16*D16 -> 26500 | F16: Mr Godswill | G16: ann-INV181
A17: 46207 | B17: Heineken Sleek Can | C17: 1 | D17: 17840 | E17: =C17*D17 -> 17840 | F17: Mr Godswill | G17: ann-INV181
B18: Grand Total | C18: =SUM(C2:C17) -> 756 | D18: =SUM(D2:D17) -> 184250 | E18: =SUM(E2:E17) -> 7269270
I20: Customer | J20: Amount_NGN | K20: % of Total Revenue
I21: Walk in Customer 1 | J21: =E2 -> 27000 | K21: =J21/E$18 -> 0.0037142657
I22: Walk in Customer 2 | J22: =E3 -> 150000 | K22: =J22/E$18 -> 0.020634809
I23: Eniola Marketer | J23: =E10 -> 415000 | K23: =J23/E$18 -> 0.057089639
I24: Rita SR | J24: =SUM(E4:E9) -> 2168250 | K24: =J24/E$18 -> 0.29827617
I25: Jeff SR | J25: =E11 -> 40380 | K25: =J25/E$18 -> 0.0055548907
I26: Looking Good | J26: =SUM(E12:E14) -> 4414800 | K26: =J26/E$18 -> 0.60732371
I27: Remilekun | J27: =E15 -> 9500 | K27: =J27/E$18 -> 0.0013068713
I28: Mr Godswill | J28: =E16+E17 -> 44340 | K28: =J28/E$18 -> 0.0060996496
I29: Total | J29: =SUM(J21:J28) -> 7269270 | K29: 1
I32: Invoice_no | J32: Amount_NGN | K32: Gross Profit
I33: ann-INV173 | J33: 27000 | K33: 0.1
I34: ann-INV174 | J34: 150000 | K34: -0.04
I35: ann-INV175 | J35: 1326000 | K35: -0.04
I36: ann-INV176 | J36: 842250 | K36: -0.02
I37: ann-INV177 | J37: 4939800 | K37: 0
I38: ann-INV178 | J38: 495000 | K38: 0.02
I39: ann-INV179 | J39: 40380 | K39: 0.04
I40: ann-INV180 | J40: 9500 | K40: 0.09
I41: ann-INV181 | J41: 44340 | K41: 0.03
I42: Total | J42: =SUM(J33:J41) -> 7874270

Sheet July 5th Sales Report
A1: July 5th, 2026
A2: No sales recorded - store closed (Sunday).

Sheet July 6th Sales Report
A1: Date | B1: Product | C1: Cases_Sold | D1: Unit_Price_NGN | E1: Amount_NGN | F1: Customer | G1: Invoice No | I1: Product | J1: Quantity | K1: Revenue | L1: % of Total Revenue | N1: Total Revnue | O1: Total Cases Sold | P1: Total transaction
A2: 46209 | B2: Maltina Pet 33cl | C2: 330 | D2: 4950 | E2: =C2*D2 -> 1633500 | F2: AZ Marketer | G2: ann-INV183 | I2: Maltina Pet 33cl | J2: =C2+C15+C23 -> 431 | K2: =E2+E15+E23 -> 2133800 | L2: =K2/K$15 -> 0.31123354 | N2: =K15 -> 6855945 | O2: =J15 -> 931 | P2: =COUNT(J2:J14) -> 13
A3: 46209 | B3: Maltina Pet 50cl | C3: 130 | D3: 7800 | E3: =C3*D3 -> 1014000 | F3: AZ Marketer | G3: ann-INV183 | I3: Maltina Pet 50cl | J3: =C3 -> 130 | K3: =E3 -> 1014000 | L3: =K3/K$15 -> 0.14790084
A4: 46209 | B4: Heineken Bottle 60cl | C4: 60 | D4: 13335 | E4: =C4*D4 -> 800100 | F4: Eniola Marketer | G4: ann-INV184 | I4: Heineken Bottle 60cl | J4: =C4+C11+C17+C25 -> 73 | K4: =E4+E11+E17+E25 -> 973455 | L4: =K4/K$15 -> 0.14198699
A5: 46209 | B5: Medium Stout | C5: 1 | D5: 18300 | E5: =C5*D5 -> 18300 | F5: Mrs Oladejo | G5: ann-INV185 | I5: Medium Stout | J5: =C5 -> 1 | K5: =E5 -> 18300 | L5: =K5/K$15 -> 0.0026692163
A6: 46209 | B6: 33 Export 60cl | C6: 30 | D6: 9200 | E6: =C6*D6 -> 276000 | F6: Eniola Marketer | G6: ann-INV186 | I6: 33 Export 60cl | J6: =C6+C10+C18+C21+C29 -> 81 | K6: =E6+E10+E18+E21+E29 -> 740040 | L6: =K6/K$15 -> 0.10794136
A7: 46209 | B7: Goldberg 60cl | C7: 30 | D7: 9200 | E7: =C7*D7 -> 276000 | F7: Eniola Marketer | G7: ann-INV186 | I7: Goldberg 60cl | J7: =C7+C14+C16+C20+C24+C28+C31 -> 175 | K7: =E7+E14+E16+E20+E24+E28+E31 -> 1593800 | L7: =K7/K$15 -> 0.23246978
A8: 46209 | B8: Trophy | C8: 20 | D8: 8300 | E8: =C8*D8 -> 166000 | F8: Eniola Marketer | G8: ann-INV186 | I8: Trophy | J8: =C8 -> 20 | K8: =E8 -> 166000 | L8: =K8/K$15 -> 0.024212563
A9: 46209 | B9: Turbo King Bottle 60cl | C9: 12 | D9: 9200 | E9: =C9*D9 -> 110400 | F9: Eniola Marketer | G9: ann-INV186 | I9: Turbo King Bottle 60cl | J9: =C9+C26+C30 -> 14 | K9: =E9+E26+E30 -> 128780 | L9: =K9/K$15 -> 0.018783698
A10: 46209 | B10: 33 Export 60cl | C10: 21 | D10: 9200 | E10: =C10*D10 -> 193200 | F10: Ameh Mathew | G10: ann-INV187 | I10: Gulder Bottle | J10: =C12 -> 1 | K10: =E12 -> 11910 | L10: =K10/K$15 -> 0.0017371785
A11: 46209 | B11: Heineken Bottle 60cl | C11: 7 | D11: 13335 | E11: =C11*D11 -> 93345 | F11: Ameh Mathew | G11: ann-INV187 | I11: Star Radler 45cl | J11: =C13 -> 1 | K11: =E13 -> 14575 | L11: =K11/K$15 -> 0.0021258922
A12: 46209 | B12: Gulder Bottle | C12: 1 | D12: 11910 | E12: =C12*D12 -> 11910 | F12: Ameh Mathew | G12: ann-INV187 | I12: Maltina Bottle | J12: =C19 -> 1 | K12: =E19 -> 13550 | L12: =K12/K$15 -> 0.0019763869
A13: 46209 | B13: Star Radler 45cl | C13: 1 | D13: 14575 | E13: =C13*D13 -> 14575 | F13: Ameh Mathew | G13: ann-INV187 | I13: STK 33cl | J13: =C22 -> 2 | K13: =E22 -> 26250 | L13: =K13/K$15 -> 0.0038287938
A14: 46209 | B14: Goldberg 60cl | C14: 4 | D14: 8600 | E14: =C14*D14 -> 34400 | F14: TD Odiolowo | G14: ann-INV188 | I14: Desperados Bottle | J14: =C27 -> 1 | K14: =E27 -> 21485 | L14: =K14/K$15 -> 0.0031337766
A15: 46209 | B15: Maltina Pet 33cl | C15: 100 | D15: 4950 | E15: =C15*D15 -> 495000 | F15: AZ Marketer | G15: ann-INV189 | I15: Grand Total | J15: =SUM(J2:J14) -> 931 | K15: =SUM(K2:K14) -> 6855945 | L15: =K15/K$15 -> 1
A16: 46209 | B16: Goldberg 60cl | C16: 4 | D16: 9200 | E16: =C16*D16 -> 36800 | F16: Jeff SR | G16: ann-INV191
A17: 46209 | B17: Heineken Bottle 60cl | C17: 2 | D17: 13335 | E17: =C17*D17 -> 26670 | F17: Jeff SR | G17: ann-INV191 | I17: Customer | J17: Amount_NGN | K17: % of Total Revenue | L17: Gross Profit
A18: 46209 | B18: 33 Export 60cl | C18: 3 | D18: 9200 | E18: =C18*D18 -> 27600 | F18: Jeff SR | G18: ann-INV191 | I18: AZ Marketer | J18: =E2+E3+E15 -> 3142500 | K18: =J18/J$29 -> 0.45836132 | L18: -0.0295
A19: 46209 | B19: Maltina Bottle | C19: 1 | D19: 13550 | E19: =C19*D19 -> 13550 | F19: Jeff SR | G19: ann-INV191 | I19: Eniola Marketer | J19: =E4+E6+E7+E8+E9 -> 1628500 | K19: =J19/J$29 -> 0.23753108 | L19: 0.0377
A20: 46209 | B20: Goldberg 60cl | C20: 70 | D20: 8990 | E20: =C20*D20 -> 629300 | F20: WURAOLA | G20: ann-INV192 | I20: Mrs Oladejo | J20: =E5 -> 18300 | K20: =J20/J$29 -> 0.0026692163 | L20: 0.0628
A21: 46209 | B21: 33 Export 60cl | C21: 26 | D21: 8990 | E21: =C21*D21 -> 233740 | F21: WURAOLA | G21: ann-INV192 | I21: Ameh Mathew | J21: =E10+E11+E12+E13 -> 313030 | K21: =J21/J$29 -> 0.045658184 | L21: 0.0257
A22: 46209 | B22: STK 33cl | C22: 2 | D22: 13125 | E22: =C22*D22 -> 26250 | F22: Mr Godswill | G22: ann-INV193 | I22: TD Odiolowo | J22: =E14 -> 34400 | K22: =J22/J$29 -> 0.0050175432 | L22: -0.0044
A23: 46209 | B23: Maltina Pet 33cl | C23: 1 | D23: 5300 | E23: =C23*D23 -> 5300 | F23: Mr Godswill | G23: ann-INV193 | I23: Jeff SR | J23: =E16+E17+E18+E19 -> 104620 | K23: =J23/J$29 -> 0.015259749 | L23: 0.0392
A24: 46209 | B24: Goldberg 60cl | C24: 64 | D24: 9200 | E24: =C24*D24 -> 588800 | F24: Tmoney NB | G24: ann-INV190 | I24: WURAOLA | J24: =E20+E21 -> 863040 | K24: =J24/J$29 -> 0.12588199 | L24: 0.0286
A25: 46209 | B25: Heineken Bottle 60cl | C25: 4 | D25: 13335 | E25: =C25*D25 -> 53340 | F25: Tmoney NB | G25: ann-INV190 | I25: Mr Godswill | J25: =E22+E23 -> 31550 | K25: =J25/J$29 -> 0.0046018456 | L25: 0.0498
A26: 46209 | B26: Turbo King Bottle 60cl | C26: 1 | D26: 8880 | E26: =C26*D26 -> 8880 | F26: Tmoney NB | G26: ann-INV190 | I26: Tmoney NB | J26: =E24+E25+E26+E27 -> 672505 | K26: =J26/J$29 -> 0.098090781 | L26: 0.0511
A27: 46209 | B27: Desperados Bottle | C27: 1 | D27: 21485 | E27: =C27*D27 -> 21485 | F27: Tmoney NB | G27: ann-INV190 | I27: Walk in Customer | J27: =E28+E29+E30 -> 28500 | K27: =J27/J$29 -> 0.0041569762 | L27: 0.0824
A28: 46209 | B28: Goldberg 60cl | C28: 1 | D28: 9500 | E28: =C28*D28 -> 9500 | F28: Walk in Customer | G28: ann-INV194 | I28: MRS IK. | J28: =E31 -> 19000 | K28: =J28/J$29 -> 0.0027713174 | L28: 0.0908
A29: 46209 | B29: 33 Export 60cl | C29: 1 | D29: 9500 | E29: =C29*D29 -> 9500 | F29: Walk in Customer | G29: ann-INV194 | I29: Total | J29: =SUM(J18:J28) -> 6855945 | K29: =J29/J$29 -> 1
A30: 46209 | B30: Turbo King Bottle 60cl | C30: 1 | D30: 9500 | E30: =C30*D30 -> 9500 | F30: Walk in Customer | G30: ann-INV194
A31: 46209 | B31: Goldberg 60cl | C31: 2 | D31: 9500 | E31: =C31*D31 -> 19000 | F31: MRS IK. | G31: ann-INV195 | I31: Invoice No | J31: Amount_NGN | K31: Gross Profit
B32: Grand Total | C32: =SUM(C2:C31) -> 931 | D32: =SUM(D2:D31) -> 315445 | E32: =SUM(E2:E31) -> 6855945 | I32: ann-INV183 | J32: 2647500 | K32: -0.03
I33: ann-INV184 | J33: 890100 | K33: 0.04
I34: ann-INV185 | J34: 18300 | K34: 0.06
I35: ann-INV186 | J35: 968400 | K35: 0.04
I36: ann-INV187 | J36: 358030 | K36: 0.03
I37: ann-INV188 | J37: 34400 | K37: 0
I38: ann-INV189 | J38: 495000 | K38: -0.05
I39: ann-INV191 | J39: 119620 | K39: 0.04
I40: ann-INV192 | J40: 863040 | K40: 0.03
I41: ann-INV193 | J41: 31550 | K41: 0.05
I42: ann-INV190 | J42: 777505 | K42: 0.05
I43: ann-INV194 | J43: 28500 | K43: 0.08
I44: ann-INV195 | J44: 19000 | K44: 0.09
I45: Total | J45: =SUM(J32:J44) -> 7250945

Sheet July 7th Sales Report
A1: Date | B1: Product | C1: Cases_Sold | D1: Unit_Price_NGN | E1: Amount_NGN | F1: Customer | G1: Invoice No | I1: Product | J1: Quantity | K1: Revenue | L1: % of Total Revenue | N1: Total Revnue | O1: Total Cases Sold | P1: Total transaction
A2: 46210 | B2: Goldberg 60cl | C2: 140 | D2: 8990 | E2: =C2*D2 -> 1258600 | F2: WURAOLA | G2: ann-INV197 | I2: Goldberg 60cl | J2: =C2+C7+C12+C13+C27 -> 403 | K2: =E2+E7+E12+E13+E27 -> 3540800 | L2: =K2/K$16 -> 0.25325048 | N2: =K16 -> 13981415 | O2: =J16 -> 1685 | P2: =COUNT(J2:J15) -> 14
A3: 46210 | B3: 33 Export 60cl | C3: 44 | D3: 8990 | E3: =C3*D3 -> 395560 | F3: WURAOLA | G3: ann-INV197 | I3: 33 Export 60cl | J3: =C3+C11+C15+C26+C32 -> 224 | K3: =E3+E11+E15+E26+E32 -> 2032510 | L3: =K3/K$16 -> 0.14537227
A4: 46210 | B4: Maltina Pet 33cl | C4: 120 | D4: 5100 | E4: =C4*D4 -> 612000 | F4: DESOLA STORE | G4: ann-INV196 | I4: Maltina Pet 33cl | J4: =C4+C5+C17+C22+C38 -> 603 | K4: =E4+E5+E17+E22+E38 -> 3011800 | L4: =K4/K$16 -> 0.21541453
A5: 46210 | B5: Maltina Pet 33cl | C5: 250 | D5: 4950 | E5: =C5*D5 -> 1237500 | F5: Demola SR | G5: ann-INV198 | I5: Heineken Sleek Can | J5: =C6+C20 -> 11 | K5: =E6+E20 -> 189100 | L5: =K5/K$16 -> 0.013525097
A6: 46210 | B6: Heineken Sleek Can | C6: 10 | D6: 17200 | E6: =C6*D6 -> 172000 | F6: Rita SR | G6: ann-INV199 | I6: Heineken Bottle 60cl | J6: =C8+C10+C24+C34 -> 262 | K6: =E8+E10+E24+E34 -> 3394545 | L6: =K6/K$16 -> 0.2427898
A7: 46210 | B7: Goldberg 60cl | C7: 25 | D7: 9200 | E7: =C7*D7 -> 230000 | F7: Eniola Marketer | G7: ann-INV200 | I7: Turbo King Bottle 60cl | J7: =C9+C16+C25+C28+C36 -> 67 | K7: =E9+E16+E25+E28+E36 -> 594160 | L7: =K7/K$16 -> 0.042496414
A8: 46210 | B8: Heineken Bottle 60cl | C8: 17 | D8: 13335 | E8: =C8*D8 -> 226695 | F8: Eniola Marketer | G8: ann-INV200 | I8: Star Radler 45cl | J8: =C14 -> 2 | K8: =E14 -> 29150 | L8: =K8/K$16 -> 0.0020849106
A9: 46210 | B9: Turbo King Bottle 60cl | C9: 10 | D9: 9200 | E9: =C9*D9 -> 92000 | F9: Eniola Marketer | G9: ann-INV200 | I9: Maltina Pet 50cl | J9: =C18+C23+C37 -> 55 | K9: =E18+E23+E37 -> 441100 | L9: =K9/K$16 -> 0.031549024
A10: 46210 | B10: Heineken Bottle 60cl | C10: 210 | D10: 12930 | E10: =C10*D10 -> 2715300 | F10: Rukky bee | G10: ann-INV201 | I10: Gulder Bottle | J10: =C19+C31 -> 23 | K10: =E19+E31 -> 264030 | L10: =K10/K$16 -> 0.018884355
A11: 46210 | B11: 33 Export 60cl | C11: 140 | D11: 9090 | E11: =C11*D11 -> 1272600 | F11: Rukky bee | G11: ann-INV201 | I11: Goldberg Can 50cl | J11: =C21 -> 1 | K11: =E21 -> 16145 | L11: =K11/K$16 -> 0.0011547472
A12: 46210 | B12: Goldberg 60cl | C12: 11 | D12: 8600 | E12: =C12*D12 -> 94600 | F12: TD Odiolowo | G12: ann-INV202 | I12: Desperados Bottle | J12: =C29 -> 6 | K12: =E29 -> 123240 | L12: =K12/K$16 -> 0.0088145585
A13: 46210 | B13: Goldberg 60cl | C13: 27 | D13: 8800 | E13: =C13*D13 -> 237600 | F13: Ameh Mathew | G13: ann-INV203 | I13: Legend Bottle 60cl | J13: =C30 -> 15 | K13: =E30 -> 172200 | L13: =K13/K$16 -> 0.01231635
A14: 46210 | B14: Star Radler 45cl | C14: 2 | D14: 14575 | E14: =C14*D14 -> 29150 | F14: Ameh Mathew | G14: ann-INV203 | I14: Maltina Bottle | J14: =C33 -> 10 | K14: =E33 -> 130200 | L14: =K14/K$16 -> 0.0093123622
A15: 46210 | B15: 33 Export 60cl | C15: 5 | D15: 9200 | E15: =C15*D15 -> 46000 | F15: Ameh Mathew | G15: ann-INV203 | I15: Goldberg Black 45cl | J15: =C35 -> 3 | K15: =E35 -> 42435 | L15: =K15/K$16 -> 0.0030351005
A16: 46210 | B16: Turbo King Bottle 60cl | C16: 5 | D16: 8880 | E16: =C16*D16 -> 44400 | F16: Ameh Mathew | G16: ann-INV203 | I16: Grand Total | J16: =SUM(J2:J15) -> 1685 | K16: =SUM(K2:K15) -> 13981415 | L16: =K16/K$16 -> 1
A17: 46210 | B17: Maltina Pet 33cl | C17: 30 | D17: 4900 | E17: =C17*D17 -> 147000 | F17: Ameh Mathew | G17: ann-INV203
A18: 46210 | B18: Maltina Pet 50cl | C18: 15 | D18: 8020 | E18: =C18*D18 -> 120300 | F18: Ameh Mathew | G18: ann-INV203 | I18: Customer | J18: Amount_NGN | K18: % of Total Revenue | L18: Gross Profit
A19: 46210 | B19: Gulder Bottle | C19: 3 | D19: 11910 | E19: =C19*D19 -> 35730 | F19: Ameh Mathew | G19: ann-INV203 | I19: WURAOLA | J19: =E2+E3 -> 1654160 | K19: =J19/J$32 -> 0.11831134 | L19: 0.0256
A20: 46210 | B20: Heineken Sleek Can | C20: 1 | D20: 17100 | E20: =C20*D20 -> 17100 | F20: Ameh Mathew | G20: ann-INV203 | I20: DESOLA STORE | J20: =E4 -> 612000 | K20: =J20/J$32 -> 0.043772394 | L20: -0.0196
A21: 46210 | B21: Goldberg Can 50cl | C21: 1 | D21: 16145 | E21: =C21*D21 -> 16145 | F21: Ameh Mathew | G21: ann-INV203 | I21: Demola SR | J21: =E5 -> 1237500 | K21: =J21/J$32 -> 0.088510355 | L21: -0.0505
A22: 46210 | B22: Maltina Pet 33cl | C22: 202 | D22: 5000 | E22: =C22*D22 -> 1010000 | F22: Mr Lekan Ojifini | G22: ann-INV204 | I22: Rita SR | J22: =E6 -> 172000 | K22: =J22/J$32 -> 0.012302045 | L22: 0.0058
A23: 46210 | B23: Maltina Pet 50cl | C23: 20 | D23: 8020 | E23: =C23*D23 -> 160400 | F23: Mr Lekan Ojifini | G23: ann-INV204 | I23: Eniola Marketer | J23: =E7+E8+E9 -> 548695 | K23: =J23/J$32 -> 0.039244597 | L23: 0.0491
A24: 46210 | B24: Heineken Bottle 60cl | C24: 30 | D24: 12930 | E24: =C24*D24 -> 387900 | F24: Tmoney NB | G24: ann-INV205 | I24: Rukky bee | J24: =E10+E11 -> 3987900 | K24: =J24/J$32 -> 0.28522864 | L24: 0.0116
A25: 46210 | B25: Turbo King Bottle 60cl | C25: 10 | D25: 8800 | E25: =C25*D25 -> 88000 | F25: Tmoney NB | G25: ann-INV205 | I25: TD Odiolowo | J25: =E12 -> 94600 | K25: =J25/J$32 -> 0.0067661249 | L25: -0.0037
A26: 46210 | B26: 33 Export 60cl | C26: 20 | D26: 9100 | E26: =C26*D26 -> 182000 | F26: Tmoney NB | G26: ann-INV205 | I26: Ameh Mathew | J26: =E13+E14+E15+E16+E17+E18+E19+E20+E21+E36 -> 711185 | K26: =J26/J$32 -> 0.050866454 | L26: 0.0088
A27: 46210 | B27: Goldberg 60cl | C27: 200 | D27: 8600 | E27: =C27*D27 -> 1720000 | F27: Emmycee | G27: ann-INV206 | I27: Mr Lekan Ojifini | J27: =E22+E23 -> 1170400 | K27: =J27/J$32 -> 0.083711127 | L27: -0.0288
A28: 46210 | B28: Turbo King Bottle 60cl | C28: 40 | D28: 8800 | E28: =C28*D28 -> 352000 | F28: Emmycee | G28: ann-INV206 | I28: Tmoney NB | J28: =E24+E25+E26 -> 657900 | K28: =J28/J$32 -> 0.047055323 | L28: 0.0139
A29: 46210 | B29: Desperados Bottle | C29: 6 | D29: 20540 | E29: =C29*D29 -> 123240 | F29: Emmycee | G29: ann-INV206 | I29: Emmycee | J29: =E27+E28+E29+E30+E31+E32+E33+E34+E35 -> 2969375 | K29: =J29/J$32 -> 0.21238015 | L29: 0.0492
A30: 46210 | B30: Legend Bottle 60cl | C30: 15 | D30: 11480 | E30: =C30*D30 -> 172200 | F30: Emmycee | G30: ann-INV206 | I30: Jeff SR | J30: =E37 -> 160400 | K30: =J30/J$32 -> 0.011472372 | L30: 0.0418
A31: 46210 | B31: Gulder Bottle | C31: 20 | D31: 11415 | E31: =C31*D31 -> 228300 | F31: Emmycee | G31: ann-INV206 | I31: Walk in Customer | J31: =E38 -> 5300 | K31: =J31/J$32 -> 0.00037907465 | L31: 0.0189
A32: 46210 | B32: 33 Export 60cl | C32: 15 | D32: 9090 | E32: =C32*D32 -> 136350 | F32: Emmycee | G32: ann-INV206 | I32: Total | J32: =SUM(J19:J31) -> 13981415 | K32: =J32/J$32 -> 1
A33: 46210 | B33: Maltina Bottle | C33: 10 | D33: 13020 | E33: =C33*D33 -> 130200 | F33: Emmycee | G33: ann-INV206
A34: 46210 | B34: Heineken Bottle 60cl | C34: 5 | D34: 12930 | E34: =C34*D34 -> 64650 | F34: Emmycee | G34: ann-INV206 | I34: Invoice No | J34: Amount_NGN | K34: Gross Profit
A35: 46210 | B35: Goldberg Black 45cl | C35: 3 | D35: 14145 | E35: =C35*D35 -> 42435 | F35: Emmycee | G35: ann-INV206 | I35: ann-INV197 | J35: 1930160 | K35: 0.03
A36: 46210 | B36: Turbo King Bottle 60cl | C36: 2 | D36: 8880 | E36: =C36*D36 -> 17760 | F36: Ameh Mathew | G36: ann-INV207 | I36: ann-INV196 | J36: 612000 | K36: -0.02
A37: 46210 | B37: Maltina Pet 50cl | C37: 20 | D37: 8020 | E37: =C37*D37 -> 160400 | F37: Jeff SR | G37: ann-INV208 | I37: ann-INV198 | J37: 1237500 | K37: -0.05
A38: 46210 | B38: Maltina Pet 33cl | C38: 1 | D38: 5300 | E38: =C38*D38 -> 5300 | F38: Walk in Customer | G38: ann-INV209 | I38: ann-INV199 | J38: 172000 | K38: 0.01
B39: Grand Total | C39: =SUM(C2:C38) -> 1685 | D39: =SUM(D2:D38) -> 383185 | E39: =SUM(E2:E38) -> 13981415 | I39: ann-INV200 | J39: 626695 | K39: 0.05
I40: ann-INV201 | J40: 4512900 | K40: 0.01
I41: ann-INV202 | J41: 111100 | K41: 0
I42: ann-INV203 | J42: 756425 | K42: 0.01
I43: ann-INV204 | J43: 1170400 | K43: -0.03
I44: ann-INV205 | J44: 747900 | K44: 0.01
I45: ann-INV206 | J45: 3597375 | K45: 0.05
I46: ann-INV207 | J46: 17760 | K46: 0.04
I47: ann-INV208 | J47: 160400 | K47: 0.04
I48: ann-INV209 | J48: 5300 | K48: 0.02
I49: Total | J49: =SUM(J35:J48) -> 15657915

Sheet July 8th Sales Report
A1: Date | B1: Product | C1: Cases_Sold | D1: Unit_Price_NGN | E1: Amount_NGN | F1: Customer | G1: Invoice No | I1: Product | J1: Quantity | K1: Revenue | L1: % of Total Revenue | N1: Total Revnue | O1: Total Cases Sold | P1: Total transaction
A2: 46211 | B2: Heineken Bottle 60cl | C2: 5 | D2: 13335 | E2: =C2*D2 -> 66675 | F2: Amandla | G2: ann-INV210 | I2: Heineken Bottle 60cl | J2: =C2+C12+C16+C24+C37 -> 137 | K2: =E2+E12+E16+E24+E37 -> 1774245 | L2: =K2/K$22 -> 0.22243068 | N2: =K22 -> 7976620 | O2: =J22 -> 844 | P2: =COUNT(J2:J21) -> 20
A3: 46211 | B3: Desperados Bottle | C3: 5 | D3: 21485 | E3: =C3*D3 -> 107425 | F3: Amandla | G3: ann-INV210 | I3: Desperados Bottle | J3: =C3 -> 5 | K3: =E3 -> 107425 | L3: =K3/K$22 -> 0.013467484
A4: 46211 | B4: Gulder Bottle | C4: 5 | D4: 11910 | E4: =C4*D4 -> 59550 | F4: Amandla | G4: ann-INV210 | I4: Gulder Bottle | J4: =C4+C14+C25+C38 -> 19 | K4: =E4+E14+E25+E38 -> 226290 | L4: =K4/K$22 -> 0.028369159
A5: 46211 | B5: Maltina Bottle | C5: 5 | D5: 13550 | E5: =C5*D5 -> 67750 | F5: Amandla | G5: ann-INV210 | I5: Maltina Bottle | J5: =C5+C27 -> 10 | K5: =E5+E27 -> 135500 | L5: =K5/K$22 -> 0.016987145
A6: 46211 | B6: Fayrouz Bottle | C6: 2 | D6: 10315 | E6: =C6*D6 -> 20630 | F6: Ameh Mathew | G6: ann-INV212 | I6: Fayrouz Bottle | J6: =C6+C31 -> 4 | K6: =E6+E31 -> 41260 | L6: =K6/K$22 -> 0.005172617
A7: 46211 | B7: Tiger Bottle | C7: 1 | D7: 15525 | E7: =C7*D7 -> 15525 | F7: Ameh Mathew | G7: ann-INV212 | I7: Tiger Bottle | J7: =C7+C41 -> 7 | K7: =E7+E41 -> 108675 | L7: =K7/K$22 -> 0.013624192
A8: 46211 | B8: Amstel Bottle | C8: 1 | D8: 14450 | E8: =C8*D8 -> 14450 | F8: Ameh Mathew | G8: ann-INV212 | I8: Amstel Bottle | J8: =C8+C26+C34 -> 5 | K8: =E8+E26+E34 -> 72250 | L8: =K8/K$22 -> 0.0090577212
A9: 46211 | B9: Legend Bottle 60cl | C9: 2 | D9: 11480 | E9: =C9*D9 -> 22960 | F9: Ameh Mathew | G9: ann-INV212 | I9: Legend Bottle 60cl | J9: =C9 -> 2 | K9: =E9 -> 22960 | L9: =K9/K$22 -> 0.0028784122
A10: 46211 | B10: Heineken Sleek Can | C10: 20 | D10: 17100 | E10: =C10*D10 -> 342000 | F10: Ameh Mathew | G10: ann-INV211 | I10: Heineken Sleek Can | J10: =C10+C29 -> 25 | K10: =E10+E29 -> 431225 | L10: =K10/K$22 -> 0.054061119
A11: 46211 | B11: Goldberg Can 50cl | C11: 25 | D11: 16145 | E11: =C11*D11 -> 403625 | F11: Ameh Mathew | G11: ann-INV211 | I11: Goldberg Can 50cl | J11: =C11 -> 25 | K11: =E11 -> 403625 | L11: =K11/K$22 -> 0.050601006
A12: 46211 | B12: Heineken Bottle 60cl | C12: 10 | D12: 12930 | E12: =C12*D12 -> 129300 | F12: Delayers | G12: ann-INV213 | I12: 33 Export 60cl | J12: =C13 -> 4 | K12: =E13 -> 36800 | L12: =K12/K$22 -> 0.0046134829
A13: 46211 | B13: 33 Export 60cl | C13: 4 | D13: 9200 | E13: =C13*D13 -> 36800 | F13: Solomon | G13: ann-INV214 | I13: Turbo King Bottle 60cl | J13: =C15+C22+C36 -> 55 | K13: =E15+E22+E36 -> 490000 | L13: =K13/K$22 -> 0.061429528
A14: 46211 | B14: Gulder Bottle | C14: 2 | D14: 11910 | E14: =C14*D14 -> 23820 | F14: Solomon | G14: ann-INV214 | I14: Maltina Pet 50cl | J14: =C17+C20 -> 20 | K14: =E17+E20 -> 160400 | L14: =K14/K$22 -> 0.020108768
A15: 46211 | B15: Turbo King Bottle 60cl | C15: 4 | D15: 9200 | E15: =C15*D15 -> 36800 | F15: Solomon | G15: ann-INV214 | I15: Goldberg 60cl | J15: =C18+C21+C30+C35 -> 310 | K15: =E18+E21+E30+E35 -> 2672300 | L15: =K15/K$22 -> 0.33501659
A16: 46211 | B16: Heineken Bottle 60cl | C16: 2 | D16: 13335 | E16: =C16*D16 -> 26670 | F16: Solomon | G16: ann-INV214 | I16: Maltina Pet 33cl | J16: =C19+C28+C43 -> 190 | K16: =E19+E28+E43 -> 950000 | L16: =K16/K$22 -> 0.11909806
A17: 46211 | B17: Maltina Pet 50cl | C17: 10 | D17: 8020 | E17: =C17*D17 -> 80200 | F17: Solomon | G17: ann-INV214 | I17: STK 33cl | J17: =C23 -> 1 | K17: =E23 -> 13125 | L17: =K17/K$22 -> 0.0016454338
A18: 46211 | B18: Goldberg 60cl | C18: 1 | D18: 9500 | E18: =C18*D18 -> 9500 | F18: Remilekun | G18: ann-INV215 | I18: Star Bottle 60cl | J18: =C32 -> 3 | K18: =E32 -> 34800 | L18: =K18/K$22 -> 0.0043627501
A19: 46211 | B19: Maltina Pet 33cl | C19: 30 | D19: 5000 | E19: =C19*D19 -> 150000 | F19: Ahmed SR | G19: ann-INV216 | I19: Goldberg Black 45cl | J19: =C33+C40 -> 7 | K19: =E33+E40 -> 99015 | L19: =K19/K$22 -> 0.012413152
A20: 46211 | B20: Maltina Pet 50cl | C20: 10 | D20: 8020 | E20: =C20*D20 -> 80200 | F20: Ahmed SR | G20: ann-INV216 | I20: Williams Bottle 60cl | J20: =C39 -> 10 | K20: =E39 -> 93450 | L20: =K20/K$22 -> 0.011715489
A21: 46211 | B21: Goldberg 60cl | C21: 4 | D21: 9200 | E21: =C21*D21 -> 36800 | F21: Walk in Customer | G21: ann-INV218 | I21: ACE BITTERS | J21: =C42 -> 5 | K21: =E42 -> 103275 | L21: =K21/K$22 -> 0.012947213
A22: 46211 | B22: Turbo King Bottle 60cl | C22: 1 | D22: 9200 | E22: =C22*D22 -> 9200 | F22: Walk in Customer | G22: ann-INV218 | I22: Grand Total | J22: =SUM(J2:J21) -> 844 | K22: =SUM(K2:K21) -> 7976620 | L22: =K22/K$22 -> 1
A23: 46211 | B23: STK 33cl | C23: 1 | D23: 13125 | E23: =C23*D23 -> 13125 | F23: Mr Godswill | G23: ann-INV219
A24: 46211 | B24: Heineken Bottle 60cl | C24: 60 | D24: 12930 | E24: =C24*D24 -> 775800 | F24: Tmoney NB | G24: ann-INV220 | I24: Customer | J24: Amount_NGN | K24: % of Total Revenue | L24: Gross Profit
A25: 46211 | B25: Gulder Bottle | C25: 2 | D25: 11910 | E25: =C25*D25 -> 23820 | F25: Tmoney NB | G25: ann-INV220 | I25: Amandla | J25: =E2+E3+E4+E5 -> 301400 | K25: =J25/J$39 -> 0.037785428 | L25: 0.1058
A26: 46211 | B26: Amstel Bottle | C26: 3 | D26: 14450 | E26: =C26*D26 -> 43350 | F26: Tmoney NB | G26: ann-INV220 | I26: Ameh Mathew | J26: =E6+E7+E8+E9+E10+E11 -> 819190 | K26: =J26/J$39 -> 0.10269889 | L26: 0.0331
A27: 46211 | B27: Maltina Bottle | C27: 5 | D27: 13550 | E27: =C27*D27 -> 67750 | F27: Tmoney NB | G27: ann-INV220 | I27: Delayers | J27: =E12 -> 129300 | K27: =J27/J$39 -> 0.016209873 | L27: 0.137
A28: 46211 | B28: Maltina Pet 33cl | C28: 150 | D28: 5000 | E28: =C28*D28 -> 750000 | F28: Eniola Marketer | G28: ann-INV222 | I28: Solomon | J28: =E13+E14+E15+E16+E17 -> 204290 | K28: =J28/J$39 -> 0.025611098 | L28: 0.0706
A29: 46211 | B29: Heineken Sleek Can | C29: 5 | D29: 17845 | E29: =C29*D29 -> 89225 | F29: Eniola Marketer | G29: ann-INV222 | I29: Remilekun | J29: =E18 -> 9500 | K29: =J29/J$39 -> 0.0011909806 | L29: 0.0908
A30: 46211 | B30: Goldberg 60cl | C30: 5 | D30: 9200 | E30: =C30*D30 -> 46000 | F30: Ola SR | G30: ann-INV221 | I30: Ahmed SR | J30: =E19+E20+E43 -> 280200 | K30: =J30/J$39 -> 0.035127661 | L30: -0.0166
A31: 46211 | B31: Fayrouz Bottle | C31: 2 | D31: 10315 | E31: =C31*D31 -> 20630 | F31: Ola SR | G31: ann-INV221 | I31: Walk in Customer | J31: =E21+E22 -> 46000 | K31: =J31/J$39 -> 0.0057668536 | L31: 0.0805
A32: 46211 | B32: Star Bottle 60cl | C32: 3 | D32: 11600 | E32: =C32*D32 -> 34800 | F32: Ola SR | G32: ann-INV221 | I32: Mr Godswill | J32: =E23 -> 13125 | K32: =J32/J$39 -> 0.0016454338 | L32: 0.0817
A33: 46211 | B33: Goldberg Black 45cl | C33: 2 | D33: 14145 | E33: =C33*D33 -> 28290 | F33: Ola SR | G33: ann-INV221 | I33: Tmoney NB | J33: =E24+E25+E26+E27 -> 910720 | K33: =J33/J$39 -> 0.11417367 | L33: 0.1259
A34: 46211 | B34: Amstel Bottle | C34: 1 | D34: 14450 | E34: =C34*D34 -> 14450 | F34: Ola SR | G34: ann-INV221 | I34: Eniola Marketer | J34: =E28+E29 -> 839225 | K34: =J34/J$39 -> 0.1052106 | L34: -0.0313
A35: 46211 | B35: Goldberg 60cl | C35: 300 | D35: 8600 | E35: =C35*D35 -> 2580000 | F35: Mama Oyin Mowe | G35: ann-INV223 | I35: Ola SR | J35: =E30+E31+E32+E33+E34 -> 144170 | K35: =J35/J$39 -> 0.018074071 | L35: 0.0646
A36: 46211 | B36: Turbo King Bottle 60cl | C36: 50 | D36: 8880 | E36: =C36*D36 -> 444000 | F36: Mama Oyin Mowe | G36: ann-INV223 | I36: Mama Oyin Mowe | J36: =E35+E36 -> 3024000 | K36: =J36/J$39 -> 0.37910794 | L36: 0.0487
A37: 46211 | B37: Heineken Bottle 60cl | C37: 60 | D37: 12930 | E37: =C37*D37 -> 775800 | F37: Mr Musefiu | G37: ann-INV224 | I37: Mr Musefiu | J37: =E37 -> 775800 | K37: =J37/J$39 -> 0.09725924 | L37: 0.0142
A38: 46211 | B38: Gulder Bottle | C38: 10 | D38: 11910 | E38: =C38*D38 -> 119100 | F38: Mr Lekan Ojifini | G38: ann-INV227 | I38: Mr Lekan Ojifini | J38: =E38+E39+E40+E41+E42 -> 479700 | K38: =J38/J$39 -> 0.060138254 | L38: 0.0609
A39: 46211 | B39: Williams Bottle 60cl | C39: 10 | D39: 9345 | E39: =C39*D39 -> 93450 | F39: Mr Lekan Ojifini | G39: ann-INV227 | I39: Total | J39: =SUM(J25:J38) -> 7976620 | K39: =J39/J$39 -> 1
A40: 46211 | B40: Goldberg Black 45cl | C40: 5 | D40: 14145 | E40: =C40*D40 -> 70725 | F40: Mr Lekan Ojifini | G40: ann-INV227
A41: 46211 | B41: Tiger Bottle | C41: 6 | D41: 15525 | E41: =C41*D41 -> 93150 | F41: Mr Lekan Ojifini | G41: ann-INV227 | I41: Invoice No | J41: Amount_NGN | K41: Gross Profit
A42: 46211 | B42: ACE BITTERS | C42: 5 | D42: 20655 | E42: =C42*D42 -> 103275 | F42: Mr Lekan Ojifini | G42: ann-INV227 | I42: ann-INV210 | J42: 339400 | K42: 0.11
A43: 46211 | B43: Maltina Pet 33cl | C43: 10 | D43: 5000 | E43: =C43*D43 -> 50000 | F43: Ahmed SR | G43: ann-INV228 | I43: ann-INV212 | J43: 84365 | K43: 0.06
B44: Grand Total | C44: =SUM(C2:C43) -> 844 | D44: =SUM(D2:D43) -> 506320 | E44: =SUM(E2:E43) -> 7976620 | I44: ann-INV211 | J44: 745625 | K44: 0.03
I45: ann-INV213 | J45: 149300 | K45: 0.14
I46: ann-INV214 | J46: 226290 | K46: 0.07
I47: ann-INV215 | J47: 9500 | K47: 0.09
I48: ann-INV216 | J48: 230200 | K48: -0.01
I49: ann-INV218 | J49: 55000 | K49: 0.08
I50: ann-INV219 | J50: 15125 | K50: 0.08
I51: ann-INV220 | J51: 1048720 | K51: 0.13
I52: ann-INV222 | J52: 839225 | K52: -0.03
I53: ann-INV221 | J53: 167570 | K53: 0.06
I54: ann-INV223 | J54: 3724000 | K54: 0.05
I55: ann-INV224 | J55: 775800 | K55: 0.01
I56: ann-INV227 | J56: 535500 | K56: 0.06
I57: ann-INV228 | J57: 50000 | K57: -0.04
I58: Total | J58: =SUM(J42:J57) -> 8995620

Sheet July 9th Sales Report
A1: Date | B1: Product | C1: Cases_Sold | D1: Unit_Price_NGN | E1: Amount_NGN | F1: Customer | G1: Invoice No | I1: Product | J1: Quantity | K1: Revenue | L1: % of Total Revenue | N1: Total Revnue | O1: Total Cases Sold | P1: Total transaction
A2: 46212 | B2: Heineken Bottle 60cl | C2: 60 | D2: 12930 | E2: =C2*D2 -> 775800 | F2: Delayers | G2: ann-INV229 | I2: Heineken Bottle 60cl | J2: =C2+C36+C42+C46 -> 69 | K2: =E2+E36+E42+E46 -> 895815 | L2: =K2/K$24 -> 0.28770806 | N2: =K24 -> 3113625 | O2: =J24 -> 236 | P2: =COUNT(J2:J23) -> 22
A3: 46212 | B3: Desperados Can | C3: 10 | D3: 21695 | E3: =C3*D3 -> 216950 | F3: Ameh Mathew | G3: ann-INV230 | I3: Desperados Can | J3: =C3 -> 10 | K3: =E3 -> 216950 | L3: =K3/K$24 -> 0.069677627
A4: 46212 | B4: Amstel Bottle | C4: 2 | D4: 14450 | E4: =C4*D4 -> 28900 | F4: Rita SR | G4: ann-INV231 | I4: Amstel Bottle | J4: =C4+C41 -> 3 | K4: =E4+E41 -> 43350 | L4: =K4/K$24 -> 0.013922679
A5: 46212 | B5: Fayrouz Bottle | C5: 2 | D5: 10315 | E5: =C5*D5 -> 20630 | F5: Rita SR | G5: ann-INV231 | I5: Fayrouz Bottle | J5: =C5 -> 2 | K5: =E5 -> 20630 | L5: =K5/K$24 -> 0.0066257176
A6: 46212 | B6: Fayrouz Can | C6: 3 | D6: 13350 | E6: =C6*D6 -> 40050 | F6: Rita SR | G6: ann-INV231 | I6: Fayrouz Can | J6: =C6+C38 -> 4 | K6: =E6+E38 -> 53510 | L6: =K6/K$24 -> 0.017185756
A7: 46212 | B7: ACE BITTERS | C7: 3 | D7: 20655 | E7: =C7*D7 -> 61965 | F7: Rita SR | G7: ann-INV231 | I7: ACE BITTERS | J7: =C7 -> 3 | K7: =E7 -> 61965 | L7: =K7/K$24 -> 0.019901241
A8: 46212 | B8: Gulder Bottle | C8: 10 | D8: 11910 | E8: =C8*D8 -> 119100 | F8: Rita SR | G8: ann-INV231 | I8: Gulder Bottle | J8: =C8+C15+C23+C29+C35+C43 -> 24 | K8: =E8+E15+E23+E29+E35+E43 -> 285840 | L8: =K8/K$24 -> 0.091802963
A9: 46212 | B9: Tiger Bottle | C9: 4 | D9: 15525 | E9: =C9*D9 -> 62100 | F9: Rita SR | G9: ann-INV231 | I9: Tiger Bottle | J9: =C9+C17+C25+C30+C34 -> 11 | K9: =E9+E17+E25+E30+E34 -> 170775 | L9: =K9/K$24 -> 0.054847645
A10: 46212 | B10: 33 Export 60cl | C10: 2 | D10: 9200 | E10: =C10*D10 -> 18400 | F10: Rita SR | G10: ann-INV231 | I10: 33 Export 60cl | J10: =C10+C26+C32+C45 -> 15 | K10: =E10+E26+E32+E45 -> 138000 | L10: =K10/K$24 -> 0.04432133
A11: 46212 | B11: Maltina Pet 50cl | C11: 30 | D11: 8020 | E11: =C11*D11 -> 240600 | F11: Rita SR | G11: ann-INV231 | I11: Maltina Pet 50cl | J11: =C11 -> 30 | K11: =E11 -> 240600 | L11: =K11/K$24 -> 0.077273275
A12: 46212 | B12: Heineken Can 50cl | C12: 20 | D12: 23770 | E12: =C12*D12 -> 475400 | F12: Rita SR | G12: ann-INV231 | I12: Heineken Can 50cl | J12: =C12 -> 20 | K12: =E12 -> 475400 | L12: =K12/K$24 -> 0.15268377
A13: 46212 | B13: Williams Bottle 60cl | C13: 2 | D13: 9345 | E13: =C13*D13 -> 18690 | F13: Rita SR | G13: ann-INV231 | I13: Williams Bottle 60cl | J13: =C13+C16+C24+C28 -> 9 | K13: =E13+E16+E24+E28 -> 84105 | L13: =K13/K$24 -> 0.027011923
A14: 46212 | B14: Legend Can 44cl | C14: 5 | D14: 21170 | E14: =C14*D14 -> 105850 | F14: Rita SR | G14: ann-INV231 | I14: Legend Can 44cl | J14: =C14 -> 5 | K14: =E14 -> 105850 | L14: =K14/K$24 -> 0.033995745
A15: 46212 | B15: Gulder Bottle | C15: 3 | D15: 11910 | E15: =C15*D15 -> 35730 | F15: Ahmed SR | G15: ann-INV232 | I15: Turbo King Bottle 60cl | J15: =C18+C37+C44 -> 6 | K15: =E18+E37+E44 -> 53280 | L15: =K15/K$24 -> 0.017111887
A16: 46212 | B16: Williams Bottle 60cl | C16: 3 | D16: 9345 | E16: =C16*D16 -> 28035 | F16: Ahmed SR | G16: ann-INV232 | I16: Trophy | J16: =C19+C50 -> 5 | K16: =E19+E50 -> 43000 | L16: =K16/K$24 -> 0.013810269
A17: 46212 | B17: Tiger Bottle | C17: 2 | D17: 15525 | E17: =C17*D17 -> 31050 | F17: Ahmed SR | G17: ann-INV232 | I17: Goldberg 60cl | J17: =C20+C27+C31+C47+C49 -> 11 | K17: =E20+E27+E31+E47+E49 -> 98700 | L17: =K17/K$24 -> 0.031699386
A18: 46212 | B18: Turbo King Bottle 60cl | C18: 3 | D18: 8880 | E18: =C18*D18 -> 26640 | F18: Ahmed SR | G18: ann-INV232 | I18: Smirnoff Ice. | J18: =C21 -> 1 | K18: =E21 -> 17000 | L18: =K18/K$24 -> 0.0054598739
A19: 46212 | B19: Trophy | C19: 4 | D19: 8500 | E19: =C19*D19 -> 34000 | F19: tomaco | G19: ann-INV233 | I19: Medium Stout | J19: =C22 -> 1 | K19: =E22 -> 18300 | L19: =K19/K$24 -> 0.0058773937
A20: 46212 | B20: Goldberg 60cl | C20: 2 | D20: 9200 | E20: =C20*D20 -> 18400 | F20: tomaco | G20: ann-INV233 | I20: Desperados Bottle | J20: =C33 -> 2 | K20: =E33 -> 42800 | L20: =K20/K$24 -> 0.013746036
A21: 46212 | B21: Smirnoff Ice. | C21: 1 | D21: 17000 | E21: =C21*D21 -> 17000 | F21: tomaco | G21: ann-INV233 | I21: Star Bottle 60cl | J21: =C39 -> 1 | K21: =E39 -> 11415 | L21: =K21/K$24 -> 0.0036661448
A22: 46212 | B22: Medium Stout | C22: 1 | D22: 18300 | E22: =C22*D22 -> 18300 | F22: tomaco | G22: ann-INV233 | I22: Maltina Bottle | J22: =C40 -> 2 | K22: =E40 -> 26040 | L22: =K22/K$24 -> 0.0083632422
A23: 46212 | B23: Gulder Bottle | C23: 4 | D23: 11910 | E23: =C23*D23 -> 47640 | F23: Solomon | G23: ann-INV234 | I23: Maltina Pet 33cl | J23: =C48+C51 -> 2 | K23: =E48+E51 -> 10300 | L23: =K23/K$24 -> 0.0033080413
A24: 46212 | B24: Williams Bottle 60cl | C24: 2 | D24: 9345 | E24: =C24*D24 -> 18690 | F24: Solomon | G24: ann-INV234 | I24: Grand Total | J24: =SUM(J2:J23) -> 236 | K24: =SUM(K2:K23) -> 3113625 | L24: =K24/K$24 -> 1
A25: 46212 | B25: Tiger Bottle | C25: 1 | D25: 15525 | E25: =C25*D25 -> 15525 | F25: Solomon | G25: ann-INV234
A26: 46212 | B26: 33 Export 60cl | C26: 1 | D26: 9200 | E26: =C26*D26 -> 9200 | F26: Walk in Customer | G26: ann-INV235 | I26: Customer | J26: Amount_NGN | K26: % of Total Revenue | L26: Gross Profit
A27: 46212 | B27: Goldberg 60cl | C27: 1 | D27: 9200 | E27: =C27*D27 -> 9200 | F27: Walk in Customer | G27: ann-INV235 | I27: Delayers | J27: =E2 -> 775800 | K27: =J27/J$36 -> 0.24916295 | L27: 0.137
A28: 46212 | B28: Williams Bottle 60cl | C28: 2 | D28: 9345 | E28: =C28*D28 -> 18690 | F28: Jeff SR | G28: ann-INV236 | I28: Ameh Mathew | J28: =E3+E31+E32+E33+E34+E35+E36+E37+E38+E39+E40+E41+E42+E43+E44+E45+E46+E47+E48 -> 727460 | K28: =J28/J$36 -> 0.23363764 | L28: 0.0597
A29: 46212 | B29: Gulder Bottle | C29: 3 | D29: 11910 | E29: =C29*D29 -> 35730 | F29: Jeff SR | G29: ann-INV236 | I29: Rita SR | J29: =E4+E5+E6+E7+E8+E9+E10+E11+E12+E13+E14 -> 1191685 | K29: =J29/J$36 -> 0.38273235 | L29: 0.0417
A30: 46212 | B30: Tiger Bottle | C30: 2 | D30: 15525 | E30: =C30*D30 -> 31050 | F30: Jeff SR | G30: ann-INV236 | I30: Ahmed SR | J30: =E15+E16+E17+E18 -> 121455 | K30: =J30/J$36 -> 0.039007588 | L30: 0.0604
A31: 46212 | B31: Goldberg 60cl | C31: 5 | D31: 8800 | E31: =C31*D31 -> 44000 | F31: Ameh Mathew | G31: ann-INV237 | I31: tomaco | J31: =E19+E20+E21+E22 -> 87700 | K31: =J31/J$36 -> 0.028166526 | L31: 0.0506
A32: 46212 | B32: 33 Export 60cl | C32: 10 | D32: 9200 | E32: =C32*D32 -> 92000 | F32: Ameh Mathew | G32: ann-INV237 | I32: Solomon | J32: =E23+E24+E25 -> 81855 | K32: =J32/J$36 -> 0.026289293 | L32: 0.062
A33: 46212 | B33: Desperados Bottle | C33: 2 | D33: 21400 | E33: =C33*D33 -> 42800 | F33: Ameh Mathew | G33: ann-INV237 | I33: Walk in Customer | J33: =E26+E27 -> 18400 | K33: =J33/J$36 -> 0.0059095106 | L33: 0.042
A34: 46212 | B34: Tiger Bottle | C34: 2 | D34: 15525 | E34: =C34*D34 -> 31050 | F34: Ameh Mathew | G34: ann-INV237 | I34: Jeff SR | J34: =E28+E29+E30 -> 85470 | K34: =J34/J$36 -> 0.027450319 | L34: 0.0394
A35: 46212 | B35: Gulder Bottle | C35: 2 | D35: 11910 | E35: =C35*D35 -> 23820 | F35: Ameh Mathew | G35: ann-INV237 | I35: MRS IK. | J35: =E49+E50+E51 -> 23800 | K35: =J35/J$36 -> 0.0076438235 | L35: 0.0774
A36: 46212 | B36: Heineken Bottle 60cl | C36: 3 | D36: 13335 | E36: =C36*D36 -> 40005 | F36: Ameh Mathew | G36: ann-INV237 | I36: Total | J36: =SUM(J27:J35) -> 3113625 | K36: =J36/J$36 -> 1
A37: 46212 | B37: Turbo King Bottle 60cl | C37: 2 | D37: 8880 | E37: =C37*D37 -> 17760 | F37: Ameh Mathew | G37: ann-INV237
A38: 46212 | B38: Fayrouz Can | C38: 1 | D38: 13460 | E38: =C38*D38 -> 13460 | F38: Ameh Mathew | G38: ann-INV237 | I38: Invoice No | J38: Amount_NGN | K38: Gross Profit
A39: 46212 | B39: Star Bottle 60cl | C39: 1 | D39: 11415 | E39: =C39*D39 -> 11415 | F39: Ameh Mathew | G39: ann-INV237 | I39: ann-INV229 | J39: 895800 | K39: 0.14
A40: 46212 | B40: Maltina Bottle | C40: 2 | D40: 13020 | E40: =C40*D40 -> 26040 | F40: Ameh Mathew | G40: ann-INV237 | I40: ann-INV230 | J40: 216950 | K40: 0
A41: 46212 | B41: Amstel Bottle | C41: 1 | D41: 14450 | E41: =C41*D41 -> 14450 | F41: Ameh Mathew | G41: ann-INV237 | I41: ann-INV231 | J41: 1224685 | K41: 0.04
A42: 46212 | B42: Heineken Bottle 60cl | C42: 5 | D42: 13335 | E42: =C42*D42 -> 66675 | F42: Ameh Mathew | G42: ann-INV238 | I42: ann-INV232 | J42: 141255 | K42: 0.06
A43: 46212 | B43: Gulder Bottle | C43: 2 | D43: 11910 | E43: =C43*D43 -> 23820 | F43: Ameh Mathew | G43: ann-INV239 | I43: ann-INV233 | J43: 87700 | K43: 0.05
A44: 46212 | B44: Turbo King Bottle 60cl | C44: 1 | D44: 8880 | E44: =C44*D44 -> 8880 | F44: Ameh Mathew | G44: ann-INV239 | I44: ann-INV234 | J44: 94455 | K44: 0.06
A45: 46212 | B45: 33 Export 60cl | C45: 2 | D45: 9200 | E45: =C45*D45 -> 18400 | F45: Ameh Mathew | G45: ann-INV239 | I45: ann-INV235 | J45: 18400 | K45: 0.04
A46: 46212 | B46: Heineken Bottle 60cl | C46: 1 | D46: 13335 | E46: =C46*D46 -> 13335 | F46: Ameh Mathew | G46: ann-INV239 | I46: ann-INV236 | J46: 95970 | K46: 0.04
A47: 46212 | B47: Goldberg 60cl | C47: 2 | D47: 8800 | E47: =C47*D47 -> 17600 | F47: Ameh Mathew | G47: ann-INV239 | I47: ann-INV237 | J47: 411800 | K47: 0.07
A48: 46212 | B48: Maltina Pet 33cl | C48: 1 | D48: 5000 | E48: =C48*D48 -> 5000 | F48: Ameh Mathew | G48: ann-INV239 | I48: ann-INV238 | J48: 76675 | K48: 0.16
A49: 46212 | B49: Goldberg 60cl | C49: 1 | D49: 9500 | E49: =C49*D49 -> 9500 | F49: MRS IK. | G49: ann-INV240 | I49: ann-INV239 | J49: 101635 | K49: 0.07
A50: 46212 | B50: Trophy | C50: 1 | D50: 9000 | E50: =C50*D50 -> 9000 | F50: MRS IK. | G50: ann-INV240 | I50: ann-INV240 | J50: 23800 | K50: 0.08
A51: 46212 | B51: Maltina Pet 33cl | C51: 1 | D51: 5300 | E51: =C51*D51 -> 5300 | F51: MRS IK. | G51: ann-INV240 | I51: Total | J51: =SUM(J39:J50) -> 3389125
B52: Grand Total | C52: =SUM(C2:C51) -> 236 | D52: =SUM(D2:D51) -> 618610 | E52: =SUM(E2:E51) -> 3113625

Sheet July 10th Sales Report
A1: Date | B1: Product | C1: Cases_Sold | D1: Unit_Price_NGN | E1: Amount_NGN | F1: Customer | G1: Invoice No | I1: Product | J1: Quantity | K1: Revenue | L1: % of Total Revenue | N1: Total Revnue | O1: Total Cases Sold | P1: Total transaction
A2: 46213 | B2: Chamdor 75cl | C2: 10 | D2: 28445 | E2: =C2*D2 -> 284450 | F2: Mr Godswill | G2: ann-INV241 | I2: Chamdor 75cl | J2: =C2 -> 10 | K2: =E2 -> 284450 | L2: =K2/K$12 -> 0.18600743 | N2: =K12 -> 1529240 | O2: =J12 -> 231 | P2: =COUNT(J2:J11) -> 10
A3: 46213 | B3: Maltina Pet 33cl | C3: 200 | D3: 5000 | E3: =C3*D3 -> 1000000 | F3: Eniola Marketer | G3: ann-INV242 | I3: Maltina Pet 33cl | J3: =C3 -> 200 | K3: =E3 -> 1000000 | L3: =K3/K$12 -> 0.65391959
A4: 46213 | B4: Fayrouz Bottle | C4: 5 | D4: 10315 | E4: =C4*D4 -> 51575 | F4: Ameh Mathew | G4: ann-INV243 | I4: Fayrouz Bottle | J4: =C4 -> 5 | K4: =E4 -> 51575 | L4: =K4/K$12 -> 0.033725903
A5: 46213 | B5: Gulder Bottle | C5: 4 | D5: 11910 | E5: =C5*D5 -> 47640 | F5: Ameh Mathew | G5: ann-INV243 | I5: Gulder Bottle | J5: =C5 -> 4 | K5: =E5 -> 47640 | L5: =K5/K$12 -> 0.031152729
A6: 46213 | B6: Heineken Bottle 60cl | C6: 1 | D6: 13335 | E6: =C6*D6 -> 13335 | F6: tomaco | G6: ann-INV244 | I6: Heineken Bottle 60cl | J6: =C6 -> 1 | K6: =E6 -> 13335 | L6: =K6/K$12 -> 0.0087200178
A7: 46213 | B7: Goldberg 60cl | C7: 1 | D7: 9200 | E7: =C7*D7 -> 9200 | F7: tomaco | G7: ann-INV244 | I7: Goldberg 60cl | J7: =C7+C12+C13 -> 4 | K7: =E7+E12+E13 -> 37700 | L7: =K7/K$12 -> 0.024652769
A8: 46213 | B8: Medium Stout | C8: 1 | D8: 18300 | E8: =C8*D8 -> 18300 | F8: tomaco | G8: ann-INV244 | I8: Medium Stout | J8: =C8 -> 1 | K8: =E8 -> 18300 | L8: =K8/K$12 -> 0.011966729
A9: 46213 | B9: Star Radler 45cl | C9: 1 | D9: 15115 | E9: =C9*D9 -> 15115 | F9: tomaco | G9: ann-INV244 | I9: Star Radler 45cl | J9: =C9 -> 1 | K9: =E9 -> 15115 | L9: =K9/K$12 -> 0.0098839947
A10: 46213 | B10: Goldberg Black 45cl | C10: 3 | D10: 14145 | E10: =C10*D10 -> 42435 | F10: Ola SR | G10: ann-INV245 | I10: Goldberg Black 45cl | J10: =C10 -> 3 | K10: =E10 -> 42435 | L10: =K10/K$12 -> 0.027749078
A11: 46213 | B11: Williams Bottle 60cl | C11: 2 | D11: 9345 | E11: =C11*D11 -> 18690 | F11: Ola SR | G11: ann-INV245 | I11: Williams Bottle 60cl | J11: =C11 -> 2 | K11: =E11 -> 18690 | L11: =K11/K$12 -> 0.012221757
A12: 46213 | B12: Goldberg 60cl | C12: 2 | D12: 9500 | E12: =C12*D12 -> 19000 | F12: Walk in Customer | G12: ann-INV247 | I12: Grand Total | J12: =SUM(J2:J11) -> 231 | K12: =SUM(K2:K11) -> 1529240 | L12: =K12/K$12 -> 1
A13: 46213 | B13: Goldberg 60cl | C13: 1 | D13: 9500 | E13: =C13*D13 -> 9500 | F13: Walk in Customer | G13: ann-INV246
B14: Grand Total | C14: =SUM(C2:C13) -> 231 | D14: =SUM(D2:D13) -> 154110 | E14: =SUM(E2:E13) -> 1529240 | I14: Customer | J14: Amount_NGN | K14: % of Total Revenue | L14: Gross Profit
I15: Mr Godswill | J15: =E2 -> 284450 | K15: =J15/J$21 -> 0.18600743 | L15: 0.0884
I16: Eniola Marketer | J16: =E3 -> 1000000 | K16: =J16/J$21 -> 0.65391959 | L16: -0.04
I17: Ameh Mathew | J17: =E4+E5 -> 99215 | K17: =J17/J$21 -> 0.064878633 | L17: 0.0607
I18: tomaco | J18: =E6+E7+E8+E9 -> 55950 | K18: =J18/J$21 -> 0.036586801 | L18: 0.0526
I19: Ola SR | J19: =E10+E11 -> 61125 | K19: =J19/J$21 -> 0.039970835 | L19: 0.0429
I20: Walk in Customer | J20: =E12+E13 -> 28500 | K20: =J20/J$21 -> 0.018636708 | L20: 0.0992
I21: Total | J21: =SUM(J15:J20) -> 1529240 | K21: =J21/J$21 -> 1
I23: Invoice No | J23: Amount_NGN | K23: Gross Profit
I24: ann-INV241 | J24: 284450 | K24: 0.09
I25: ann-INV242 | J25: 1000000 | K25: -0.04
I26: ann-INV243 | J26: 115415 | K26: 0.06
I27: ann-INV244 | J27: 55950 | K27: 0.05
I28: ann-INV245 | J28: 61125 | K28: 0.04
I29: ann-INV247 | J29: 22600 | K29: 0.1
I30: ann-INV246 | J30: 9500 | K30: 0.09
I31: Total | J31: =SUM(J24:J30) -> 1549040

Sheet July 11th Sales Report
A1: Date | B1: Product | C1: Cases_Sold | D1: Unit_Price_NGN | E1: Amount_NGN | F1: Customer | G1: Invoice No | I1: Product | J1: Quantity | K1: Revenue | L1: % of Total Revenue | N1: Total Revnue | O1: Total Cases Sold | P1: Total transaction
A2: 46214 | B2: Trophy | C2: 2 | D2: 9000 | E2: =C2*D2 -> 18000 | F2: Remilekun | G2: ann-INV248 | I2: Trophy | J2: =C2+C30 -> 3 | K2: =E2+E30 -> 27000 | L2: =K2/K$18 -> 0.0081727415 | N2: =K18 -> 3303665 | O2: =J18 -> 410 | P2: =COUNT(J2:J17) -> 16
A3: 46214 | B3: Goldberg 60cl | C3: 3 | D3: 9500 | E3: =C3*D3 -> 28500 | F3: Remilekun | G3: ann-INV248 | I3: Goldberg 60cl | J3: =C3+C11+C14+C23+C29 -> 43 | K3: =E3+E11+E14+E23+E29 -> 395000 | L3: =K3/K$18 -> 0.11956418
A4: 46214 | B4: 33 Export 60cl | C4: 1 | D4: 9500 | E4: =C4*D4 -> 9500 | F4: Remilekun | G4: ann-INV248 | I4: 33 Export 60cl | J4: =C4+C12+C24+C31 -> 22 | K4: =E4+E12+E24+E31 -> 202700 | L4: =K4/K$18 -> 0.0613561
A5: 46214 | B5: Tiger Bottle | C5: 1 | D5: 16140 | E5: =C5*D5 -> 16140 | F5: Walk in Customer | G5: ann-INV251 | I5: Tiger Bottle | J5: =C5+C16 -> 4 | K5: =E5+E16 -> 62715 | L5: =K5/K$18 -> 0.018983462
A6: 46214 | B6: Maltina Pet 33cl | C6: 30 | D6: 5000 | E6: =C6*D6 -> 150000 | F6: Jeff SR | G6: ann-INV249 | I6: Maltina Pet 33cl | J6: =C6+C8+C21 -> 230 | K6: =E6+E8+E21 -> 1150000 | L6: =K6/K$18 -> 0.34809825
A7: 46214 | B7: Heineken Bottle 60cl | C7: 1 | D7: 13950 | E7: =C7*D7 -> 13950 | F7: Walk in Customer | G7: ann-INV250 | I7: Heineken Bottle 60cl | J7: =C7+C9+C15+C25+C34 -> 37 | K7: =E7+E9+E15+E25+E34 -> 500775 | L7: =K7/K$18 -> 0.15158165
A8: 46214 | B8: Maltina Pet 33cl | C8: 100 | D8: 5000 | E8: =C8*D8 -> 500000 | F8: AZ Marketer | G8: ann-INV255 | I8: Desperados Bottle | J8: =C10+C28+C37 -> 16 | K8: =E10+E28+E37 -> 348225 | L8: =K8/K$18 -> 0.10540566
A9: 46214 | B9: Heineken Bottle 60cl | C9: 10 | D9: 13950 | E9: =C9*D9 -> 139500 | F9: XXIII LOUNGE | G9: ann-INV252 | I9: Gulder Bottle | J9: =C13+C26+C33 -> 15 | K9: =E13+E26+E33 -> 178650 | L9: =K9/K$18 -> 0.054076306
A10: 46214 | B10: Desperados Bottle | C10: 5 | D10: 22565 | E10: =C10*D10 -> 112825 | F10: XXIII LOUNGE | G10: ann-INV252 | I10: Star Bottle 60cl | J10: =C17+C35 -> 3 | K10: =E17+E35 -> 34430 | L10: =K10/K$18 -> 0.010421759
A11: 46214 | B11: Goldberg 60cl | C11: 5 | D11: 9300 | E11: =C11*D11 -> 46500 | F11: XXIII LOUNGE | G11: ann-INV252 | I11: Goldberg Can 50cl | J11: =C18 -> 1 | K11: =E18 -> 16145 | L11: =K11/K$18 -> 0.0048869967
A12: 46214 | B12: 33 Export 60cl | C12: 10 | D12: 9200 | E12: =C12*D12 -> 92000 | F12: Ameh Mathew | G12: ann-INV253 | I12: Star Radler 45cl | J12: =C19+C27 -> 11 | K12: =E19+E27 -> 159325 | L12: =K12/K$18 -> 0.048226742
A13: 46214 | B13: Gulder Bottle | C13: 5 | D13: 11910 | E13: =C13*D13 -> 59550 | F13: Ameh Mathew | G13: ann-INV253 | I13: Heineken Bottle 45cl | J13: =C20 -> 1 | K13: =E20 -> 17840 | L13: =K13/K$18 -> 0.0054000633
A14: 46214 | B14: Goldberg 60cl | C14: 5 | D14: 8800 | E14: =C14*D14 -> 44000 | F14: Ameh Mathew | G14: ann-INV253 | I14: Maltina Pet 50cl | J14: =C22 -> 20 | K14: =E22 -> 160400 | L14: =K14/K$18 -> 0.048552138
A15: 46214 | B15: Heineken Bottle 60cl | C15: 5 | D15: 13335 | E15: =C15*D15 -> 66675 | F15: Ameh Mathew | G15: ann-INV253 | I15: Turbo King Bottle 60cl | J15: =C32+C39 -> 2 | K15: =E32+E39 -> 18700 | L15: =K15/K$18 -> 0.0056603802
A16: 46214 | B16: Tiger Bottle | C16: 3 | D16: 15525 | E16: =C16*D16 -> 46575 | F16: Ameh Mathew | G16: ann-INV253 | I16: Medium Stout | J16: =C36 -> 1 | K16: =E36 -> 18300 | L16: =K16/K$18 -> 0.0055393026
A17: 46214 | B17: Star Bottle 60cl | C17: 2 | D17: 11415 | E17: =C17*D17 -> 22830 | F17: Ameh Mathew | G17: ann-INV253 | I17: Fayrouz Can | J17: =C38 -> 1 | K17: =E38 -> 13460 | L17: =K17/K$18 -> 0.004074263
A18: 46214 | B18: Goldberg Can 50cl | C18: 1 | D18: 16145 | E18: =C18*D18 -> 16145 | F18: Ameh Mathew | G18: ann-INV253 | I18: Grand Total | J18: =SUM(J2:J17) -> 410 | K18: =SUM(K2:K17) -> 3303665 | L18: =K18/K$18 -> 1
A19: 46214 | B19: Star Radler 45cl | C19: 1 | D19: 14575 | E19: =C19*D19 -> 14575 | F19: Ameh Mathew | G19: ann-INV253
A20: 46214 | B20: Heineken Bottle 45cl | C20: 1 | D20: 17840 | E20: =C20*D20 -> 17840 | F20: Ameh Mathew | G20: ann-INV253 | I20: Customer | J20: Amount_NGN | K20: % of Total Revenue | L20: Gross Profit
A21: 46214 | B21: Maltina Pet 33cl | C21: 100 | D21: 5000 | E21: =C21*D21 -> 500000 | F21: Eniola Marketer | G21: ann-INV254 | I21: Remilekun | J21: =E2+E3+E4+E39 -> 65500 | K21: =J21/J$31 -> 0.019826465 | L21: 0.089
A22: 46214 | B22: Maltina Pet 50cl | C22: 20 | D22: 8020 | E22: =C22*D22 -> 160400 | F22: Eniola Marketer | G22: ann-INV254 | I22: Walk in Customer | J22: =E5+E7 -> 30090 | K22: =J22/J$31 -> 0.0091080663 | L22: 0.1341
A23: 46214 | B23: Goldberg 60cl | C23: 28 | D23: 9200 | E23: =C23*D23 -> 257600 | F23: ATW | G23: ann-INV256 | I23: Jeff SR | J23: =E6 -> 150000 | K23: =J23/J$31 -> 0.045404119 | L23: -0.04
A24: 46214 | B24: 33 Export 60cl | C24: 10 | D24: 9200 | E24: =C24*D24 -> 92000 | F24: Rita SR | G24: ann-INV257 | I24: AZ Marketer | J24: =E8 -> 500000 | K24: =J24/J$31 -> 0.15134706 | L24: -0.04
A25: 46214 | B25: Heineken Bottle 60cl | C25: 20 | D25: 13335 | E25: =C25*D25 -> 266700 | F25: Rita SR | G25: ann-INV257 | I25: XXIII LOUNGE | J25: =E9+E10+E11 -> 298825 | K25: =J25/J$31 -> 0.090452573 | L25: 0.1638
A26: 46214 | B26: Gulder Bottle | C26: 9 | D26: 11910 | E26: =C26*D26 -> 107190 | F26: Rita SR | G26: ann-INV257 | I26: Ameh Mathew | J26: =E12+E13+E14+E15+E16+E17+E18+E19+E20 -> 380190 | K26: =J26/J$31 -> 0.11508128 | L26: 0.0722
A27: 46214 | B27: Star Radler 45cl | C27: 10 | D27: 14475 | E27: =C27*D27 -> 144750 | F27: Rita SR | G27: ann-INV257 | I27: Eniola Marketer | J27: =E21+E22 -> 660400 | K27: =J27/J$31 -> 0.1998992 | L27: -0.0201
A28: 46214 | B28: Desperados Bottle | C28: 10 | D28: 21400 | E28: =C28*D28 -> 214000 | F28: Rita SR | G28: ann-INV257 | I28: ATW | J28: =E23 -> 257600 | K28: =J28/J$31 -> 0.077974008 | L28: 0.0781
A29: 46214 | B29: Goldberg 60cl | C29: 2 | D29: 9200 | E29: =C29*D29 -> 18400 | F29: MRS IK. | G29: ann-INV258 | I29: Rita SR | J29: =E24+E25+E26+E27+E28 -> 824640 | K29: =J29/J$31 -> 0.24961369 | L29: 0.0995
A30: 46214 | B30: Trophy | C30: 1 | D30: 9000 | E30: =C30*D30 -> 9000 | F30: MRS IK. | G30: ann-INV258 | I30: MRS IK. | J30: =E29+E30+E31+E32+E33+E34+E35+E36+E37+E38 -> 136420 | K30: =J30/J$31 -> 0.041293533 | L30: 0.0577
A31: 46214 | B31: 33 Export 60cl | C31: 1 | D31: 9200 | E31: =C31*D31 -> 9200 | F31: MRS IK. | G31: ann-INV258 | I31: Total | J31: =SUM(J21:J30) -> 3303665 | K31: =J31/J$31 -> 1
A32: 46214 | B32: Turbo King Bottle 60cl | C32: 1 | D32: 9200 | E32: =C32*D32 -> 9200 | F32: MRS IK. | G32: ann-INV258
A33: 46214 | B33: Gulder Bottle | C33: 1 | D33: 11910 | E33: =C33*D33 -> 11910 | F33: MRS IK. | G33: ann-INV258 | I33: Invoice No | J33: Amount_NGN | K33: Gross Profit
A34: 46214 | B34: Heineken Bottle 60cl | C34: 1 | D34: 13950 | E34: =C34*D34 -> 13950 | F34: MRS IK. | G34: ann-INV258 | I34: ann-INV248 | J34: 56000 | K34: 0.09
A35: 46214 | B35: Star Bottle 60cl | C35: 1 | D35: 11600 | E35: =C35*D35 -> 11600 | F35: MRS IK. | G35: ann-INV258 | I35: ann-INV251 | J35: 16140 | K35: 0.08
A36: 46214 | B36: Medium Stout | C36: 1 | D36: 18300 | E36: =C36*D36 -> 18300 | F36: MRS IK. | G36: ann-INV258 | I36: ann-INV249 | J36: 150000 | K36: -0.04
A37: 46214 | B37: Desperados Bottle | C37: 1 | D37: 21400 | E37: =C37*D37 -> 21400 | F37: MRS IK. | G37: ann-INV258 | I37: ann-INV250 | J37: 15950 | K37: 0.19
A38: 46214 | B38: Fayrouz Can | C38: 1 | D38: 13460 | E38: =C38*D38 -> 13460 | F38: MRS IK. | G38: ann-INV258 | I38: ann-INV255 | J38: 500000 | K38: -0.04
A39: 46214 | B39: Turbo King Bottle 60cl | C39: 1 | D39: 9500 | E39: =C39*D39 -> 9500 | F39: Remilekun | G39: ann-INV259 | I39: ann-INV252 | J39: 337825 | K39: 0.16
B40: Grand Total | C40: =SUM(C2:C39) -> 410 | D40: =SUM(D2:D39) -> 461910 | E40: =SUM(E2:E39) -> 3303665 | I40: ann-INV253 | J40: 438990 | K40: 0.07
I41: ann-INV254 | J41: 660400 | K41: -0.02
I42: ann-INV256 | J42: 308000 | K42: 0.08
I43: ann-INV257 | J43: 936840 | K43: 0.1
I44: ann-INV258 | J44: 136420 | K44: 0.06
I45: ann-INV259 | J45: 9500 | K45: 0.1
I46: Total | J46: =SUM(J34:J45) -> 3566065

Sheet July 12th Sales Report
A1: July 12th, 2026
A2: No sales recorded - store closed (Sunday).

Sheet July 13th Sales Report
A1: Date | B1: Product | C1: Cases_Sold | D1: Unit_Price_NGN | E1: Amount_NGN | F1: Customer | G1: Invoice No | I1: Product | J1: Quantity | K1: Revenue | L1: % of Total Revenue | N1: Total Revnue | O1: Total Cases Sold | P1: Total transaction
A2: 46216 | B2: Maltina Pet 33cl | C2: 1240 | D2: 4950 | E2: =C2*D2 -> 6138000 | F2: FINO STORES | G2: ann-INV260 | I2: Maltina Pet 33cl | J2: =C2+C15 -> 1390 | K2: =E2+E15 -> 6888000 | L2: =K2/K$18 -> 0.71994632 | N2: =K18 -> 9567380 | O2: =J18 -> 1675 | P2: =COUNT(J2:J17) -> 16
A3: 46216 | B3: Goldberg 60cl | C3: 5 | D3: 9200 | E3: =C3*D3 -> 46000 | F3: Mr Olayinka | G3: ann-INV261 | I3: Goldberg 60cl | J3: =C3+C4 -> 22 | K3: =E3+E4 -> 195600 | L3: =K3/K$18 -> 0.020444469
A4: 46216 | B4: Goldberg 60cl | C4: 17 | D4: 8800 | E4: =C4*D4 -> 149600 | F4: Ameh Mathew | G4: ann-INV262 | I4: Heineken Bottle 60cl | J4: =C5+C17 -> 17 | K4: =E5+E17 -> 232845 | L4: =K4/K$18 -> 0.024337384
A5: 46216 | B5: Heineken Bottle 60cl | C5: 7 | D5: 13335 | E5: =C5*D5 -> 93345 | F5: Ameh Mathew | G5: ann-INV262 | I5: Gulder Bottle | J5: =C6 -> 3 | K5: =E6 -> 35730 | L5: =K5/K$18 -> 0.0037345647
A6: 46216 | B6: Gulder Bottle | C6: 3 | D6: 11910 | E6: =C6*D6 -> 35730 | F6: Ameh Mathew | G6: ann-INV262 | I6: Star Radler 45cl | J6: =C7 -> 2 | K6: =E7 -> 29150 | L6: =K6/K$18 -> 0.0030468111
A7: 46216 | B7: Star Radler 45cl | C7: 2 | D7: 14575 | E7: =C7*D7 -> 29150 | F7: Ameh Mathew | G7: ann-INV262 | I7: Turbo King Bottle 60cl | J7: =C8 -> 3 | K7: =E8 -> 26640 | L7: =K7/K$18 -> 0.0027844614
A8: 46216 | B8: Turbo King Bottle 60cl | C8: 3 | D8: 8880 | E8: =C8*D8 -> 26640 | F8: Ameh Mathew | G8: ann-INV262 | I8: Tiger Bottle | J8: =C9 -> 2 | K8: =E9 -> 31050 | L8: =K8/K$18 -> 0.0032454026
A9: 46216 | B9: Tiger Bottle | C9: 2 | D9: 15525 | E9: =C9*D9 -> 31050 | F9: Ameh Mathew | G9: ann-INV262 | I9: Desperados Bottle | J9: =C10 -> 1 | K9: =E10 -> 21400 | L9: =K9/K$18 -> 0.002236767
A10: 46216 | B10: Desperados Bottle | C10: 1 | D10: 21400 | E10: =C10*D10 -> 21400 | F10: Ameh Mathew | G10: ann-INV262 | I10: Fayrouz Bottle | J10: =C11+C19 -> 6 | K10: =E11+E19 -> 61890 | L10: =K10/K$18 -> 0.0064688556
A11: 46216 | B11: Fayrouz Bottle | C11: 1 | D11: 10315 | E11: =C11*D11 -> 10315 | F11: Ameh Mathew | G11: ann-INV262 | I11: Star Bottle 60cl | J11: =C12 -> 1 | K11: =E12 -> 11415 | L11: =K11/K$18 -> 0.0011931166
A12: 46216 | B12: Star Bottle 60cl | C12: 1 | D12: 11415 | E12: =C12*D12 -> 11415 | F12: Ameh Mathew | G12: ann-INV262 | I12: 33 Export 60cl | J12: =C13 -> 21 | K12: =E13 -> 193200 | L12: =K12/K$18 -> 0.020193616
A13: 46216 | B13: 33 Export 60cl | C13: 21 | D13: 9200 | E13: =C13*D13 -> 193200 | F13: Ameh Mathew | G13: ann-INV262 | I13: Williams Bottle 60cl | J13: =C14 -> 1 | K13: =E14 -> 9345 | L13: =K13/K$18 -> 0.00097675644
A14: 46216 | B14: Williams Bottle 60cl | C14: 1 | D14: 9345 | E14: =C14*D14 -> 9345 | F14: Ameh Mathew | G14: ann-INV263 | I14: Maltina Can | J14: =C16 -> 5 | K14: =E16 -> 65750 | L14: =K14/K$18 -> 0.0068723099
A15: 46216 | B15: Maltina Pet 33cl | C15: 150 | D15: 5000 | E15: =C15*D15 -> 750000 | F15: Eniola Marketer | G15: ann-INV264 | I15: Maltina Bottle | J15: =C18 -> 3 | K15: =E18 -> 43365 | L15: =K15/K$18 -> 0.0045325889
A16: 46216 | B16: Maltina Can | C16: 5 | D16: 13150 | E16: =C16*D16 -> 65750 | F16: Eniola Marketer | G16: ann-INV264 | I16: Chamdor 75cl | J16: =C20 -> 6 | K16: =E20 -> 234000 | L16: =K16/K$18 -> 0.024458107
A17: 46216 | B17: Heineken Bottle 60cl | C17: 10 | D17: 13950 | E17: =C17*D17 -> 139500 | F17: XXIII LOUNGE | G17: ann-INV265 | I17: Maltina Pet 50cl | J17: =C21 -> 192 | K17: =E21 -> 1488000 | L17: =K17/K$18 -> 0.15552847
A18: 46216 | B18: Maltina Bottle | C18: 3 | D18: 14455 | E18: =C18*D18 -> 43365 | F18: XXIII LOUNGE | G18: ann-INV265 | I18: Grand Total | J18: =SUM(J2:J17) -> 1675 | K18: =SUM(K2:K17) -> 9567380 | L18: =K18/K$18 -> 1
A19: 46216 | B19: Fayrouz Bottle | C19: 5 | D19: 10315 | E19: =C19*D19 -> 51575 | F19: XXIII LOUNGE | G19: ann-INV265
A20: 46216 | B20: Chamdor 75cl | C20: 6 | D20: 39000 | E20: =C20*D20 -> 234000 | F20: XXIII LOUNGE | G20: ann-INV265 | I20: Customer | J20: Amount_NGN | K20: % of Total Revenue | L20: Gross Profit
A21: 46216 | B21: Maltina Pet 50cl | C21: 192 | D21: 7750 | E21: =C21*D21 -> 1488000 | F21: Demola SR | G21: ann-INV266 | I21: FINO STORES | J21: =E2 -> 6138000 | K21: =J21/J$27 -> 0.64155495 | L21: -0.0505
B22: Grand Total | C22: =SUM(C2:C21) -> 1675 | D22: =SUM(D2:D21) -> 252470 | E22: =SUM(E2:E21) -> 9567380 | I22: Mr Olayinka | J22: =E3 -> 46000 | K22: =J22/J$27 -> 0.0048080039 | L22: 0.059
I23: Ameh Mathew | J23: =E4+E5+E6+E7+E8+E9+E10+E11+E12+E13+E14 -> 611190 | K23: =J23/J$27 -> 0.063882693 | L23: 0.0658
I24: Eniola Marketer | J24: =E15+E16 -> 815750 | K24: =J24/J$27 -> 0.085263677 | L24: -0.0389
I25: XXIII LOUNGE | J25: =E17+E18+E19+E20 -> 468440 | K25: =J25/J$27 -> 0.048962203 | L25: 0.2346
I26: Demola SR | J26: =E21 -> 1488000 | K26: =J26/J$27 -> 0.15552847 | L26: 0.0084
I27: Total | J27: =SUM(J21:J26) -> 9567380 | K27: =J27/J$27 -> 1
I29: Invoice No | J29: Amount_NGN | K29: Gross Profit
I30: ann-INV260 | J30: 6138000 | K30: -0.05
I31: ann-INV261 | J31: 46000 | K31: 0.06
I32: ann-INV262 | J32: 707845 | K32: 0.07
I33: ann-INV263 | J33: 11145 | K33: 0.06
I34: ann-INV264 | J34: 815750 | K34: -0.04
I35: ann-INV265 | J35: 502840 | K35: 0.23
I36: ann-INV266 | J36: 1488000 | K36: 0.01
I37: Total | J37: =SUM(J30:J36) -> 9709580

Sheet July 14th Sales Report
A1: Date | B1: Product | C1: Cases_Sold | D1: Unit_Price_NGN | E1: Amount_NGN | F1: Customer | G1: Invoice No | I1: Product | J1: Quantity | K1: Revenue | L1: % of Total Revenue | N1: Total Revnue | O1: Total Cases Sold | P1: Total transaction
A2: 46217 | B2: Goldberg 60cl | C2: 1 | D2: 9200 | E2: =C2*D2 -> 9200 | F2: Staff Debit | G2: ann-INV267 | I2: Goldberg 60cl | J2: =C2+C9+C13+C24+C32+C37 -> 189 | K2: =E2+E9+E13+E24+E32+E37 -> 1691400 | L2: =K2/K$24 -> 0.1880816 | N2: =K24 -> 8992905 | O2: =J24 -> 1093 | P2: =COUNT(J2:J23) -> 22
A3: 46217 | B3: Maltina Pet 33cl | C3: 253 | D3: 5000 | E3: =C3*D3 -> 1265000 | F3: Rita SR | G3: ann-INV268 | I3: Maltina Pet 33cl | J3: =C3+C14+C16+C17+C22+C23+C44 -> 518 | K3: =E3+E14+E16+E17+E22+E23+E44 -> 2596000 | L3: =K3/K$24 -> 0.28867201
A4: 46217 | B4: Heineken Sleek Can | C4: 15 | D4: 17100 | E4: =C4*D4 -> 256500 | F4: Ameh Mathew | G4: ann-INV269 | I4: Heineken Sleek Can | J4: =C4 -> 15 | K4: =E4 -> 256500 | L4: =K4/K$24 -> 0.028522485
A5: 46217 | B5: Amstel Can | C5: 2 | D5: 14430 | E5: =C5*D5 -> 28860 | F5: Ameh Mathew | G5: ann-INV269 | I5: Amstel Can | J5: =C5 -> 2 | K5: =E5 -> 28860 | L5: =K5/K$24 -> 0.0032091966
A6: 46217 | B6: ACE BITTERS | C6: 1 | D6: 20655 | E6: =C6*D6 -> 20655 | F6: Ameh Mathew | G6: ann-INV269 | I6: ACE BITTERS | J6: =C6 -> 1 | K6: =E6 -> 20655 | L6: =K6/K$24 -> 0.0022968107
A7: 46217 | B7: Maltina Can | C7: 2 | D7: 13200 | E7: =C7*D7 -> 26400 | F7: Ameh Mathew | G7: ann-INV269 | I7: Maltina Can | J7: =C7 -> 2 | K7: =E7 -> 26400 | L7: =K7/K$24 -> 0.0029356476
A8: 46217 | B8: 33 Export 60cl | C8: 2 | D8: 9200 | E8: =C8*D8 -> 18400 | F8: Ameh Mathew | G8: ann-INV269 | I8: 33 Export 60cl | J8: =C8+C10+C25+C36+C42 -> 88 | K8: =E8+E10+E25+E36+E42 -> 794900 | L8: =K8/K$24 -> 0.088391905
A9: 46217 | B9: Goldberg 60cl | C9: 5 | D9: 8800 | E9: =C9*D9 -> 44000 | F9: Ameh Mathew | G9: ann-INV269 | I9: Heineken Bottle 60cl | J9: =C11+C26+C33+C43 -> 81 | K9: =E11+E26+E33+E43 -> 1079985 | L9: =K9/K$24 -> 0.12009301
A10: 46217 | B10: 33 Export 60cl | C10: 9 | D10: 9200 | E10: =C10*D10 -> 82800 | F10: Ameh Mathew | G10: ann-INV270 | I10: Turbo King Bottle 60cl | J10: =C12+C27+C31+C38 -> 79 | K10: =E12+E27+E31+E38 -> 703560 | L10: =K10/K$24 -> 0.078235009
A11: 46217 | B11: Heineken Bottle 60cl | C11: 5 | D11: 13335 | E11: =C11*D11 -> 66675 | F11: Ameh Mathew | G11: ann-INV270 | I11: Maltina Pet 50cl | J11: =C15+C45 -> 12 | K11: =E15+E45 -> 96240 | L11: =K11/K$24 -> 0.01070177
A12: 46217 | B12: Turbo King Bottle 60cl | C12: 2 | D12: 8880 | E12: =C12*D12 -> 17760 | F12: Ameh Mathew | G12: ann-INV270 | I12: Goldberg Can 50cl | J12: =C18 -> 5 | K12: =E18 -> 80725 | L12: =K12/K$24 -> 0.0089765209
A13: 46217 | B13: Goldberg 60cl | C13: 10 | D13: 8800 | E13: =C13*D13 -> 88000 | F13: Ameh Mathew | G13: ann-INV270 | I13: Legend Can 44cl | J13: =C19 -> 3 | K13: =E19 -> 63510 | L13: =K13/K$24 -> 0.0070622341
A14: 46217 | B14: Maltina Pet 33cl | C14: 15 | D14: 5000 | E14: =C14*D14 -> 75000 | F14: Ameh Mathew | G14: ann-INV270 | I14: TROPHY CAN | J14: =C20 -> 5 | K14: =E20 -> 77450 | L14: =K14/K$24 -> 0.008612345
A15: 46217 | B15: Maltina Pet 50cl | C15: 2 | D15: 8020 | E15: =C15*D15 -> 16040 | F15: Ameh Mathew | G15: ann-INV270 | I15: Desperados Can | J15: =C21+C40 -> 6 | K15: =E21+E40 -> 136440 | L15: =K15/K$24 -> 0.015171961
A16: 46217 | B16: Maltina Pet 33cl | C16: 20 | D16: 5000 | E16: =C16*D16 -> 100000 | F16: Solomon | G16: ann-INV271 | I16: Smirnoff Ice. | J16: =C28 -> 60 | K16: =E28 -> 1014000 | L16: =K16/K$24 -> 0.11275556
A17: 46217 | B17: Maltina Pet 33cl | C17: 20 | D17: 5300 | E17: =C17*D17 -> 106000 | F17: Mr Godswill | G17: ann-INV272 | I17: Trophy | J17: =C29 -> 3 | K17: =E29 -> 27000 | L17: =K17/K$24 -> 0.0030023669
A18: 46217 | B18: Goldberg Can 50cl | C18: 5 | D18: 16145 | E18: =C18*D18 -> 80725 | F18: Eniola Marketer | G18: ann-INV273 | I18: Castle Lite | J18: =C30 -> 8 | K18: =E30 -> 77600 | L18: =K18/K$24 -> 0.0086290248
A19: 46217 | B19: Legend Can 44cl | C19: 3 | D19: 21170 | E19: =C19*D19 -> 63510 | F19: Eniola Marketer | G19: ann-INV273 | I19: Tiger Bottle | J19: =C34 -> 3 | K19: =E34 -> 46500 | L19: =K19/K$24 -> 0.0051707429
A20: 46217 | B20: TROPHY CAN | C20: 5 | D20: 15490 | E20: =C20*D20 -> 77450 | F20: Eniola Marketer | G20: ann-INV273 | I20: Medium Stout | J20: =C35 -> 1 | K20: =E35 -> 18100 | L20: =K20/K$24 -> 0.0020126978
A21: 46217 | B21: Desperados Can | C21: 5 | D21: 22740 | E21: =C21*D21 -> 113700 | F21: Eniola Marketer | G21: ann-INV273 | I21: Gulder Bottle | J21: =C39 -> 5 | K21: =E39 -> 59550 | L21: =K21/K$24 -> 0.0066218869
A22: 46217 | B22: Maltina Pet 33cl | C22: 100 | D22: 5000 | E22: =C22*D22 -> 500000 | F22: Eniola Marketer | G22: ann-INV273 | I22: Star Radler 45cl | J22: =C41 -> 2 | K22: =E41 -> 30230 | L22: =K22/K$24 -> 0.0033615389
A23: 46217 | B23: Maltina Pet 33cl | C23: 50 | D23: 5000 | E23: =C23*D23 -> 250000 | F23: Jeff SR | G23: ann-INV274 | I23: Fayrouz Can | J23: =C46 -> 5 | K23: =E46 -> 67300 | L23: =K23/K$24 -> 0.0074836774
A24: 46217 | B24: Goldberg 60cl | C24: 140 | D24: 8990 | E24: =C24*D24 -> 1258600 | F24: Etigwam Nig Ltd | G24: Tayo-INV138 | I24: Grand Total | J24: =SUM(J2:J23) -> 1093 | K24: =SUM(K2:K23) -> 8992905 | L24: =K24/K$24 -> 1
A25: 46217 | B25: 33 Export 60cl | C25: 70 | D25: 8990 | E25: =C25*D25 -> 629300 | F25: Etigwam Nig Ltd | G25: Tayo-INV138
A26: 46217 | B26: Heineken Bottle 60cl | C26: 70 | D26: 13332 | E26: =C26*D26 -> 933240 | F26: Etigwam Nig Ltd | G26: Tayo-INV138 | I26: Customer | J26: Amount_NGN | K26: % of Total Revenue | L26: Gross Profit
A27: 46217 | B27: Turbo King Bottle 60cl | C27: 70 | D27: 8900 | E27: =C27*D27 -> 623000 | F27: Etigwam Nig Ltd | G27: Tayo-INV138 | I27: Staff Debit | J27: =E2 -> 9200 | K27: =J27/J$38 -> 0.0010230287 | L27: 0.059
A28: 46217 | B28: Smirnoff Ice. | C28: 60 | D28: 16900 | E28: =C28*D28 -> 1014000 | F28: Etigwam Nig Ltd | G28: Tayo-INV138 | I28: Rita SR | J28: =E3 -> 1265000 | K28: =J28/J$38 -> 0.14066645 | L28: -0.04
A29: 46217 | B29: Trophy | C29: 3 | D29: 9000 | E29: =C29*D29 -> 27000 | F29: Walk in Customer | G29: ann-INV275 | I29: Ameh Mathew | J29: =E4+E5+E6+E7+E8+E9+E10+E11+E12+E13+E14+E15+E37+E38+E39 -> 1109040 | K29: =J29/J$38 -> 0.12332389 | L29: 0.037
A30: 46217 | B30: Castle Lite | C30: 8 | D30: 9700 | E30: =C30*D30 -> 77600 | F30: Walk in Customer | G30: ann-INV275 | I30: Solomon | J30: =E16 -> 100000 | K30: =J30/J$38 -> 0.011119877 | L30: -0.04
A31: 46217 | B31: Turbo King Bottle 60cl | C31: 2 | D31: 9200 | E31: =C31*D31 -> 18400 | F31: Walk in Customer | G31: ann-INV275 | I31: Mr Godswill | J31: =E17 -> 106000 | K31: =J31/J$38 -> 0.01178707 | L31: 0.0189
A32: 46217 | B32: Goldberg 60cl | C32: 3 | D32: 9200 | E32: =C32*D32 -> 27600 | F32: Walk in Customer | G32: ann-INV275 | I32: Eniola Marketer | J32: =E18+E19+E20+E21+E22 -> 835385 | K32: =J32/J$38 -> 0.092893787 | L32: 0
A33: 46217 | B33: Heineken Bottle 60cl | C33: 4 | D33: 13350 | E33: =C33*D33 -> 53400 | F33: Walk in Customer | G33: ann-INV275 | I33: Jeff SR | J33: =E23 -> 250000 | K33: =J33/J$38 -> 0.027799693 | L33: -0.04
A34: 46217 | B34: Tiger Bottle | C34: 3 | D34: 15500 | E34: =C34*D34 -> 46500 | F34: Walk in Customer | G34: ann-INV275 | I34: Etigwam Nig Ltd | J34: =E24+E25+E26+E27+E28 -> 4458140 | K34: =J34/J$38 -> 0.4957397 | L34: 0.0628
A35: 46217 | B35: Medium Stout | C35: 1 | D35: 18100 | E35: =C35*D35 -> 18100 | F35: Walk in Customer | G35: ann-INV275 | I35: Walk in Customer | J35: =E29+E30+E31+E32+E33+E34+E35+E36 -> 314600 | K35: =J35/J$38 -> 0.034983134 | L35: 0.0483
A36: 46217 | B36: 33 Export 60cl | C36: 5 | D36: 9200 | E36: =C36*D36 -> 46000 | F36: Walk in Customer | G36: ann-INV275 | I36: Y k BAR | J36: =E40+E41+E42+E43 -> 98040 | K36: =J36/J$38 -> 0.010901928 | L36: 0.0887
A37: 46217 | B37: Goldberg 60cl | C37: 30 | D37: 8800 | E37: =C37*D37 -> 264000 | F37: Ameh Mathew | G37: ann-INV277 | I37: Ahmed SR | J37: =E44+E45+E46 -> 447500 | K37: =J37/J$38 -> 0.049761451 | L37: -0.0126
A38: 46217 | B38: Turbo King Bottle 60cl | C38: 5 | D38: 8880 | E38: =C38*D38 -> 44400 | F38: Ameh Mathew | G38: ann-INV277 | I38: Total | J38: =SUM(J27:J37) -> 8992905 | K38: =J38/J$38 -> 1
A39: 46217 | B39: Gulder Bottle | C39: 5 | D39: 11910 | E39: =C39*D39 -> 59550 | F39: Ameh Mathew | G39: ann-INV277
A40: 46217 | B40: Desperados Can | C40: 1 | D40: 22740 | E40: =C40*D40 -> 22740 | F40: Y k BAR | G40: ann-INV278 | I40: Invoice No | J40: Amount_NGN | K40: Gross Profit
A41: 46217 | B41: Star Radler 45cl | C41: 2 | D41: 15115 | E41: =C41*D41 -> 30230 | F41: Y k BAR | G41: ann-INV278 | I41: ann-INV267 | J41: 9200 | K41: 0.06
A42: 46217 | B42: 33 Export 60cl | C42: 2 | D42: 9200 | E42: =C42*D42 -> 18400 | F42: Y k BAR | G42: ann-INV278 | I42: ann-INV268 | J42: 1265000 | K42: -0.04
A43: 46217 | B43: Heineken Bottle 60cl | C43: 2 | D43: 13335 | E43: =C43*D43 -> 26670 | F43: Y k BAR | G43: ann-INV278 | I43: ann-INV269 | J43: 407415 | K43: 0.01
A44: 46217 | B44: Maltina Pet 33cl | C44: 60 | D44: 5000 | E44: =C44*D44 -> 300000 | F44: Ahmed SR | G44: ann-INV276 | I44: ann-INV270 | J44: 394075 | K44: 0.05
A45: 46217 | B45: Maltina Pet 50cl | C45: 10 | D45: 8020 | E45: =C45*D45 -> 80200 | F45: Ahmed SR | G45: ann-INV276 | I45: ann-INV271 | J45: 100000 | K45: -0.04
A46: 46217 | B46: Fayrouz Can | C46: 5 | D46: 13460 | E46: =C46*D46 -> 67300 | F46: Ahmed SR | G46: ann-INV276 | I46: ann-INV272 | J46: 106000 | K46: 0.02
B47: Grand Total | C47: =SUM(C2:C46) -> 1093 | D47: =SUM(D2:D46) -> 513487 | E47: =SUM(E2:E46) -> 8992905 | I47: ann-INV273 | J47: 835385 | K47: 0
I48: ann-INV274 | J48: 250000 | K48: -0.04
I49: Tayo-INV138 | J49: 4538140 | K49: 0.06
I50: ann-INV275 | J50: 314600 | K50: 0.05
I51: ann-INV277 | J51: 439950 | K51: 0.05
I52: ann-INV278 | J52: 110040 | K52: 0.09
I53: ann-INV276 | J53: 447500 | K53: -0.01
I54: Total | J54: =SUM(J41:J53) -> 9217305

Sheet July 15th Sales Report
A1: Date | B1: Product | C1: Cases_Sold | D1: Unit_Price_NGN | E1: Amount_NGN | F1: Customer | G1: Invoice No | I1: Product | J1: Quantity | K1: Revenue | L1: % of Total Revenue | N1: Total Revnue | O1: Total Cases Sold | P1: Total transaction
A2: 46218 | B2: Desperados Bottle | C2: 5 | D2: 21485 | E2: =C2*D2 -> 107425 | F2: ATW | G2: Tayo-INV139 | I2: Desperados Bottle | J2: =C2 -> 5 | K2: =E2 -> 107425 | L2: =K2/K$27 -> 0.02391024 | N2: =K27 -> 4492845 | O2: =J27 -> 364 | P2: =COUNT(J2:J26) -> 25
A3: 46218 | B3: Heineken Bottle 45cl | C3: 20 | D3: 17840 | E3: =C3*D3 -> 356800 | F3: ATW | G3: Tayo-INV139 | I3: Heineken Bottle 45cl | J3: =C3 -> 20 | K3: =E3 -> 356800 | L3: =K3/K$27 -> 0.079415159
A4: 46218 | B4: Heineken Bottle 60cl | C4: 15 | D4: 13332 | E4: =C4*D4 -> 199980 | F4: ATW | G4: Tayo-INV139 | I4: Heineken Bottle 60cl | J4: =C4+C26+C29 -> 18 | K4: =E4+E26+E29 -> 240000 | L4: =K4/K$27 -> 0.053418268
A5: 46218 | B5: Star Bottle 60cl | C5: 5 | D5: 11600 | E5: =C5*D5 -> 58000 | F5: ATW | G5: Tayo-INV139 | I5: Star Bottle 60cl | J5: =C5 -> 5 | K5: =E5 -> 58000 | L5: =K5/K$27 -> 0.012909415
A6: 46218 | B6: Maltina Pet 33cl | C6: 30 | D6: 6195 | E6: =C6*D6 -> 185850 | F6: ATW | G6: Tayo-INV139 | I6: Maltina Pet 33cl | J6: =C6+C27 -> 100 | K6: =E6+E27 -> 535850 | L6: =K6/K$27 -> 0.11926741
A7: 46218 | B7: Maltina Pet 50cl | C7: 20 | D7: 8020 | E7: =C7*D7 -> 160400 | F7: ATW | G7: Tayo-INV139 | I7: Maltina Pet 50cl | J7: =C7 -> 20 | K7: =E7 -> 160400 | L7: =K7/K$27 -> 0.035701209
A8: 46218 | B8: Legend 45cl | C8: 10 | D8: 15945 | E8: =C8*D8 -> 159450 | F8: ATW | G8: Tayo-INV139 | I8: Legend 45cl | J8: =C8 -> 10 | K8: =E8 -> 159450 | L8: =K8/K$27 -> 0.035489762
A9: 46218 | B9: Legend Can 44cl | C9: 10 | D9: 21170 | E9: =C9*D9 -> 211700 | F9: ATW | G9: Tayo-INV139 | I9: Legend Can 44cl | J9: =C9 -> 10 | K9: =E9 -> 211700 | L9: =K9/K$27 -> 0.047119364
A10: 46218 | B10: Goldberg Can 50cl | C10: 10 | D10: 16145 | E10: =C10*D10 -> 161450 | F10: ATW | G10: Tayo-INV139 | I10: Goldberg Can 50cl | J10: =C10 -> 10 | K10: =E10 -> 161450 | L10: =K10/K$27 -> 0.035934914
A11: 46218 | B11: Goldberg Black 45cl | C11: 10 | D11: 14145 | E11: =C11*D11 -> 141450 | F11: ATW | G11: Tayo-INV139 | I11: Goldberg Black 45cl | J11: =C11 -> 10 | K11: =E11 -> 141450 | L11: =K11/K$27 -> 0.031483392
A12: 46218 | B12: Desperados Can | C12: 5 | D12: 22740 | E12: =C12*D12 -> 113700 | F12: ATW | G12: Tayo-INV139 | I12: Desperados Can | J12: =C12 -> 5 | K12: =E12 -> 113700 | L12: =K12/K$27 -> 0.025306905
A13: 46218 | B13: Fayrouz Can | C13: 50 | D13: 13460 | E13: =C13*D13 -> 673000 | F13: ATW | G13: Tayo-INV139 | I13: Fayrouz Can | J13: =C13 -> 50 | K13: =E13 -> 673000 | L13: =K13/K$27 -> 0.14979373
A14: 46218 | B14: Amstel Can | C14: 11 | D14: 14430 | E14: =C14*D14 -> 158730 | F14: ATW | G14: Tayo-INV139 | I14: Amstel Can | J14: =C14 -> 11 | K14: =E14 -> 158730 | L14: =K14/K$27 -> 0.035329507
A15: 46218 | B15: Maltina Can | C15: 31 | D15: 14400 | E15: =C15*D15 -> 446400 | F15: ATW | G15: Tayo-INV139 | I15: Maltina Can | J15: =C15+C28 -> 51 | K15: =E15+E28 -> 709400 | L15: =K15/K$27 -> 0.1578955
A16: 46218 | B16: Heineken Can 50cl | C16: 10 | D16: 23770 | E16: =C16*D16 -> 237700 | F16: ATW | G16: Tayo-INV139 | I16: Heineken Can 50cl | J16: =C16 -> 10 | K16: =E16 -> 237700 | L16: =K16/K$27 -> 0.052906343
A17: 46218 | B17: Heineken Sleek Can | C17: 10 | D17: 17845 | E17: =C17*D17 -> 178450 | F17: ATW | G17: Tayo-INV139 | I17: Heineken Sleek Can | J17: =C17 -> 10 | K17: =E17 -> 178450 | L17: =K17/K$27 -> 0.039718708
A18: 46218 | B18: Chamdor 75cl | C18: 2 | D18: 28445 | E18: =C18*D18 -> 56890 | F18: ATW | G18: Tayo-INV139 | I18: Chamdor 75cl | J18: =C18 -> 2 | K18: =E18 -> 56890 | L18: =K18/K$27 -> 0.012662355
A19: 46218 | B19: 4th Street wine | C19: 2 | D19: 24185 | E19: =C19*D19 -> 48370 | F19: ATW | G19: Tayo-INV139 | I19: 4th Street wine | J19: =C19 -> 2 | K19: =E19 -> 48370 | L19: =K19/K$27 -> 0.010766007
A20: 46218 | B20: Star Radler 45cl | C20: 5 | D20: 15115 | E20: =C20*D20 -> 75575 | F20: ATW | G20: Tayo-INV139 | I20: Star Radler 45cl | J20: =C20 -> 5 | K20: =E20 -> 75575 | L20: =K20/K$27 -> 0.01682119
A21: 46218 | B21: ACE BITTERS | C21: 1 | D21: 20655 | E21: =C21*D21 -> 20655 | F21: Mr Godswill | G21: ann-INV279 | I21: ACE BITTERS | J21: =C21 -> 1 | K21: =E21 -> 20655 | L21: =K21/K$27 -> 0.0045973097
A22: 46218 | B22: Amstel Bottle | C22: 1 | D22: 14450 | E22: =C22*D22 -> 14450 | F22: Jeff SR | G22: ann-INV280 | I22: Amstel Bottle | J22: =C22 -> 1 | K22: =E22 -> 14450 | L22: =K22/K$27 -> 0.0032162249
A23: 46218 | B23: Goldberg 60cl | C23: 2 | D23: 9200 | E23: =C23*D23 -> 18400 | F23: Jeff SR | G23: ann-INV280 | I23: Goldberg 60cl | J23: =C23+C30 -> 3 | K23: =E23+E30 -> 27600 | L23: =K23/K$27 -> 0.0061431009
A24: 46218 | B24: 33 Export 60cl | C24: 2 | D24: 9200 | E24: =C24*D24 -> 18400 | F24: Jeff SR | G24: ann-INV280 | I24: 33 Export 60cl | J24: =C24+C31 -> 3 | K24: =E24+E31 -> 27600 | L24: =K24/K$27 -> 0.0061431009
A25: 46218 | B25: Turbo King Bottle 60cl | C25: 1 | D25: 9200 | E25: =C25*D25 -> 9200 | F25: Jeff SR | G25: ann-INV280 | I25: Turbo King Bottle 60cl | J25: =C25 -> 1 | K25: =E25 -> 9200 | L25: =K25/K$27 -> 0.0020477003
A26: 46218 | B26: Heineken Bottle 60cl | C26: 2 | D26: 13335 | E26: =C26*D26 -> 26670 | F26: Jeff SR | G26: ann-INV280 | I26: Trophy | J26: =C32 -> 1 | K26: =E32 -> 9000 | L26: =K26/K$27 -> 0.0020031851
A27: 46218 | B27: Maltina Pet 33cl | C27: 70 | D27: 5000 | E27: =C27*D27 -> 350000 | F27: Eniola Marketer | G27: ann-INV281 | I27: Grand Total | J27: =SUM(J2:J26) -> 364 | K27: =SUM(K2:K26) -> 4492845 | L27: =K27/K$27 -> 1
A28: 46218 | B28: Maltina Can | C28: 20 | D28: 13150 | E28: =C28*D28 -> 263000 | F28: Eniola Marketer | G28: ann-INV281
A29: 46218 | B29: Heineken Bottle 60cl | C29: 1 | D29: 13350 | E29: =C29*D29 -> 13350 | F29: Walk in Customer | G29: ann-INV282 | I29: Customer | J29: Amount_NGN | K29: % of Total Revenue | L29: Gross Profit
A30: 46218 | B30: Goldberg 60cl | C30: 1 | D30: 9200 | E30: =C30*D30 -> 9200 | F30: Walk in Customer | G30: ann-INV282 | I30: ATW | J30: =E2+E3+E4+E5+E6+E7+E8+E9+E10+E11+E12+E13+E14+E15+E16+E17+E18+E19+E20 -> 3731320 | K30: =J30/J$35 -> 0.83050272 | L30: 0.0713
A31: 46218 | B31: 33 Export 60cl | C31: 1 | D31: 9200 | E31: =C31*D31 -> 9200 | F31: Walk in Customer | G31: ann-INV282 | I31: Mr Godswill | J31: =E21 -> 20655 | K31: =J31/J$35 -> 0.0045973097 | L31: 0.0654
A32: 46218 | B32: Trophy | C32: 1 | D32: 9000 | E32: =C32*D32 -> 9000 | F32: Walk in Customer | G32: ann-INV282 | I32: Jeff SR | J32: =E22+E23+E24+E25+E26 -> 87120 | K32: =J32/J$35 -> 0.019390831 | L32: 0.0462
B33: Grand Total | C33: =SUM(C2:C32) -> 364 | D33: =SUM(D2:D32) -> 455207 | E33: =SUM(E2:E32) -> 4492845 | I33: Eniola Marketer | J33: =E27+E28 -> 613000 | K33: =J33/J$35 -> 0.13643916 | L33: -0.0343
I34: Walk in Customer | J34: =E29+E30+E31+E32 -> 40750 | K34: =J34/J$35 -> 0.0090699768 | L34: 0.0548
I35: Total | J35: =SUM(J30:J34) -> 4492845 | K35: =J35/J$35 -> 1
I37: Invoice No | J37: Amount_NGN | K37: Gross Profit
I38: Tayo-INV139 | J38: 3865320 | K38: 0.07
I39: ann-INV279 | J39: 20655 | K39: 0.07
I40: ann-INV280 | J40: 87120 | K40: 0.05
I41: ann-INV281 | J41: 613000 | K41: -0.03
I42: ann-INV282 | J42: 40750 | K42: 0.05
I43: Total | J43: =SUM(J38:J42) -> 4626845

Sheet July 16th Sales Report
A1: Date | B1: Product | C1: Cases_Sold | D1: Unit_Price_NGN | E1: Amount_NGN | F1: Customer | G1: Invoice No | I1: Product | J1: Quantity | K1: Revenue | L1: % of Total Revenue | N1: Total Revnue | O1: Total Cases Sold | P1: Total transaction
A2: 46219 | B2: Desperados Can | C2: 5 | D2: 22740 | E2: =C2*D2 -> 113700 | F2: Taiwo SR | G2: ann-INV283 | I2: Desperados Can | J2: =C2 -> 5 | K2: =E2 -> 113700 | L2: =K2/K$15 -> 0.04303786 | N2: =K15 -> 2641860 | O2: =J15 -> 267 | P2: =COUNT(J2:J14) -> 13
A3: 46219 | B3: CLIMAX CAN | C3: 5 | D3: 12885 | E3: =C3*D3 -> 64425 | F3: Taiwo SR | G3: ann-INV283 | I3: CLIMAX CAN | J3: =C3 -> 5 | K3: =E3 -> 64425 | L3: =K3/K$15 -> 0.024386228
A4: 46219 | B4: Maltina Pet 33cl | C4: 1 | D4: 5300 | E4: =C4*D4 -> 5300 | F4: Walk in Customer | G4: ann-INV284 | I4: Maltina Pet 33cl | J4: =C4+C5+C10+C12 -> 104 | K4: =E4+E5+E10+E12 -> 521200 | L4: =K4/K$15 -> 0.19728525
A5: 46219 | B5: Maltina Pet 33cl | C5: 100 | D5: 5000 | E5: =C5*D5 -> 500000 | F5: Rita SR | G5: ann-INV285 | I5: Goldberg Can 50cl | J5: =C6 -> 30 | K5: =E6 -> 469650 | L5: =K5/K$15 -> 0.17777248
A6: 46219 | B6: Goldberg Can 50cl | C6: 30 | D6: 15655 | E6: =C6*D6 -> 469650 | F6: Rita SR | G6: ann-INV285 | I6: Heineken Sleek Can | J6: =C7 -> 15 | K6: =E7 -> 258000 | L6: =K6/K$15 -> 0.097658468
A7: 46219 | B7: Heineken Sleek Can | C7: 15 | D7: 17200 | E7: =C7*D7 -> 258000 | F7: Rita SR | G7: ann-INV285 | I7: 33 Export Can | J7: =C8 -> 25 | K7: =E8 -> 391375 | L7: =K7/K$15 -> 0.14814373
A8: 46219 | B8: 33 Export Can | C8: 25 | D8: 15655 | E8: =C8*D8 -> 391375 | F8: Rita SR | G8: ann-INV285 | I8: Maltina Can | J8: =C9 -> 20 | K8: =E9 -> 258000 | L8: =K8/K$15 -> 0.097658468
A9: 46219 | B9: Maltina Can | C9: 20 | D9: 12900 | E9: =C9*D9 -> 258000 | F9: Rita SR | G9: ann-INV285 | I9: Fayrouz Can | J9: =C11 -> 1 | K9: =E11 -> 13460 | L9: =K9/K$15 -> 0.0050948953
A10: 46219 | B10: Maltina Pet 33cl | C10: 2 | D10: 5300 | E10: =C10*D10 -> 10600 | F10: Walk in Customer | G10: ann-INV286 | I10: Goldberg 60cl | J10: =C13+C16+C20 -> 28 | K10: =E13+E16+E20 -> 257600 | L10: =K10/K$15 -> 0.097507059
A11: 46219 | B11: Fayrouz Can | C11: 1 | D11: 13460 | E11: =C11*D11 -> 13460 | F11: Walk in Customer | G11: ann-INV286 | I11: Trophy | J11: =C14+C17 -> 26 | K11: =E14+E17 -> 214000 | L11: =K11/K$15 -> 0.081003535
A12: 46219 | B12: Maltina Pet 33cl | C12: 1 | D12: 5300 | E12: =C12*D12 -> 5300 | F12: Walk in Customer | G12: ann-INV287 | I12: 33 Export 60cl | J12: =C15+C21 -> 6 | K12: =E15+E21 -> 55500 | L12: =K12/K$15 -> 0.021007926
A13: 46219 | B13: Goldberg 60cl | C13: 25 | D13: 9200 | E13: =C13*D13 -> 230000 | F13: Eniola Marketer | G13: ann-INV288 | I13: Heineken Bottle 60cl | J13: =C18 -> 1 | K13: =E18 -> 13350 | L13: =K13/K$15 -> 0.0050532579
A14: 46219 | B14: Trophy | C14: 25 | D14: 8200 | E14: =C14*D14 -> 205000 | F14: Eniola Marketer | G14: ann-INV288 | I14: Star Bottle 60cl | J14: =C19 -> 1 | K14: =E19 -> 11600 | L14: =K14/K$15 -> 0.0043908458
A15: 46219 | B15: 33 Export 60cl | C15: 5 | D15: 9200 | E15: =C15*D15 -> 46000 | F15: Eniola Marketer | G15: ann-INV288 | I15: Grand Total | J15: =SUM(J2:J14) -> 267 | K15: =SUM(K2:K14) -> 2641860 | L15: =K15/K$15 -> 1
A16: 46219 | B16: Goldberg 60cl | C16: 2 | D16: 9200 | E16: =C16*D16 -> 18400 | F16: MRS IK. | G16: ann-INV289
A17: 46219 | B17: Trophy | C17: 1 | D17: 9000 | E17: =C17*D17 -> 9000 | F17: MRS IK. | G17: ann-INV289 | I17: Customer | J17: Amount_NGN | K17: % of Total Revenue | L17: Gross Profit
A18: 46219 | B18: Heineken Bottle 60cl | C18: 1 | D18: 13350 | E18: =C18*D18 -> 13350 | F18: Walk in Customer | G18: ann-INV290 | I18: Taiwo SR | J18: =E2+E3 -> 178125 | K18: =J18/J$24 -> 0.067424088 | L18: 0.0536
A19: 46219 | B19: Star Bottle 60cl | C19: 1 | D19: 11600 | E19: =C19*D19 -> 11600 | F19: Walk in Customer | G19: ann-INV290 | I19: Walk in Customer | J19: =E4+E10+E11+E12+E18+E19+E20 -> 68810 | K19: =J19/J$24 -> 0.026046043 | L19: 0.0381
A20: 46219 | B20: Goldberg 60cl | C20: 1 | D20: 9200 | E20: =C20*D20 -> 9200 | F20: Walk in Customer | G20: ann-INV291 | I20: Rita SR | J20: =E5+E6+E7+E8+E9 -> 1877025 | K20: =J20/J$24 -> 0.71049374 | L20: -0.0084
A21: 46219 | B21: 33 Export 60cl | C21: 1 | D21: 9500 | E21: =C21*D21 -> 9500 | F21: Remilekun | G21: ann-INV292 | I21: Eniola Marketer | J21: =E13+E14+E15 -> 481000 | K21: =J21/J$24 -> 0.18206869 | L21: 0.0438
B22: Grand Total | C22: =SUM(C2:C21) -> 267 | D22: =SUM(D2:D21) -> 219845 | E22: =SUM(E2:E21) -> 2641860 | I22: MRS IK. | J22: =E16+E17 -> 27400 | K22: =J22/J$24 -> 0.010371481 | L22: 0.0717
I23: Remilekun | J23: =E21 -> 9500 | K23: =J23/J$24 -> 0.0035959513 | L23: 0.0537
I24: Total | J24: =SUM(J18:J23) -> 2641860 | K24: =J24/J$24 -> 1
I26: Invoice No | J26: Amount_NGN | K26: Gross Profit
I27: ann-INV283 | J27: 178125 | K27: 0.05
I28: ann-INV284 | J28: 5300 | K28: 0.02
I29: ann-INV285 | J29: 1877025 | K29: -0.01
I30: ann-INV286 | J30: 24060 | K30: 0.03
I31: ann-INV287 | J31: 5300 | K31: 0.02
I32: ann-INV288 | J32: 575000 | K32: 0.04
I33: ann-INV289 | J33: 27400 | K33: 0.07
I34: ann-INV290 | J34: 24950 | K34: 0.04
I35: ann-INV291 | J35: 9200 | K35: 0.06
I36: ann-INV292 | J36: 9500 | K36: 0.05
I37: Total | J37: =SUM(J27:J36) -> 2735860

Sheet July 17th Sales Report
A1: Date | B1: Product | C1: Cases_Sold | D1: Unit_Price_NGN | E1: Amount_NGN | F1: Customer | G1: Invoice No | I1: Product | J1: Quantity | K1: Revenue | L1: % of Total Revenue | N1: Total Revnue | O1: Total Cases Sold | P1: Total transaction
A2: 46220 | B2: Maltina Can | C2: 30 | D2: 12900 | E2: =C2*D2 -> 387000 | F2: Rita SR | G2: ann-INV293 | I2: Maltina Can | J2: =C2+C4+C27 -> 56 | K2: =E2+E4+E27 -> 722700 | L2: =K2/K$19 -> 0.11725186 | N2: =K19 -> 6163655 | O2: =J19 -> 798 | P2: =COUNT(J2:J18) -> 17
A3: 46220 | B3: Fayrouz Can | C3: 30 | D3: 13100 | E3: =C3*D3 -> 393000 | F3: Rita SR | G3: ann-INV293 | I3: Fayrouz Can | J3: =C3+C5+C11 -> 32 | K3: =E3+E5+E11 -> 419920 | L3: =K3/K$19 -> 0.068128408
A4: 46220 | B4: Maltina Can | C4: 25 | D4: 12900 | E4: =C4*D4 -> 322500 | F4: Rita SR | G4: ann-INV296 | I4: Goldberg 60cl | J4: =C6+C16 -> 23 | K4: =E6+E16 -> 202800 | L4: =K4/K$19 -> 0.032902555
A5: 46220 | B5: Fayrouz Can | C5: 1 | D5: 13460 | E5: =C5*D5 -> 13460 | F5: Mr Godswill | G5: ann-INV297 | I5: Heineken Bottle 60cl | J5: =C7+C14+C21 -> 9 | K5: =E7+E14+E21 -> 121860 | L5: =K5/K$19 -> 0.019770737
A6: 46220 | B6: Goldberg 60cl | C6: 22 | D6: 8800 | E6: =C6*D6 -> 193600 | F6: Ameh Mathew | G6: ann-INV294 | I6: Turbo King Bottle 60cl | J6: =C8+C18 -> 10 | K6: =E8+E18 -> 89120 | L6: =K6/K$19 -> 0.014458953
A7: 46220 | B7: Heineken Bottle 60cl | C7: 6 | D7: 13335 | E7: =C7*D7 -> 80010 | F7: Ameh Mathew | G7: ann-INV294 | I7: 33 Export 60cl | J7: =C9+C15+C17 -> 16 | K7: =E9+E15+E17 -> 147500 | L7: =K7/K$19 -> 0.023930606
A8: 46220 | B8: Turbo King Bottle 60cl | C8: 9 | D8: 8880 | E8: =C8*D8 -> 79920 | F8: Ameh Mathew | G8: ann-INV294 | I8: Maltina Pet 33cl | J8: =C10+C25+C28 -> 251 | K8: =E10+E25+E28 -> 1255300 | L8: =K8/K$19 -> 0.20366163
A9: 46220 | B9: 33 Export 60cl | C9: 14 | D9: 9200 | E9: =C9*D9 -> 128800 | F9: Ameh Mathew | G9: ann-INV294 | I9: Gulder Bottle | J9: =C12+C22 -> 3 | K9: =E12+E22 -> 35730 | L9: =K9/K$19 -> 0.0057968851
A10: 46220 | B10: Maltina Pet 33cl | C10: 50 | D10: 5000 | E10: =C10*D10 -> 250000 | F10: Ameh Mathew | G10: ann-INV294 | I10: Budweiser | J10: =C13 -> 1 | K10: =E13 -> 11320 | L10: =K10/K$19 -> 0.0018365726
A11: 46220 | B11: Fayrouz Can | C11: 1 | D11: 13460 | E11: =C11*D11 -> 13460 | F11: Ameh Mathew | G11: ann-INV294 | I11: Trophy | J11: =C19 -> 1 | K11: =E19 -> 9000 | L11: =K11/K$19 -> 0.0014601726
A12: 46220 | B12: Gulder Bottle | C12: 2 | D12: 11910 | E12: =C12*D12 -> 23820 | F12: Ameh Mathew | G12: ann-INV294 | I12: Medium Stout | J12: =C20 -> 1 | K12: =E20 -> 18300 | L12: =K12/K$19 -> 0.0029690176
A13: 46220 | B13: Budweiser | C13: 1 | D13: 11320 | E13: =C13*D13 -> 11320 | F13: Walk in Customer | G13: ann-INV295 | I13: Desperados Bottle | J13: =C23 -> 1 | K13: =E23 -> 21400 | L13: =K13/K$19 -> 0.0034719659
A14: 46220 | B14: Heineken Bottle 60cl | C14: 2 | D14: 13950 | E14: =C14*D14 -> 27900 | F14: Walk in Customer | G14: ann-INV295 | I14: Star Bottle 60cl | J14: =C24+C29 -> 6 | K14: =E24+E29 -> 69600 | L14: =K14/K$19 -> 0.011292001
A15: 46220 | B15: 33 Export 60cl | C15: 1 | D15: 9500 | E15: =C15*D15 -> 9500 | F15: Walk in Customer | G15: ann-INV295 | I15: Maltina Pet 50cl | J15: =C26 -> 384 | K15: =E26 -> 2976000 | L15: =K15/K$19 -> 0.4828304
A16: 46220 | B16: Goldberg 60cl | C16: 1 | D16: 9200 | E16: =C16*D16 -> 9200 | F16: MRS IK. | G16: ann-INV298 | I16: Legend Bottle 60cl | J16: =C30 -> 1 | K16: =E30 -> 11480 | L16: =K16/K$19 -> 0.0018625312
A17: 46220 | B17: 33 Export 60cl | C17: 1 | D17: 9200 | E17: =C17*D17 -> 9200 | F17: MRS IK. | G17: ann-INV298 | I17: Legend 45cl | J17: =C31 -> 1 | K17: =E31 -> 15945 | L17: =K17/K$19 -> 0.0025869391
A18: 46220 | B18: Turbo King Bottle 60cl | C18: 1 | D18: 9200 | E18: =C18*D18 -> 9200 | F18: MRS IK. | G18: ann-INV298 | I18: Heineken Bottle 45cl | J18: =C32 -> 2 | K18: =E32 -> 35680 | L18: =K18/K$19 -> 0.0057887731
A19: 46220 | B19: Trophy | C19: 1 | D19: 9000 | E19: =C19*D19 -> 9000 | F19: MRS IK. | G19: ann-INV298 | I19: Grand Total | J19: =SUM(J2:J18) -> 798 | K19: =SUM(K2:K18) -> 6163655 | L19: =K19/K$19 -> 1
A20: 46220 | B20: Medium Stout | C20: 1 | D20: 18300 | E20: =C20*D20 -> 18300 | F20: MRS IK. | G20: ann-INV298
A21: 46220 | B21: Heineken Bottle 60cl | C21: 1 | D21: 13950 | E21: =C21*D21 -> 13950 | F21: MRS IK. | G21: ann-INV298 | I21: Customer | J21: Amount_NGN | K21: % of Total Revenue | L21: Gross Profit
A22: 46220 | B22: Gulder Bottle | C22: 1 | D22: 11910 | E22: =C22*D22 -> 11910 | F22: MRS IK. | G22: ann-INV298 | I22: Rita SR | J22: =E2+E3+E4 -> 1102500 | K22: =J22/J$30 -> 0.17887114 | L22: -0.0233
A23: 46220 | B23: Desperados Bottle | C23: 1 | D23: 21400 | E23: =C23*D23 -> 21400 | F23: MRS IK. | G23: ann-INV298 | I23: Mr Godswill | J23: =E5 -> 13460 | K23: =J23/J$30 -> 0.0021837692 | L23: 0.0449
A24: 46220 | B24: Star Bottle 60cl | C24: 2 | D24: 11600 | E24: =C24*D24 -> 23200 | F24: MRS IK. | G24: ann-INV298 | I24: Ameh Mathew | J24: =E6+E7+E8+E9+E10+E11+E12+E32 -> 805290 | K24: =J24/J$30 -> 0.13065137 | L24: 0.0378
A25: 46220 | B25: Maltina Pet 33cl | C25: 1 | D25: 5300 | E25: =C25*D25 -> 5300 | F25: MRS IK. | G25: ann-INV298 | I25: Walk in Customer | J25: =E13+E14+E15 -> 48720 | K25: =J25/J$30 -> 0.0079044009 | L25: 0.0785
A26: 46220 | B26: Maltina Pet 50cl | C26: 384 | D26: 7750 | E26: =C26*D26 -> 2976000 | F26: OGUNDE SR | G26: ann-INV299 | I26: MRS IK. | J26: =E16+E17+E18+E19+E20+E21+E22+E23+E24+E25 -> 130660 | K26: =J26/J$30 -> 0.021198461 | L26: 0.0701
A27: 46220 | B27: Maltina Can | C27: 1 | D27: 13200 | E27: =C27*D27 -> 13200 | F27: Ola SR | G27: ann-INV300 | I27: OGUNDE SR | J27: =E26 -> 2976000 | K27: =J27/J$30 -> 0.4828304 | L27: 0.0084
A28: 46220 | B28: Maltina Pet 33cl | C28: 200 | D28: 5000 | E28: =C28*D28 -> 1000000 | F28: Eniola Marketer | G28: ann-INV301 | I28: Ola SR | J28: =E27+E29+E30+E31 -> 87025 | K28: =J28/J$30 -> 0.014119058 | L28: 0.0453
A29: 46220 | B29: Star Bottle 60cl | C29: 4 | D29: 11600 | E29: =C29*D29 -> 46400 | F29: Ola SR | G29: ann-INV302 | I29: Eniola Marketer | J29: =E28 -> 1000000 | K29: =J29/J$30 -> 0.1622414 | L29: -0.04
A30: 46220 | B30: Legend Bottle 60cl | C30: 1 | D30: 11480 | E30: =C30*D30 -> 11480 | F30: Ola SR | G30: ann-INV302 | I30: Total | J30: =SUM(J22:J29) -> 6163655 | K30: =J30/J$30 -> 1
A31: 46220 | B31: Legend 45cl | C31: 1 | D31: 15945 | E31: =C31*D31 -> 15945 | F31: Ola SR | G31: ann-INV302
A32: 46220 | B32: Heineken Bottle 45cl | C32: 2 | D32: 17840 | E32: =C32*D32 -> 35680 | F32: Ameh Mathew | G32: ann-INV303 | I32: Invoice No | J32: Amount_NGN | K32: Gross Profit
B33: Grand Total | C33: =SUM(C2:C32) -> 798 | D33: =SUM(D2:D32) -> 359590 | E33: =SUM(E2:E32) -> 6163655 | I33: ann-INV293 | J33: 780000 | K33: -0.01
I34: ann-INV296 | J34: 322500 | K34: -0.05
I35: ann-INV297 | J35: 13460 | K35: 0.04
I36: ann-INV294 | J36: 866210 | K36: 0.03
I37: ann-INV295 | J37: 48720 | K37: 0.08
I38: ann-INV298 | J38: 134460 | K38: 0.07
I39: ann-INV299 | J39: 2976000 | K39: 0.01
I40: ann-INV300 | J40: 13200 | K40: -0.02
I41: ann-INV301 | J41: 1000000 | K41: -0.04
I42: ann-INV302 | J42: 84625 | K42: 0.06
I43: ann-INV303 | J43: 39680 | K43: 0.12
I44: Total | J44: =SUM(J33:J43) -> 6278855

Sheet July 18th Sales Report
A1: Date | B1: Product | C1: Cases_Sold | D1: Unit_Price_NGN | E1: Amount_NGN | F1: Customer | G1: Invoice No | I1: Product | J1: Quantity | K1: Revenue | L1: % of Total Revenue | N1: Total Revnue | O1: Total Cases Sold | P1: Total transaction
A2: 46221 | B2: Heineken Bottle 60cl | C2: 140 | D2: 12730 | E2: =C2*D2 -> 1782200 | F2: Abbey Illisan | G2: ann-INV304 | I2: Heineken Bottle 60cl | J2: =C2+C13+C17+C27+C35 -> 304 | K2: =E2+E13+E17+E27+E35 -> 3898440 | L2: =K2/K$21 -> 0.30804375 | N2: =K21 -> 12655475 | O2: =J21 -> 1117 | P2: =COUNT(J2:J20) -> 19
A3: 46221 | B3: 33 Export 60cl | C3: 140 | D3: 8990 | E3: =C3*D3 -> 1258600 | F3: Abbey Illisan | G3: ann-INV304 | I3: 33 Export 60cl | J3: =C3+C15+C33 -> 155 | K3: =E3+E15+E33 -> 1395500 | L3: =K3/K$21 -> 0.11026848
A4: 46221 | B4: Tiger Bottle | C4: 60 | D4: 14900 | E4: =C4*D4 -> 894000 | F4: Abbey Illisan | G4: ann-INV304 | I4: Tiger Bottle | J4: =C4+C22 -> 62 | K4: =E4+E22 -> 925050 | L4: =K4/K$21 -> 0.073094846
A5: 46221 | B5: Star Radler 45cl | C5: 60 | D5: 14475 | E5: =C5*D5 -> 868500 | F5: Abbey Illisan | G5: ann-INV304 | I5: Star Radler 45cl | J5: =C5+C18+C29 -> 91 | K5: =E5+E18+E29 -> 1320325 | L5: =K5/K$21 -> 0.10432836
A6: 46221 | B6: Maltina Can | C6: 45 | D6: 13150 | E6: =C6*D6 -> 591750 | F6: Eniola Marketer | G6: ann-INV305 | I6: Maltina Can | J6: =C6 -> 45 | K6: =E6 -> 591750 | L6: =K6/K$21 -> 0.046758419
A7: 46221 | B7: Heineken Sleek Can | C7: 10 | D7: 17845 | E7: =C7*D7 -> 178450 | F7: Eniola Marketer | G7: ann-INV305 | I7: Heineken Sleek Can | J7: =C7 -> 10 | K7: =E7 -> 178450 | L7: =K7/K$21 -> 0.014100617
A8: 46221 | B8: Goldberg Can 50cl | C8: 10 | D8: 16145 | E8: =C8*D8 -> 161450 | F8: Eniola Marketer | G8: ann-INV305 | I8: Goldberg Can 50cl | J8: =C8 -> 10 | K8: =E8 -> 161450 | L8: =K8/K$21 -> 0.012757324
A9: 46221 | B9: Fayrouz Can | C9: 10 | D9: 13460 | E9: =C9*D9 -> 134600 | F9: Eniola Marketer | G9: ann-INV306 | I9: Fayrouz Can | J9: =C9 -> 10 | K9: =E9 -> 134600 | L9: =K9/K$21 -> 0.010635713
A10: 46221 | B10: Medium Stout | C10: 10 | D10: 17700 | E10: =C10*D10 -> 177000 | F10: Eniola Marketer | G10: ann-INV306 | I10: Medium Stout | J10: =C10+C32+C34 -> 31 | K10: =E10+E32+E34 -> 551300 | L10: =K10/K$21 -> 0.043562174
A11: 46221 | B11: Goldberg 60cl | C11: 20 | D11: 8800 | E11: =C11*D11 -> 176000 | F11: Rita SR | G11: ann-INV311 | I11: Goldberg 60cl | J11: =C11+C16+C26+C36+C39 -> 179 | K11: =E11+E16+E26+E36+E39 -> 1537880 | L11: =K11/K$21 -> 0.12151895
A12: 46221 | B12: Star Bottle 60cl | C12: 10 | D12: 11600 | E12: =C12*D12 -> 116000 | F12: Rita SR | G12: ann-INV310 | I12: Star Bottle 60cl | J12: =C12 -> 10 | K12: =E12 -> 116000 | L12: =K12/K$21 -> 0.0091659934
A13: 46221 | B13: Heineken Bottle 60cl | C13: 20 | D13: 13335 | E13: =C13*D13 -> 266700 | F13: Rita SR | G13: ann-INV310 | I13: Turbo King Bottle 60cl | J13: =C14+C19+C28+C37 -> 75 | K13: =E14+E19+E28+E37 -> 666620 | L13: =K13/K$21 -> 0.052674435
A14: 46221 | B14: Turbo King Bottle 60cl | C14: 2 | D14: 8880 | E14: =C14*D14 -> 17760 | F14: Ameh Mathew | G14: ann-INV309 | I14: Williams Bottle 60cl | J14: =C20 -> 1 | K14: =E20 -> 9345 | L14: =K14/K$21 -> 0.00073841559
A15: 46221 | B15: 33 Export 60cl | C15: 5 | D15: 9200 | E15: =C15*D15 -> 46000 | F15: Ameh Mathew | G15: ann-INV312 | I15: Desperados Bottle | J15: =C21 -> 1 | K15: =E21 -> 21400 | L15: =K15/K$21 -> 0.0016909677
A16: 46221 | B16: Goldberg 60cl | C16: 10 | D16: 8800 | E16: =C16*D16 -> 88000 | F16: Ameh Mathew | G16: ann-INV312 | I16: Gulder Bottle | J16: =C23 -> 2 | K16: =E23 -> 23820 | L16: =K16/K$21 -> 0.0018821893
A17: 46221 | B17: Heineken Bottle 60cl | C17: 3 | D17: 13335 | E17: =C17*D17 -> 40005 | F17: Ameh Mathew | G17: ann-INV312 | I17: Legend 45cl | J17: =C24 -> 1 | K17: =E24 -> 15945 | L17: =K17/K$21 -> 0.001259929
A18: 46221 | B18: Star Radler 45cl | C18: 1 | D18: 14575 | E18: =C18*D18 -> 14575 | F18: Ameh Mathew | G18: ann-INV312 | I18: Maltina Pet 33cl | J18: =C25+C31 -> 30 | K18: =E25+E31 -> 150000 | L18: =K18/K$21 -> 0.011852578
A19: 46221 | B19: Turbo King Bottle 60cl | C19: 2 | D19: 8880 | E19: =C19*D19 -> 17760 | F19: Ameh Mathew | G19: ann-INV312 | I19: Maltina Bottle | J19: =C30 -> 30 | K19: =E30 -> 390600 | L19: =K19/K$21 -> 0.030864112
A20: 46221 | B20: Williams Bottle 60cl | C20: 1 | D20: 9345 | E20: =C20*D20 -> 9345 | F20: Ameh Mathew | G20: ann-INV312 | I20: Trophy | J20: =C38 -> 70 | K20: =E38 -> 567000 | L20: =K20/K$21 -> 0.044802743
A21: 46221 | B21: Desperados Bottle | C21: 1 | D21: 21400 | E21: =C21*D21 -> 21400 | F21: Ameh Mathew | G21: ann-INV312 | I21: Grand Total | J21: =SUM(J2:J20) -> 1117 | K21: =SUM(K2:K20) -> 12655475 | L21: =K21/K$21 -> 1
A22: 46221 | B22: Tiger Bottle | C22: 2 | D22: 15525 | E22: =C22*D22 -> 31050 | F22: Ameh Mathew | G22: ann-INV312
A23: 46221 | B23: Gulder Bottle | C23: 2 | D23: 11910 | E23: =C23*D23 -> 23820 | F23: Ameh Mathew | G23: ann-INV312 | I23: Customer | J23: Amount_NGN | K23: % of Total Revenue | L23: Gross Profit
A24: 46221 | B24: Legend 45cl | C24: 1 | D24: 15945 | E24: =C24*D24 -> 15945 | F24: Ameh Mathew | G24: ann-INV312 | I24: Abbey Illisan | J24: =E2+E3+E4+E5 -> 4803300 | K24: =J24/J$33 -> 0.37954324 | L24: 0.0603
A25: 46221 | B25: Maltina Pet 33cl | C25: 20 | D25: 5000 | E25: =C25*D25 -> 100000 | F25: Ameh Mathew | G25: ann-INV312 | I25: Eniola Marketer | J25: =E6+E7+E8+E9+E10 -> 1243250 | K25: =J25/J$33 -> 0.098238114 | L25: 0.0761
A26: 46221 | B26: Goldberg 60cl | C26: 140 | D26: 8500 | E26: =C26*D26 -> 1190000 | F26: Alhaja GRA Road | G26: ann-INV316 | I26: Rita SR | J26: =E11+E12+E13+E31 -> 608700 | K26: =J26/J$33 -> 0.04809776 | L26: 0.0903
A27: 46221 | B27: Heineken Bottle 60cl | C27: 140 | D27: 12830 | E27: =C27*D27 -> 1796200 | F27: Alhaja GRA Road | G27: ann-INV316 | I27: Ameh Mathew | J27: =E14+E15+E16+E17+E18+E19+E20+E21+E22+E23+E24+E25 -> 425660 | K27: =J27/J$33 -> 0.033634455 | L27: 0.0396
A28: 46221 | B28: Turbo King Bottle 60cl | C28: 70 | D28: 8880 | E28: =C28*D28 -> 621600 | F28: Alhaja GRA Road | G28: ann-INV316 | I28: Alhaja GRA Road | J28: =E26+E27+E28+E29+E30 -> 4435650 | K28: =J28/J$33 -> 0.35049257 | L28: 0.0694
A29: 46221 | B29: Star Radler 45cl | C29: 30 | D29: 14575 | E29: =C29*D29 -> 437250 | F29: Alhaja GRA Road | G29: ann-INV316 | I29: LAKE AND RIVER FOODS | J29: =E32+E33+E38 -> 1013900 | K29: =J29/J$33 -> 0.080115523 | L29: 0.1509
A30: 46221 | B30: Maltina Bottle | C30: 30 | D30: 13020 | E30: =C30*D30 -> 390600 | F30: Alhaja GRA Road | G30: ann-INV316 | I30: MAADE HOTEL | J30: =E34+E35+E36 -> 40835 | K30: =J30/J$33 -> 0.0032266667 | L30: 0.0559
A31: 46221 | B31: Maltina Pet 33cl | C31: 10 | D31: 5000 | E31: =C31*D31 -> 50000 | F31: Rita SR | G31: ann-INV313 | I31: Remilekun | J31: =E37 -> 9500 | K31: =J31/J$33 -> 0.00075066325 | L31: 0.1026
A32: 46221 | B32: Medium Stout | C32: 20 | D32: 17800 | E32: =C32*D32 -> 356000 | F32: LAKE AND RIVER FOODS | G32: ann-INV314 | I32: June Target Achievement Incentive Scheme | J32: =E39 -> 74680 | K32: =J32/J$33 -> 0.0059010033 | L32: 0.0727
A33: 46221 | B33: 33 Export 60cl | C33: 10 | D33: 9090 | E33: =C33*D33 -> 90900 | F33: LAKE AND RIVER FOODS | G33: ann-INV314 | I33: Total | J33: =SUM(J24:J32) -> 12655475 | K33: =J33/J$33 -> 1
A34: 46221 | B34: Medium Stout | C34: 1 | D34: 18300 | E34: =C34*D34 -> 18300 | F34: MAADE HOTEL | G34: ann-INV308
A35: 46221 | B35: Heineken Bottle 60cl | C35: 1 | D35: 13335 | E35: =C35*D35 -> 13335 | F35: MAADE HOTEL | G35: ann-INV308 | I35: Invoice No | J35: Amount_NGN | K35: Gross Profit
A36: 46221 | B36: Goldberg 60cl | C36: 1 | D36: 9200 | E36: =C36*D36 -> 9200 | F36: MAADE HOTEL | G36: ann-INV308 | I36: ann-INV304 | J36: 5551300 | K36: 0.06
A37: 46221 | B37: Turbo King Bottle 60cl | C37: 1 | D37: 9500 | E37: =C37*D37 -> 9500 | F37: Remilekun | G37: ann-INV315 | I37: ann-INV305 | J37: 931650 | K37: 0
A38: 46221 | B38: Trophy | C38: 70 | D38: 8100 | E38: =C38*D38 -> 567000 | F38: LAKE AND RIVER FOODS | G38: ann-INV307 | I38: ann-INV306 | J38: 361600 | K38: 0.27
A39: 46221 | B39: Goldberg 60cl | C39: 8 | D39: 9335 | E39: =C39*D39 -> 74680 | F39: June Target Achievement Incentive Scheme | G39: ann-INV317 | I39: ann-INV311 | J39: 212000 | K39: 0.04
B40: Grand Total | C40: =SUM(C2:C39) -> 1117 | D40: =SUM(D2:D39) -> 463390 | E40: =SUM(E2:E39) -> 12655475 | I40: ann-INV310 | J40: 440700 | K40: 0.13
I41: ann-INV309 | J41: 17760 | K41: 0.04
I42: ann-INV312 | J42: 458900 | K42: 0.04
I43: ann-INV316 | J43: 5201650 | K43: 0.07
I44: ann-INV313 | J44: 50000 | K44: -0.04
I45: ann-INV314 | J45: 564900 | K45: 0.34
I46: ann-INV308 | J46: 40835 | K46: 0.06
I47: ann-INV315 | J47: 9500 | K47: 0.1
I48: ann-INV307 | J48: 679000 | K48: 0
I49: ann-INV317 | J49: 74680 | K49: 0.07
I50: Total | J50: =SUM(J36:J49) -> 14594475

Sheet July 19th Sales Report
A1: July 19th, 2026
A2: No sales recorded - store closed (Sunday).

Sheet July 20th Sales Report
A1: Date | B1: Product | C1: Cases_Sold | D1: Unit_Price_NGN | E1: Amount_NGN | F1: Customer | G1: Invoice No | I1: Product | J1: Quantity | K1: Revenue | L1: % of Total Revenue | N1: Total Revnue | O1: Total Cases Sold | P1: Total transaction
A2: 46223 | B2: Goldberg 60cl | C2: 3 | D2: 9200 | E2: =C2*D2 -> 27600 | F2: Mr Olayinka | G2: ann-INV318 | I2: Goldberg 60cl | J2: =C2+C5+C8+C12+C18+C27 -> 536 | K2: =E2+E5+E8+E12+E18+E27 -> 4586400 | L2: =K2/K$21 -> 0.46233172 | N2: =K21 -> 9920150 | O2: =J21 -> 1200 | P2: =COUNT(J2:J20) -> 19
A3: 46223 | B3: Trophy | C3: 3 | D3: 9000 | E3: =C3*D3 -> 27000 | F3: Mr Olayinka | G3: ann-INV318 | I3: Trophy | J3: =C3+C7+C34 -> 41 | K3: =E3+E7+E34 -> 339400 | L3: =K3/K$21 -> 0.034213192
A4: 46223 | B4: Maltina Pet 33cl | C4: 248 | D4: 5000 | E4: =C4*D4 -> 1240000 | F4: Rita SR | G4: ann-INV321 | I4: Maltina Pet 33cl | J4: =C4+C21+C25+C35 -> 335 | K4: =E4+E21+E25+E35 -> 1675600 | L4: =K4/K$21 -> 0.16890874
A5: 46223 | B5: Goldberg 60cl | C5: 350 | D5: 8500 | E5: =C5*D5 -> 2975000 | F5: Delayers | G5: ann-INV319 | I5: 33 Export 60cl | J5: =C6+C13+C17 -> 82 | K5: =E6+E13+E17 -> 746700 | L5: =K5/K$21 -> 0.075271039
A6: 46223 | B6: 33 Export 60cl | C6: 70 | D6: 9090 | E6: =C6*D6 -> 636300 | F6: Delayers | G6: ann-INV319 | I6: Heineken Bottle 60cl | J6: =C9+C26 -> 55 | K6: =E9+E26 -> 712770 | L6: =K6/K$21 -> 0.071850728
A7: 46223 | B7: Trophy | C7: 30 | D7: 8200 | E7: =C7*D7 -> 246000 | F7: Eniola Marketer | G7: ann-INV325 | I7: Fayrouz Bottle | J7: =C10+C33 -> 12 | K7: =E10+E33 -> 121880 | L7: =K7/K$21 -> 0.012286105
A8: 46223 | B8: Goldberg 60cl | C8: 15 | D8: 9200 | E8: =C8*D8 -> 138000 | F8: Eniola Marketer | G8: ann-INV325 | I8: Desperados Bottle | J8: =C11+C32 -> 13 | K8: =E11+E32 -> 268910 | L8: =K8/K$21 -> 0.027107453
A9: 46223 | B9: Heineken Bottle 60cl | C9: 4 | D9: 13335 | E9: =C9*D9 -> 53340 | F9: Solomon | G9: ann-INV323 | I9: Heineken Sleek Can | J9: =C14+C23 -> 13 | K9: =E14+E23 -> 222300 | L9: =K9/K$21 -> 0.022408935
A10: 46223 | B10: Fayrouz Bottle | C10: 2 | D10: 10315 | E10: =C10*D10 -> 20630 | F10: Solomon | G10: ann-INV323 | I10: Desperados Can | J10: =C15 -> 1 | K10: =E15 -> 21695 | L10: =K10/K$21 -> 0.0021869629
A11: 46223 | B11: Desperados Bottle | C11: 2 | D11: 21485 | E11: =C11*D11 -> 42970 | F11: Solomon | G11: ann-INV323 | I11: Goldberg Can 50cl | J11: =C16 -> 1 | K11: =E16 -> 16145 | L11: =K11/K$21 -> 0.0016274956
A12: 46223 | B12: Goldberg 60cl | C12: 1 | D12: 9200 | E12: =C12*D12 -> 9200 | F12: Solomon | G12: ann-INV323 | I12: Gulder Bottle | J12: =C19+C30 -> 13 | K12: =E19+E30 -> 149385 | L12: =K12/K$21 -> 0.015058744
A13: 46223 | B13: 33 Export 60cl | C13: 1 | D13: 9200 | E13: =C13*D13 -> 9200 | F13: Solomon | G13: ann-INV323 | I13: Star Radler 45cl | J13: =C20+C31 -> 6 | K13: =E20+E31 -> 87950 | L13: =K13/K$21 -> 0.0088657934
A14: 46223 | B14: Heineken Sleek Can | C14: 3 | D14: 17100 | E14: =C14*D14 -> 51300 | F14: Ameh Mathew | G14: ann-INV320 | I14: Maltina Can | J14: =C22 -> 10 | K14: =E22 -> 132000 | L14: =K14/K$21 -> 0.01330625
A15: 46223 | B15: Desperados Can | C15: 1 | D15: 21695 | E15: =C15*D15 -> 21695 | F15: Ameh Mathew | G15: ann-INV320 | I15: CLIMAX CAN | J15: =C24 -> 1 | K15: =E24 -> 12885 | L15: =K15/K$21 -> 0.0012988715
A16: 46223 | B16: Goldberg Can 50cl | C16: 1 | D16: 16145 | E16: =C16*D16 -> 16145 | F16: Ameh Mathew | G16: ann-INV320 | I16: Maltina Bottle | J16: =C28 -> 20 | K16: =E28 -> 260400 | L16: =K16/K$21 -> 0.026249603
A17: 46223 | B17: 33 Export 60cl | C17: 11 | D17: 9200 | E17: =C17*D17 -> 101200 | F17: Ameh Mathew | G17: ann-INV324 | I17: Star Bottle 60cl | J17: =C29 -> 15 | K17: =E29 -> 169950 | L17: =K17/K$21 -> 0.017131797
A18: 46223 | B18: Goldberg 60cl | C18: 2 | D18: 8800 | E18: =C18*D18 -> 17600 | F18: Ameh Mathew | G18: ann-INV324 | I18: Maltina Pet 50cl | J18: =C36 -> 15 | K18: =E36 -> 120300 | L18: =K18/K$21 -> 0.012126833
A19: 46223 | B19: Gulder Bottle | C19: 2 | D19: 11910 | E19: =C19*D19 -> 23820 | F19: Ameh Mathew | G19: ann-INV324 | I19: Turbo King Bottle 60cl | J19: =C37 -> 30 | K19: =E37 -> 264000 | L19: =K19/K$21 -> 0.026612501
A20: 46223 | B20: Star Radler 45cl | C20: 1 | D20: 14575 | E20: =C20*D20 -> 14575 | F20: Ameh Mathew | G20: ann-INV324 | I20: Legend Bottle 60cl | J20: =C38 -> 1 | K20: =E38 -> 11480 | L20: =K20/K$21 -> 0.0011572406
A21: 46223 | B21: Maltina Pet 33cl | C21: 80 | D21: 5000 | E21: =C21*D21 -> 400000 | F21: Ameh Mathew | G21: ann-INV324 | I21: Grand Total | J21: =SUM(J2:J20) -> 1200 | K21: =SUM(K2:K20) -> 9920150 | L21: =K21/K$21 -> 1
A22: 46223 | B22: Maltina Can | C22: 10 | D22: 13200 | E22: =C22*D22 -> 132000 | F22: Ameh Mathew | G22: ann-INV324
A23: 46223 | B23: Heineken Sleek Can | C23: 10 | D23: 17100 | E23: =C23*D23 -> 171000 | F23: Ameh Mathew | G23: ann-INV324 | I23: Customer | J23: Amount_NGN | K23: % of Total Revenue | L23: Gross Profit
A24: 46223 | B24: CLIMAX CAN | C24: 1 | D24: 12885 | E24: =C24*D24 -> 12885 | F24: Tmoney NB | G24: ann-INV326 | I24: Mr Olayinka | J24: =E2+E3 -> 54600 | K24: =J24/J$33 -> 0.005503949 | L24: 0.0781
A25: 46223 | B25: Maltina Pet 33cl | C25: 2 | D25: 5300 | E25: =C25*D25 -> 10600 | F25: Walk in Customer | G25: ann-INV327 | I25: Rita SR | J25: =E4 -> 1240000 | K25: =J25/J$33 -> 0.12499811 | L25: -0.04
A26: 46223 | B26: Heineken Bottle 60cl | C26: 51 | D26: 12930 | E26: =C26*D26 -> 659430 | F26: Emmycee | G26: ann-INV328 | I26: Delayers | J26: =E5+E6 -> 3611300 | K26: =J26/J$33 -> 0.36403683 | L26: -0.0133
A27: 46223 | B27: Goldberg 60cl | C27: 165 | D27: 8600 | E27: =C27*D27 -> 1419000 | F27: Emmycee | G27: ann-INV328 | I27: Eniola Marketer | J27: =E7+E8 -> 384000 | K27: =J27/J$33 -> 0.038709092 | L27: 0.0322
A28: 46223 | B28: Maltina Bottle | C28: 20 | D28: 13020 | E28: =C28*D28 -> 260400 | F28: Emmycee | G28: ann-INV328 | I28: Solomon | J28: =E9+E10+E11+E12+E13 -> 135340 | K28: =J28/J$33 -> 0.013642939 | L28: 0.119
A29: 46223 | B29: Star Bottle 60cl | C29: 15 | D29: 11330 | E29: =C29*D29 -> 169950 | F29: Emmycee | G29: ann-INV328 | I29: Ameh Mathew | J29: =E14+E15+E16+E17+E18+E19+E20+E21+E22+E23 -> 949335 | K29: =J29/J$33 -> 0.095697646 | L29: -0.0098
A30: 46223 | B30: Gulder Bottle | C30: 11 | D30: 11415 | E30: =C30*D30 -> 125565 | F30: Emmycee | G30: ann-INV328 | I30: Tmoney NB | J30: =E24 -> 12885 | K30: =J30/J$33 -> 0.0012988715 | L30: 0.0594
A31: 46223 | B31: Star Radler 45cl | C31: 5 | D31: 14675 | E31: =C31*D31 -> 73375 | F31: Emmycee | G31: ann-INV328 | I31: Walk in Customer | J31: =E25 -> 10600 | K31: =J31/J$33 -> 0.0010685322 | L31: 0.0189
A32: 46223 | B32: Desperados Bottle | C32: 11 | D32: 20540 | E32: =C32*D32 -> 225940 | F32: Emmycee | G32: ann-INV328 | I32: Emmycee | J32: =E26+E27+E28+E29+E30+E31+E32+E33+E34+E35+E36+E37+E38 -> 3522090 | K32: =J32/J$33 -> 0.35504403 | L32: 0.052
A33: 46223 | B33: Fayrouz Bottle | C33: 10 | D33: 10125 | E33: =C33*D33 -> 101250 | F33: Emmycee | G33: ann-INV328 | I33: Total | J33: =SUM(J24:J32) -> 9920150 | K33: =J33/J$33 -> 1
A34: 46223 | B34: Trophy | C34: 8 | D34: 8300 | E34: =C34*D34 -> 66400 | F34: Emmycee | G34: ann-INV328
A35: 46223 | B35: Maltina Pet 33cl | C35: 5 | D35: 5000 | E35: =C35*D35 -> 25000 | F35: Emmycee | G35: ann-INV328 | I35: Invoice No | J35: Amount_NGN | K35: Gross Profit
A36: 46223 | B36: Maltina Pet 50cl | C36: 15 | D36: 8020 | E36: =C36*D36 -> 120300 | F36: Emmycee | G36: ann-INV328 | I36: ann-INV318 | J36: 54600 | K36: 0.08
A37: 46223 | B37: Turbo King Bottle 60cl | C37: 30 | D37: 8800 | E37: =C37*D37 -> 264000 | F37: Emmycee | G37: ann-INV328 | I37: ann-INV321 | J37: 1240000 | K37: -0.04
A38: 46223 | B38: Legend Bottle 60cl | C38: 1 | D38: 11480 | E38: =C38*D38 -> 11480 | F38: Emmycee | G38: ann-INV328 | I38: ann-INV319 | J38: 3611300 | K38: -0.01
B39: Grand Total | C39: =SUM(C2:C38) -> 1200 | D39: =SUM(D2:D38) -> 418870 | E39: =SUM(E2:E38) -> 9920150 | I39: ann-INV325 | J39: 459000 | K39: 0.03
I40: ann-INV323 | J40: 154540 | K40: 0.12
I41: ann-INV320 | J41: 89140 | K41: 0.01
I42: ann-INV324 | J42: 888995 | K42: -0.01
I43: ann-INV326 | J43: 12885 | K43: 0.06
I44: ann-INV327 | J44: 10600 | K44: 0.02
I45: ann-INV328 | J45: 4121490 | K45: 0.05
I46: Total | J46: =SUM(J36:J45) -> 10642550

Sheet July 21st Sales Report
A1: Date | B1: Product | C1: Cases_Sold | D1: Unit_Price_NGN | E1: Amount_NGN | F1: Customer | G1: Invoice No | I1: Product | J1: Quantity | K1: Revenue | L1: % of Total Revenue | N1: Total Revnue | O1: Total Cases Sold | P1: Total transaction
A2: 46224 | B2: Maltina Pet 33cl | C2: 120 | D2: 5000 | E2: =C2*D2 -> 600000 | F2: Rita SR | G2: ann-INV329 | I2: Maltina Pet 33cl | J2: =C2+C15+C16+C25+C29+C30 -> 380 | K2: =E2+E15+E16+E25+E29+E30 -> 1900300 | L2: =K2/K$19 -> 0.66006589 | N2: =K19 -> 2878955 | O2: =J19 -> 461 | P2: =COUNT(J2:J18) -> 17
A3: 46224 | B3: 33 Export 60cl | C3: 10 | D3: 9200 | E3: =C3*D3 -> 92000 | F3: Rita SR | G3: ann-INV330 | I3: 33 Export 60cl | J3: =C3+C23 -> 11 | K3: =E3+E23 -> 101200 | L3: =K3/K$19 -> 0.035151644
A4: 46224 | B4: Desperados Bottle | C4: 5 | D4: 21400 | E4: =C4*D4 -> 107000 | F4: Rita SR | G4: ann-INV330 | I4: Desperados Bottle | J4: =C4+C18 -> 8 | K4: =E4+E18 -> 174695 | L4: =K4/K$19 -> 0.060680004
A5: 46224 | B5: Turbo King Bottle 60cl | C5: 5 | D5: 9200 | E5: =C5*D5 -> 46000 | F5: Rita SR | G5: ann-INV330 | I5: Turbo King Bottle 60cl | J5: =C5 -> 5 | K5: =E5 -> 46000 | L5: =K5/K$19 -> 0.01597802
A6: 46224 | B6: Amstel Bottle | C6: 2 | D6: 14450 | E6: =C6*D6 -> 28900 | F6: Rita SR | G6: ann-INV330 | I6: Amstel Bottle | J6: =C6 -> 2 | K6: =E6 -> 28900 | L6: =K6/K$19 -> 0.010038365
A7: 46224 | B7: Fayrouz Bottle | C7: 1 | D7: 10315 | E7: =C7*D7 -> 10315 | F7: Rita SR | G7: ann-INV330 | I7: Fayrouz Bottle | J7: =C7 -> 1 | K7: =E7 -> 10315 | L7: =K7/K$19 -> 0.0035828973
A8: 46224 | B8: Goldberg 60cl | C8: 18 | D8: 8800 | E8: =C8*D8 -> 158400 | F8: Ameh Mathew | G8: ann-INV332 | I8: Goldberg 60cl | J8: =C8+C24+C28 -> 21 | K8: =E8+E24+E28 -> 186000 | L8: =K8/K$19 -> 0.064606776
A9: 46224 | B9: Heineken Bottle 60cl | C9: 4 | D9: 13335 | E9: =C9*D9 -> 53340 | F9: Ameh Mathew | G9: ann-INV332 | I9: Heineken Bottle 60cl | J9: =C9+C20+C22+C27 -> 9 | K9: =E9+E20+E22+E27 -> 122475 | L9: =K9/K$19 -> 0.042541478
A10: 46224 | B10: Maltina Can | C10: 3 | D10: 13200 | E10: =C10*D10 -> 39600 | F10: Ameh Mathew | G10: ann-INV332 | I10: Maltina Can | J10: =C10 -> 3 | K10: =E10 -> 39600 | L10: =K10/K$19 -> 0.013754991
A11: 46224 | B11: Fayrouz Can | C11: 2 | D11: 13460 | E11: =C11*D11 -> 26920 | F11: Ameh Mathew | G11: ann-INV332 | I11: Fayrouz Can | J11: =C11 -> 2 | K11: =E11 -> 26920 | L11: =K11/K$19 -> 0.0093506151
A12: 46224 | B12: CLIMAX CAN | C12: 1 | D12: 12885 | E12: =C12*D12 -> 12885 | F12: Ameh Mathew | G12: ann-INV332 | I12: CLIMAX CAN | J12: =C12 -> 1 | K12: =E12 -> 12885 | L12: =K12/K$19 -> 0.0044755823
A13: 46224 | B13: Goldberg Can 50cl | C13: 2 | D13: 16145 | E13: =C13*D13 -> 32290 | F13: Ameh Mathew | G13: ann-INV332 | I13: Goldberg Can 50cl | J13: =C13 -> 2 | K13: =E13 -> 32290 | L13: =K13/K$19 -> 0.011215875
A14: 46224 | B14: 33 Export Can | C14: 2 | D14: 16145 | E14: =C14*D14 -> 32290 | F14: Ameh Mathew | G14: ann-INV332 | I14: 33 Export Can | J14: =C14 -> 2 | K14: =E14 -> 32290 | L14: =K14/K$19 -> 0.011215875
A15: 46224 | B15: Maltina Pet 33cl | C15: 3 | D15: 5000 | E15: =C15*D15 -> 15000 | F15: Ameh Mathew | G15: ann-INV332 | I15: Desperados Can | J15: =C17 -> 1 | K15: =E17 -> 22740 | L15: =K15/K$19 -> 0.0078986994
A16: 46224 | B16: Maltina Pet 33cl | C16: 240 | D16: 5000 | E16: =C16*D16 -> 1200000 | F16: Eniola Marketer | G16: ann-INV333 | I16: Star Radler 45cl | J16: =C19+C32 -> 5 | K16: =E19+E32 -> 76245 | L16: =K16/K$19 -> 0.026483568
A17: 46224 | B17: Desperados Can | C17: 1 | D17: 22740 | E17: =C17*D17 -> 22740 | F17: XXIII LOUNGE | G17: ann-INV337 | I17: Trophy | J17: =C21+C26 -> 3 | K17: =E21+E26 -> 26000 | L17: =K17/K$19 -> 0.0090310547
A18: 46224 | B18: Desperados Bottle | C18: 3 | D18: 22565 | E18: =C18*D18 -> 67695 | F18: XXIII LOUNGE | G18: ann-INV337 | I18: Maltina Pet 50cl | J18: =C31 -> 5 | K18: =E31 -> 40100 | L18: =K18/K$19 -> 0.013928665
A19: 46224 | B19: Star Radler 45cl | C19: 3 | D19: 15765 | E19: =C19*D19 -> 47295 | F19: XXIII LOUNGE | G19: ann-INV337 | I19: Grand Total | J19: =SUM(J2:J18) -> 461 | K19: =SUM(K2:K18) -> 2878955 | L19: =K19/K$19 -> 1
A20: 46224 | B20: Heineken Bottle 60cl | C20: 3 | D20: 13950 | E20: =C20*D20 -> 41850 | F20: XXIII LOUNGE | G20: ann-INV337
A21: 46224 | B21: Trophy | C21: 1 | D21: 9000 | E21: =C21*D21 -> 9000 | F21: MRS IK. | G21: ann-INV335 | I21: Customer | J21: Amount_NGN | K21: % of Total Revenue | L21: Gross Profit
A22: 46224 | B22: Heineken Bottle 60cl | C22: 1 | D22: 13950 | E22: =C22*D22 -> 13950 | F22: MRS IK. | G22: ann-INV335 | I22: Rita SR | J22: =E2+E3+E4+E5+E6+E7 -> 884215 | K22: =J22/J$30 -> 0.30713054 | L22: 0.0027
A23: 46224 | B23: 33 Export 60cl | C23: 1 | D23: 9200 | E23: =C23*D23 -> 9200 | F23: MRS IK. | G23: ann-INV335 | I23: Ameh Mathew | J23: =E8+E9+E10+E11+E12+E13+E14+E15 -> 370725 | K23: =J23/J$30 -> 0.12877068 | L23: 0.0511
A24: 46224 | B24: Goldberg 60cl | C24: 1 | D24: 9200 | E24: =C24*D24 -> 9200 | F24: MRS IK. | G24: ann-INV335 | I24: Eniola Marketer | J24: =E16 -> 1200000 | K24: =J24/J$30 -> 0.41681791 | L24: -0.04
A25: 46224 | B25: Maltina Pet 33cl | C25: 1 | D25: 5300 | E25: =C25*D25 -> 5300 | F25: MRS IK. | G25: ann-INV335 | I25: XXIII LOUNGE | J25: =E17+E18+E19+E20 -> 179580 | K25: =J25/J$30 -> 0.0623768 | L25: 0.1377
A26: 46224 | B26: Trophy | C26: 2 | D26: 8500 | E26: =C26*D26 -> 17000 | F26: MAADE HOTEL | G26: ann-INV334 | I26: MRS IK. | J26: =E21+E22+E23+E24+E25 -> 46650 | K26: =J26/J$30 -> 0.016203796 | L26: 0.0629
A27: 46224 | B27: Heineken Bottle 60cl | C27: 1 | D27: 13335 | E27: =C27*D27 -> 13335 | F27: MAADE HOTEL | G27: ann-INV334 | I27: MAADE HOTEL | J27: =E26+E27+E28 -> 48735 | K27: =J27/J$30 -> 0.016928017 | L27: 0.0499
A28: 46224 | B28: Goldberg 60cl | C28: 2 | D28: 9200 | E28: =C28*D28 -> 18400 | F28: MAADE HOTEL | G28: ann-INV334 | I28: Solomon | J28: =E29+E32 -> 33950 | K28: =J28/J$30 -> 0.011792473 | L28: 0.0099
A29: 46224 | B29: Maltina Pet 33cl | C29: 1 | D29: 5000 | E29: =C29*D29 -> 5000 | F29: Solomon | G29: ann-INV336 | I29: Jeff SR | J29: =E30+E31 -> 115100 | K29: =J29/J$30 -> 0.039979784 | L29: -0.0115
A30: 46224 | B30: Maltina Pet 33cl | C30: 15 | D30: 5000 | E30: =C30*D30 -> 75000 | F30: Jeff SR | G30: ann-INV338 | I30: Total | J30: =SUM(J22:J29) -> 2878955 | K30: =J30/J$30 -> 1
A31: 46224 | B31: Maltina Pet 50cl | C31: 5 | D31: 8020 | E31: =C31*D31 -> 40100 | F31: Jeff SR | G31: ann-INV338
A32: 46224 | B32: Star Radler 45cl | C32: 2 | D32: 14475 | E32: =C32*D32 -> 28950 | F32: Solomon | G32: ann-INV331 | I32: Invoice No | J32: Amount_NGN | K32: Gross Profit
B33: Grand Total | C33: =SUM(C2:C32) -> 461 | D33: =SUM(D2:D32) -> 358735 | E33: =SUM(E2:E32) -> 2878955 | I33: ann-INV329 | J33: 600000 | K33: -0.04
I34: ann-INV330 | J34: 326615 | K34: 0.08
I35: ann-INV332 | J35: 411125 | K35: 0.05
I36: ann-INV333 | J36: 1200000 | K36: -0.04
I37: ann-INV337 | J37: 196980 | K37: 0.14
I38: ann-INV335 | J38: 46650 | K38: 0.06
I39: ann-INV334 | J39: 48735 | K39: 0.05
I40: ann-INV336 | J40: 5000 | K40: -0.04
I41: ann-INV338 | J41: 115100 | K41: -0.01
I42: ann-INV331 | J42: 32550 | K42: 0.02
I43: Total | J43: =SUM(J33:J42) -> 2982755

Sheet July 22nd Sales Report
A1: Date | B1: Product | C1: Cases_Sold | D1: Unit_Price_NGN | E1: Amount_NGN | F1: Customer | G1: Invoice No | I1: Product | J1: Quantity | K1: Revenue | L1: % of Total Revenue | N1: Total Revenue | O1: Total Cases Sold | P1: Total transaction
A2: 46225 | B2: 33 Export Can | C2: 30 | D2: 15655 | E2: =C2*D2 -> 469650 | F2: Rita SR | G2: ann-INV340 | I2: 33 Export Can | J2: =C2 -> 30 | K2: =E2 -> 469650 | L2: =K2/K$15 -> 0.087165682 | N2: =K15 -> 5388015 | O2: =J15 -> 778 | P2: =COUNT(J2:J14) -> 13
A3: 46225 | B3: Goldberg Can 50cl | C3: 15 | D3: 15655 | E3: =C3*D3 -> 234825 | F3: Rita SR | G3: ann-INV340 | I3: Goldberg Can 50cl | J3: =C3 -> 15 | K3: =E3 -> 234825 | L3: =K3/K$15 -> 0.043582841
A4: 46225 | B4: Fayrouz Can | C4: 20 | D4: 13100 | E4: =C4*D4 -> 262000 | F4: Rita SR | G4: ann-INV340 | I4: Fayrouz Can | J4: =C4+C18 -> 21 | K4: =E4+E18 -> 275460 | L4: =K4/K$15 -> 0.051124579
A5: 46225 | B5: Heineken Sleek Can | C5: 40 | D5: 17200 | E5: =C5*D5 -> 688000 | F5: Rita SR | G5: ann-INV340 | I5: Heineken Sleek Can | J5: =C5 -> 40 | K5: =E5 -> 688000 | L5: =K5/K$15 -> 0.12769081
A6: 46225 | B6: Maltina Pet 33cl | C6: 40 | D6: 5000 | E6: =C6*D6 -> 200000 | F6: ATW | G6: ann-INV342 | I6: Maltina Pet 33cl | J6: =C6+C7+C9+C12 -> 598 | K6: =E6+E7+E9+E12 -> 2990000 | L6: =K6/K$15 -> 0.55493535
A7: 46225 | B7: Maltina Pet 33cl | C7: 100 | D7: 5000 | E7: =C7*D7 -> 500000 | F7: Stella SR | G7: ann-INV341 | I7: Goldberg 60cl | J7: =C8+C14+C17+C21 -> 64 | K7: =E8+E14+E17+E21 -> 589700 | L7: =K7/K$15 -> 0.10944661
A8: 46225 | B8: Goldberg 60cl | C8: 2 | D8: 9500 | E8: =C8*D8 -> 19000 | F8: Walk in Customer | G8: ann-INV343 | I8: Chamdor 75cl | J8: =C10 -> 1 | K8: =E10 -> 28445 | L8: =K8/K$15 -> 0.0052793097
A9: 46225 | B9: Maltina Pet 33cl | C9: 248 | D9: 5000 | E9: =C9*D9 -> 1240000 | F9: Rita SR | G9: ann-INV339 | I9: 4th Street wine | J9: =C11 -> 1 | K9: =E11 -> 24235 | L9: =K9/K$15 -> 0.0044979459
A10: 46225 | B10: Chamdor 75cl | C10: 1 | D10: 28445 | E10: =C10*D10 -> 28445 | F10: Eniola Marketer | G10: ann-INV345 | I10: Trophy | J10: =C13+C22 -> 2 | K10: =E13+E22 -> 18000 | L10: =K10/K$15 -> 0.0033407479
A11: 46225 | B11: 4th Street wine | C11: 1 | D11: 24235 | E11: =C11*D11 -> 24235 | F11: Eniola Marketer | G11: ann-INV345 | I11: 33 Export 60cl | J11: =C15+C20 -> 2 | K11: =E15+E20 -> 18700 | L11: =K11/K$15 -> 0.0034706659
A12: 46225 | B12: Maltina Pet 33cl | C12: 210 | D12: 5000 | E12: =C12*D12 -> 1050000 | F12: Eniola Marketer | G12: ann-INV344 | I12: Heineken Bottle 60cl | J12: =C16+C19 -> 2 | K12: =E16+E19 -> 27900 | L12: =K12/K$15 -> 0.0051781593
A13: 46225 | B13: Trophy | C13: 1 | D13: 9000 | E13: =C13*D13 -> 9000 | F13: Walk in Customer | G13: ann-INV346 | I13: STK 33cl | J13: =C23 -> 1 | K13: =E23 -> 13900 | L13: =K13/K$15 -> 0.0025797998
A14: 46225 | B14: Goldberg 60cl | C14: 1 | D14: 9500 | E14: =C14*D14 -> 9500 | F14: Walk in Customer | G14: ann-INV346 | I14: Turbo King Bottle 60cl | J14: =C24 -> 1 | K14: =E24 -> 9200 | L14: =K14/K$15 -> 0.0017074934
A15: 46225 | B15: 33 Export 60cl | C15: 1 | D15: 9500 | E15: =C15*D15 -> 9500 | F15: Walk in Customer | G15: ann-INV346 | I15: Grand Total | J15: =SUM(J2:J14) -> 778 | K15: =SUM(K2:K14) -> 5388015 | L15: =K15/K$15 -> 1
A16: 46225 | B16: Heineken Bottle 60cl | C16: 1 | D16: 13950 | E16: =C16*D16 -> 13950 | F16: Walk in Customer | G16: ann-INV346
A17: 46225 | B17: Goldberg 60cl | C17: 60 | D17: 9200 | E17: =C17*D17 -> 552000 | F17: ATW | G17: ann-INV347 | I17: Customer | J17: Amount_NGN | K17: % of Total Revenue | L17: Gross Profit
A18: 46225 | B18: Fayrouz Can | C18: 1 | D18: 13460 | E18: =C18*D18 -> 13460 | F18: MRS IK. | G18: ann-INV348 | I18: Rita SR | J18: =E2+E3+E4+E5+E9 -> 2894475 | K18: =J18/J$24 -> 0.53720619 | L18: -0.0109
A19: 46225 | B19: Heineken Bottle 60cl | C19: 1 | D19: 13950 | E19: =C19*D19 -> 13950 | F19: MRS IK. | G19: ann-INV348 | I19: ATW | J19: =E6+E17 -> 752000 | K19: =J19/J$24 -> 0.13956902 | L19: 0.0327
A20: 46225 | B20: 33 Export 60cl | C20: 1 | D20: 9200 | E20: =C20*D20 -> 9200 | F20: MRS IK. | G20: ann-INV348 | I20: Stella SR | J20: =E7 -> 500000 | K20: =J20/J$24 -> 0.092798554 | L20: -0.04
A21: 46225 | B21: Goldberg 60cl | C21: 1 | D21: 9200 | E21: =C21*D21 -> 9200 | F21: MRS IK. | G21: ann-INV348 | I21: Walk in Customer | J21: =E8+E13+E14+E15+E16+E23+E24 -> 84050 | K21: =J21/J$24 -> 0.015599437 | L21: 0.0869
A22: 46225 | B22: Trophy | C22: 1 | D22: 9000 | E22: =C22*D22 -> 9000 | F22: MRS IK. | G22: ann-INV348 | I22: Eniola Marketer | J22: =E10+E11+E12 -> 1102680 | K22: =J22/J$24 -> 0.20465422 | L22: -0.034
A23: 46225 | B23: STK 33cl | C23: 1 | D23: 13900 | E23: =C23*D23 -> 13900 | F23: Walk in Customer | G23: ann-INV349 | I23: MRS IK. | J23: =E18+E19+E20+E21+E22 -> 54810 | K23: =J23/J$24 -> 0.010172577 | L23: 0.0627
A24: 46225 | B24: Turbo King Bottle 60cl | C24: 1 | D24: 9200 | E24: =C24*D24 -> 9200 | F24: Walk in Customer | G24: ann-INV349 | I24: Total | J24: =SUM(J18:J23) -> 5388015 | K24: =J24/J$24 -> 1
B25: Grand Total | C25: =SUM(C2:C24) -> 778 | D25: =SUM(D2:D24) -> 272850 | E25: =SUM(E2:E24) -> 5388015
I26: Invoice No | J26: Amount_NGN | K26: Gross Profit
I27: ann-INV340 | J27: 1654475 | K27: 0.01
I28: ann-INV342 | J28: 200000 | K28: -0.04
I29: ann-INV341 | J29: 500000 | K29: -0.04
I30: ann-INV343 | J30: 19000 | K30: 0.09
I31: ann-INV339 | J31: 1240000 | K31: -0.04
I32: ann-INV345 | J32: 52680 | K32: 0.09
I33: ann-INV344 | J33: 1050000 | K33: -0.04
I34: ann-INV346 | J34: 41950 | K34: 0.08
I35: ann-INV347 | J35: 552000 | K35: 0.06
I36: ann-INV348 | J36: 54810 | K36: 0.06
I37: ann-INV349 | J37: 23100 | K37: 0.09
I38: Total | J38: =SUM(J27:J37) -> 5388015

Sheet July 23rd Sales Report
A1: Date | B1: Product | C1: Cases_Sold | D1: Unit_Price_NGN | E1: Amount_NGN | F1: Customer | G1: Invoice No | I1: Product | J1: Quantity | K1: Revenue | L1: % of Total Revenue | N1: Total Revnue | O1: Total Cases Sold | P1: Total transaction
A2: 46226 | B2: Maltina Pet 33cl | C2: 496 | D2: 5000 | E2: =C2*D2 -> 2480000 | F2: Rita SR | G2: ann-INV350 | I2: Maltina Pet 33cl | J2: =C2+C4+C19 -> 804 | K2: =E2+E4+E19 -> 4020000 | L2: =K2/K$15 -> 0.78393365 | N2: =K15 -> 5127985 | O2: =J15 -> 916 | P2: =COUNT(J2:J14) -> 13
A3: 46226 | B3: Maltina Bottle | C3: 5 | D3: 13550 | E3: =C3*D3 -> 67750 | F3: Rita SR | G3: ann-INV351 | I3: Maltina Bottle | J3: =C3 -> 5 | K3: =E3 -> 67750 | L3: =K3/K$15 -> 0.013211817
A4: 46226 | B4: Maltina Pet 33cl | C4: 248 | D4: 5000 | E4: =C4*D4 -> 1240000 | F4: Eniola Marketer | G4: ann-INV352 | I4: Goldberg 60cl | J4: =C5+C8+C13+C20+C22 -> 51 | K4: =E5+E8+E13+E20+E22 -> 465740 | L4: =K4/K$15 -> 0.090823199
A5: 46226 | B5: Goldberg 60cl | C5: 4 | D5: 9335 | E5: =C5*D5 -> 37340 | F5: June Target Achievement Incentive Scheme | G5: Tayo-INV141 | I5: Heineken Bottle 60cl | J5: =C6+C18 -> 9 | K5: =E6+E18 -> 120015 | L5: =K5/K$15 -> 0.02340393
A6: 46226 | B6: Heineken Bottle 60cl | C6: 5 | D6: 13335 | E6: =C6*D6 -> 66675 | F6: Ameh Mathew | G6: ann-INV353 | I6: 33 Export 60cl | J6: =C7+C14 -> 16 | K6: =E7+E14 -> 147200 | L6: =K6/K$15 -> 0.028705232
A7: 46226 | B7: 33 Export 60cl | C7: 10 | D7: 9200 | E7: =C7*D7 -> 92000 | F7: Ameh Mathew | G7: ann-INV353 | I7: Desperados Bottle | J7: =C9 -> 1 | K7: =E9 -> 21400 | L7: =K7/K$15 -> 0.0041731791
A8: 46226 | B8: Goldberg 60cl | C8: 10 | D8: 8800 | E8: =C8*D8 -> 88000 | F8: Ameh Mathew | G8: ann-INV353 | I8: Tiger Bottle | J8: =C10 -> 2 | K8: =E10 -> 31050 | L8: =K8/K$15 -> 0.0060550099
A9: 46226 | B9: Desperados Bottle | C9: 1 | D9: 21400 | E9: =C9*D9 -> 21400 | F9: Ameh Mathew | G9: ann-INV353 | I9: Fayrouz Can | J9: =C11 -> 1 | K9: =E11 -> 13460 | L9: =K9/K$15 -> 0.0026248127
A10: 46226 | B10: Tiger Bottle | C10: 2 | D10: 15525 | E10: =C10*D10 -> 31050 | F10: Ameh Mathew | G10: ann-INV353 | I10: Gulder Bottle | J10: =C12 -> 2 | K10: =E12 -> 23820 | L10: =K10/K$15 -> 0.0046450994
A11: 46226 | B11: Fayrouz Can | C11: 1 | D11: 13460 | E11: =C11*D11 -> 13460 | F11: Ameh Mathew | G11: ann-INV353 | I11: Turbo King Bottle 60cl | J11: =C15 -> 5 | K11: =E15 -> 44400 | L11: =K11/K$15 -> 0.0086583717
A12: 46226 | B12: Gulder Bottle | C12: 2 | D12: 11910 | E12: =C12*D12 -> 23820 | F12: Ameh Mathew | G12: ann-INV353 | I12: Legend Bottle 60cl | J12: =C16 -> 2 | K12: =E16 -> 22960 | L12: =K12/K$15 -> 0.0044773922
A13: 46226 | B13: Goldberg 60cl | C13: 20 | D13: 9200 | E13: =C13*D13 -> 184000 | F13: Ahmed SR | G13: ann-INV354 | I13: Williams Bottle 60cl | J13: =C17 -> 2 | K13: =E17 -> 18690 | L13: =K13/K$15 -> 0.0036447064
A14: 46226 | B14: 33 Export 60cl | C14: 6 | D14: 9200 | E14: =C14*D14 -> 55200 | F14: Ahmed SR | G14: ann-INV354 | I14: Trophy | J14: =C21+C23 -> 16 | K14: =E21+E23 -> 131500 | L14: =K14/K$15 -> 0.025643601
A15: 46226 | B15: Turbo King Bottle 60cl | C15: 5 | D15: 8880 | E15: =C15*D15 -> 44400 | F15: Ahmed SR | G15: ann-INV354 | I15: Grand Total | J15: =SUM(J2:J14) -> 916 | K15: =SUM(K2:K14) -> 5127985 | L15: =K15/K$15 -> 1
A16: 46226 | B16: Legend Bottle 60cl | C16: 2 | D16: 11480 | E16: =C16*D16 -> 22960 | F16: Ahmed SR | G16: ann-INV354
A17: 46226 | B17: Williams Bottle 60cl | C17: 2 | D17: 9345 | E17: =C17*D17 -> 18690 | F17: Ahmed SR | G17: ann-INV354 | I17: Customer | J17: Amount_NGN | K17: % of Total Revenue | L17: Gross Profit
A18: 46226 | B18: Heineken Bottle 60cl | C18: 4 | D18: 13335 | E18: =C18*D18 -> 53340 | F18: Ahmed SR | G18: ann-INV354 | I18: Rita SR | J18: =E2+E3 -> 2547750 | K18: =J18/J$24 -> 0.49683258 | L18: -0.0377
A19: 46226 | B19: Maltina Pet 33cl | C19: 60 | D19: 5000 | E19: =C19*D19 -> 300000 | F19: Ameh Mathew | G19: ann-INV355 | I19: Eniola Marketer | J19: =E4+E22+E23 -> 1501000 | K19: =J19/J$24 -> 0.29270756 | L19: -0.0202
A20: 46226 | B20: Goldberg 60cl | C20: 2 | D20: 9200 | E20: =C20*D20 -> 18400 | F20: MAADE HOTEL | G20: ann-INV356 | I20: June Target Achievement Incentive Scheme | J20: =E5 -> 37340 | K20: =J20/J$24 -> 0.0072816126 | L20: 0.0727
A21: 46226 | B21: Trophy | C21: 1 | D21: 8500 | E21: =C21*D21 -> 8500 | F21: MAADE HOTEL | G21: ann-INV356 | I21: Ameh Mathew | J21: =E6+E7+E8+E9+E10+E11+E12+E19 -> 636405 | K21: =J21/J$24 -> 0.1241043 | L21: 0.024
A22: 46226 | B22: Goldberg 60cl | C22: 15 | D22: 9200 | E22: =C22*D22 -> 138000 | F22: Eniola Marketer | G22: ann-INV357 | I22: Ahmed SR | J22: =E13+E14+E15+E16+E17+E18 -> 378590 | K22: =J22/J$24 -> 0.073828219 | L22: 0.0792
A23: 46226 | B23: Trophy | C23: 15 | D23: 8200 | E23: =C23*D23 -> 123000 | F23: Eniola Marketer | G23: ann-INV357 | I23: MAADE HOTEL | J23: =E20+E21 -> 26900 | K23: =J23/J$24 -> 0.0052457252 | L23: 0.0545
B24: Grand Total | C24: =SUM(C2:C23) -> 916 | D24: =SUM(D2:D23) -> 228055 | E24: =SUM(E2:E23) -> 5127985 | I24: Total | J24: =SUM(J18:J23) -> 5127985 | K24: =J24/J$24 -> 1
I26: Invoice No | J26: Amount_NGN | K26: Gross Profit
I27: ann-INV350 | J27: 2480000 | K27: -0.04
I28: ann-INV351 | J28: 67750 | K28: 0.05
I29: ann-INV352 | J29: 1240000 | K29: -0.04
I30: Tayo-INV141 | J30: 37340 | K30: 0.07
I31: ann-INV353 | J31: 391605 | K31: 0.07
I32: ann-INV354 | J32: 449590 | K32: 0.08
I33: ann-INV355 | J33: 300000 | K33: -0.04
I34: ann-INV356 | J34: 26900 | K34: 0.05
I35: ann-INV357 | J35: 316500 | K35: 0.06
I36: Total | J36: =SUM(J27:J35) -> 5309685

Sheet July 24th Sales Report
A1: Date | B1: Product | C1: Cases_Sold | D1: Unit_Price_NGN | E1: Amount_NGN | F1: Customer | G1: Invoice No | I1: Product | J1: Quantity | K1: Revenue | L1: % of Total Revenue | N1: Total Revenue | O1: Total Cases Sold | P1: Total transaction
A2: 46227 | B2: Goldberg 60cl | C2: 140 | D2: 8500 | E2: =C2*D2 -> 1190000 | F2: Abbey Illisan | G2: ann-INV358 | I2: Goldberg 60cl | J2: =C2+C4+C6+C18+C22+C26+C30+C34+C36+C37 -> 258 | K2: =E2+E4+E6+E18+E22+E26+E30+E34+E36+E37 -> 2276840 | L2: =K2/K$14 -> 0.33363226 | N2: =K14 -> 6824400 | O2: =J14 -> 880 | P2: =COUNT(J2:J13) -> 12
A3: 46227 | B3: 33 Export 60cl | C3: 280 | D3: 8990 | E3: =C3*D3 -> 2517200 | F3: Abbey Illisan | G3: ann-INV358 | I3: 33 Export 60cl | J3: =C3+C10+C14+C19+C31+C35 -> 298 | K3: =E3+E10+E14+E19+E31+E35 -> 2683400 | L3: =K3/K$14 -> 0.39320673
A4: 46227 | B4: Goldberg 60cl | C4: 1 | D4: 9500 | E4: =C4*D4 -> 9500 | F4: Remilekun | G4: ann-INV359 | I4: Heineken Bottle 60cl | J4: =C5+C13+C20+C25 -> 11 | K4: =E5+E13+E20+E25 -> 149760 | L4: =K4/K$14 -> 0.021944786
A5: 46227 | B5: Heineken Bottle 60cl | C5: 1 | D5: 13950 | E5: =C5*D5 -> 13950 | F5: Remilekun | G5: ann-INV360 | I5: Maltina Pet 33cl | J5: =C7+C16+C17+C33 -> 292 | K5: =E7+E16+E17+E33 -> 1460400 | L5: =K5/K$14 -> 0.21399683
A6: 46227 | B6: Goldberg 60cl | C6: 20 | D6: 8800 | E6: =C6*D6 -> 176000 | F6: Ameh Mathew | G6: ann-INV363 | I6: Desperados Bottle | J6: =C8 -> 1 | K6: =E8 -> 21400 | L6: =K6/K$14 -> 0.0031358068
A7: 46227 | B7: Maltina Pet 33cl | C7: 5 | D7: 5000 | E7: =C7*D7 -> 25000 | F7: Ameh Mathew | G7: ann-INV363 | I7: Maltina Bottle | J7: =C9+C24 -> 5 | K7: =E9+E24 -> 66160 | L7: =K7/K$14 -> 0.0096946252
A8: 46227 | B8: Desperados Bottle | C8: 1 | D8: 21400 | E8: =C8*D8 -> 21400 | F8: Ameh Mathew | G8: ann-INV363 | I8: Star Radler 45cl | J8: =C11 -> 1 | K8: =E11 -> 14575 | L8: =K8/K$14 -> 0.0021357189
A9: 46227 | B9: Maltina Bottle | C9: 3 | D9: 13020 | E9: =C9*D9 -> 39060 | F9: Ameh Mathew | G9: ann-INV363 | I9: Gulder Bottle | J9: =C12+C23+C32 -> 4 | K9: =E12+E23+E32 -> 48255 | L9: =K9/K$14 -> 0.0070709513
A10: 46227 | B10: 33 Export 60cl | C10: 6 | D10: 9200 | E10: =C10*D10 -> 55200 | F10: Ameh Mathew | G10: ann-INV363 | I10: Turbo King Bottle 60cl | J10: =C15 -> 1 | K10: =E15 -> 9500 | L10: =K10/K$14 -> 0.0013920638
A11: 46227 | B11: Star Radler 45cl | C11: 1 | D11: 14575 | E11: =C11*D11 -> 14575 | F11: Ameh Mathew | G11: ann-INV363 | I11: Legend Bottle 60cl | J11: =C21 -> 5 | K11: =E21 -> 57400 | L11: =K11/K$14 -> 0.0084109958
A12: 46227 | B12: Gulder Bottle | C12: 1 | D12: 11910 | E12: =C12*D12 -> 11910 | F12: Ameh Mathew | G12: ann-INV363 | I12: Trophy | J12: =C27+C29 -> 3 | K12: =E27+E29 -> 27000 | L12: =K12/K$14 -> 0.0039563918
A13: 46227 | B13: Heineken Bottle 60cl | C13: 1 | D13: 13335 | E13: =C13*D13 -> 13335 | F13: Ameh Mathew | G13: ann-INV363 | I13: Castle Lite | J13: =C28 -> 1 | K13: =E28 -> 9710 | L13: =K13/K$14 -> 0.0014228357
A14: 46227 | B14: 33 Export 60cl | C14: 1 | D14: 9500 | E14: =C14*D14 -> 9500 | F14: Walk in Customer | G14: ann-INV361 | I14: Grand Total | J14: =SUM(J2:J13) -> 880 | K14: =SUM(K2:K13) -> 6824400 | L14: =K14/K$14 -> 1
A15: 46227 | B15: Turbo King Bottle 60cl | C15: 1 | D15: 9500 | E15: =C15*D15 -> 9500 | F15: Walk in Customer | G15: ann-INV361
A16: 46227 | B16: Maltina Pet 33cl | C16: 270 | D16: 5000 | E16: =C16*D16 -> 1350000 | F16: Eniola Marketer | G16: ann-INV362 | I16: Customer | J16: Amount_NGN | K16: % of Total Revenue | L16: Gross Profit
A17: 46227 | B17: Maltina Pet 33cl | C17: 15 | D17: 5000 | E17: =C17*D17 -> 75000 | F17: Mr Godswill | G17: ann-INV364 | I17: Abbey Illisan | J17: =E2+E3 -> 3707200 | K17: =J17/J$26 -> 0.54322724 | L17: 0.0219
A18: 46227 | B18: Goldberg 60cl | C18: 10 | D18: 9200 | E18: =C18*D18 -> 92000 | F18: Mr Godswill | G18: ann-INV364 | I18: Remilekun | J18: =E4+E5 -> 23450 | K18: =J18/J$26 -> 0.0034361995 | L18: 0.0872
A19: 46227 | B19: 33 Export 60cl | C19: 5 | D19: 9200 | E19: =C19*D19 -> 46000 | F19: Mr Godswill | G19: ann-INV364 | I19: Ameh Mathew | J19: =E6+E7+E8+E9+E10+E11+E12+E13 -> 356480 | K19: =J19/J$26 -> 0.052236094 | L19: 0.0439
A20: 46227 | B20: Heineken Bottle 60cl | C20: 5 | D20: 13335 | E20: =C20*D20 -> 66675 | F20: Mr Godswill | G20: ann-INV364 | I20: Walk in Customer | J20: =E14+E15+E29+E30+E31+E32+E33 -> 69925 | K20: =J20/J$26 -> 0.010246322 | L20: 0.0788
A21: 46227 | B21: Legend Bottle 60cl | C21: 5 | D21: 11480 | E21: =C21*D21 -> 57400 | F21: Mr Godswill | G21: ann-INV364 | I21: Eniola Marketer | J21: =E16 -> 1350000 | K21: =J21/J$26 -> 0.19781959 | L21: -0.04
A22: 46227 | B22: Goldberg 60cl | C22: 2 | D22: 9335 | E22: =C22*D22 -> 18670 | F22: ATW | G22: ann-INV365 | I22: Mr Godswill | J22: =E17+E18+E19+E20+E21 -> 337075 | K22: =J22/J$26 -> 0.049392621 | L22: 0.0635
A23: 46227 | B23: Gulder Bottle | C23: 2 | D23: 11910 | E23: =C23*D23 -> 23820 | F23: Mr Olayinka | G23: ann-INV366 | I23: ATW | J23: =E22+E36+E37 -> 597440 | K23: =J23/J$26 -> 0.087544693 | L23: 0.0729
A24: 46227 | B24: Maltina Bottle | C24: 2 | D24: 13550 | E24: =C24*D24 -> 27100 | F24: Mr Olayinka | G24: ann-INV366 | I24: Mr Olayinka | J24: =E23+E24+E25+E26+E27+E28 -> 152830 | K24: =J24/J$26 -> 0.022394643 | L24: 0.07
A25: 46227 | B25: Heineken Bottle 60cl | C25: 4 | D25: 13950 | E25: =C25*D25 -> 55800 | F25: Mr Olayinka | G25: ann-INV366 | I25: Stella SR | J25: =E34+E35 -> 230000 | K25: =J25/J$26 -> 0.033702597 | L25: 0.0518
A26: 46227 | B26: Goldberg 60cl | C26: 2 | D26: 9200 | E26: =C26*D26 -> 18400 | F26: Mr Olayinka | G26: ann-INV366 | I26: Total | J26: =SUM(J17:J25) -> 6824400 | K26: =J26/J$26 -> 1
A27: 46227 | B27: Trophy | C27: 2 | D27: 9000 | E27: =C27*D27 -> 18000 | F27: Mr Olayinka | G27: ann-INV366
A28: 46227 | B28: Castle Lite | C28: 1 | D28: 9710 | E28: =C28*D28 -> 9710 | F28: Mr Olayinka | G28: ann-INV366 | I28: Invoice No | J28: Amount_NGN | K28: Gross Profit
A29: 46227 | B29: Trophy | C29: 1 | D29: 9000 | E29: =C29*D29 -> 9000 | F29: Walk in Customer | G29: ann-INV367 | I29: ann-INV358 | J29: 4463200 | K29: 0.02
A30: 46227 | B30: Goldberg 60cl | C30: 1 | D30: 9500 | E30: =C30*D30 -> 9500 | F30: Walk in Customer | G30: ann-INV367 | I30: ann-INV359 | J30: 9500 | K30: 0.09
A31: 46227 | B31: 33 Export 60cl | C31: 1 | D31: 9500 | E31: =C31*D31 -> 9500 | F31: Walk in Customer | G31: ann-INV367 | I31: ann-INV360 | J31: 13950 | K31: 0.09
A32: 46227 | B32: Gulder Bottle | C32: 1 | D32: 12525 | E32: =C32*D32 -> 12525 | F32: Walk in Customer | G32: ann-INV367 | I32: ann-INV363 | J32: 416280 | K32: 0.04
A33: 46227 | B33: Maltina Pet 33cl | C33: 2 | D33: 5200 | E33: =C33*D33 -> 10400 | F33: Walk in Customer | G33: ann-INV367 | I33: ann-INV361 | J33: 19000 | K33: 0.08
A34: 46227 | B34: Goldberg 60cl | C34: 20 | D34: 9200 | E34: =C34*D34 -> 184000 | F34: Stella SR | G34: ann-INV368 | I34: ann-INV362 | J34: 1350000 | K34: -0.04
A35: 46227 | B35: 33 Export 60cl | C35: 5 | D35: 9200 | E35: =C35*D35 -> 46000 | F35: Stella SR | G35: ann-INV368 | I35: ann-INV364 | J35: 383075 | K35: 0.06
A36: 46227 | B36: Goldberg 60cl | C36: 2 | D36: 9335 | E36: =C36*D36 -> 18670 | F36: ATW | G36: ann-INV369 | I36: ann-INV365 | J36: 18670 | K36: 0.07
A37: 46227 | B37: Goldberg 60cl | C37: 60 | D37: 9335 | E37: =C37*D37 -> 560100 | F37: ATW | G37: ann-INV370 | I37: ann-INV366 | J37: 154730 | K37: 0.07
B38: Grand Total | C38: =SUM(C2:C37) -> 880 | D38: =SUM(D2:D37) -> 369845 | E38: =SUM(E2:E37) -> 6824400 | I38: ann-INV367 | J38: 58225 | K38: 0.08
I39: ann-INV368 | J39: 230000 | K39: 0.05
I40: ann-INV369 | J40: 20470 | K40: 0.08
I41: ann-INV370 | J41: 560100 | K41: 0.07
I42: Total | J42: =SUM(J29:J41) -> 7697200

Sheet July 25th Sales Report
A1: Date | B1: Product | C1: Cases_Sold | D1: Unit_Price_NGN | E1: Amount_NGN | F1: Customer | G1: Invoice No | I1: Product | J1: Quantity | K1: Revenue | L1: % of Total Revenue | N1: Total Revnue | O1: Total Cases Sold | P1: Total transaction
A2: 46228 | B2: Desperados Bottle | C2: 1 | D2: 21485 | E2: =C2*D2 -> 21485 | F2: Mr Godswill | G2: ann-INV372 | I2: Desperados Bottle | J2: =C2 -> 1 | K2: =E2 -> 21485 | L2: =K2/K$16 -> 0.0082236874 | N2: =K16 -> 2612575 | O2: =J16 -> 384 | P2: =COUNT(J2:J15) -> 14
A3: 46228 | B3: Goldberg Black 45cl | C3: 2 | D3: 14145 | E3: =C3*D3 -> 28290 | F3: Mr Godswill | G3: ann-INV372 | I3: Goldberg Black 45cl | J3: =C3 -> 2 | K3: =E3 -> 28290 | L3: =K3/K$16 -> 0.010828397
A4: 46228 | B4: Maltina Pet 33cl | C4: 1 | D4: 5300 | E4: =C4*D4 -> 5300 | F4: Walk in Customer | G4: ann-INV373 | I4: Maltina Pet 33cl | J4: =C4+C5+C7+C24 -> 267 | K4: =E4+E5+E7+E24 -> 1335600 | L4: =K4/K$16 -> 0.51121977
A5: 46228 | B5: Maltina Pet 33cl | C5: 260 | D5: 5000 | E5: =C5*D5 -> 1300000 | F5: Mr Lekan Ojifini | G5: ann-INV374 | I5: Goldberg 60cl | J5: =C6+C10+C11+C12+C16+C17+C20+C26+C29+C32 -> 64 | K5: =E6+E10+E11+E12+E16+E17+E20+E26+E29+E32 -> 576035 | L5: =K5/K$16 -> 0.22048554
A6: 46228 | B6: Goldberg 60cl | C6: 10 | D6: 9200 | E6: =C6*D6 -> 92000 | F6: Mr Godswill | G6: ann-INV375 | I6: Desperados Can | J6: =C8+C21 -> 6 | K6: =E8+E21 -> 136440 | L6: =K6/K$16 -> 0.052224338
A7: 46228 | B7: Maltina Pet 33cl | C7: 5 | D7: 5000 | E7: =C7*D7 -> 25000 | F7: Mr Godswill | G7: ann-INV375 | I7: Legend Can 44cl | J7: =C9 -> 3 | K7: =E9 -> 63510 | L7: =K7/K$16 -> 0.02430935
A8: 46228 | B8: Desperados Can | C8: 5 | D8: 22740 | E8: =C8*D8 -> 113700 | F8: Taiwo SR | G8: ann-INV376 | I8: Turbo King Bottle 60cl | J8: =C13+C27 -> 11 | K8: =E13+E27 -> 98000 | L8: =K8/K$16 -> 0.037510885
A9: 46228 | B9: Legend Can 44cl | C9: 3 | D9: 21170 | E9: =C9*D9 -> 63510 | F9: Taiwo SR | G9: ann-INV376 | I9: 33 Export 60cl | J9: =C14+C33 -> 12 | K9: =E14+E33 -> 110400 | L9: =K9/K$16 -> 0.04225716
A10: 46228 | B10: Goldberg 60cl | C10: 10 | D10: 9200 | E10: =C10*D10 -> 92000 | F10: Solomon | G10: ann-INV377 | I10: Heineken Bottle 60cl | J10: =C15+C18+C30+C34 -> 8 | K10: =E15+E18+E30+E34 -> 107295 | L10: =K10/K$16 -> 0.041068677
A11: 46228 | B11: Goldberg 60cl | C11: 3 | D11: 9200 | E11: =C11*D11 -> 27600 | F11: Mr Olayinka | G11: ann-INV378 | I11: Trophy | J11: =C19+C28 -> 2 | K11: =E19+E28 -> 17500 | L11: =K11/K$16 -> 0.0066983723
A12: 46228 | B12: Goldberg 60cl | C12: 30 | D12: 8800 | E12: =C12*D12 -> 264000 | F12: Ameh Mathew | G12: ann-INV379 | I12: Maltina Pet 25cl | J12: =C22 -> 1 | K12: =E22 -> 4200 | L12: =K12/K$16 -> 0.0016076094
A13: 46228 | B13: Turbo King Bottle 60cl | C13: 10 | D13: 8880 | E13: =C13*D13 -> 88800 | F13: Ameh Mathew | G13: ann-INV379 | I13: 33 Export Can | J13: =C23 -> 1 | K13: =E23 -> 16145 | L13: =K13/K$16 -> 0.0061797269
A14: 46228 | B14: 33 Export 60cl | C14: 10 | D14: 9200 | E14: =C14*D14 -> 92000 | F14: Ameh Mathew | G14: ann-INV379 | I14: Goldberg Can 50cl | J14: =C25 -> 5 | K14: =E25 -> 80725 | L14: =K14/K$16 -> 0.030898634
A15: 46228 | B15: Heineken Bottle 60cl | C15: 5 | D15: 13335 | E15: =C15*D15 -> 66675 | F15: Ameh Mathew | G15: ann-INV379 | I15: Smirnoff Ice. | J15: =C31 -> 1 | K15: =E31 -> 16950 | L15: =K15/K$16 -> 0.006487852
A16: 46228 | B16: Goldberg 60cl | C16: 1 | D16: 9335 | E16: =C16*D16 -> 9335 | F16: ATW | G16: ann-INV380 | I16: Grand Total | J16: =SUM(J2:J15) -> 384 | K16: =SUM(K2:K15) -> 2612575 | L16: =K16/K$16 -> 1
A17: 46228 | B17: Goldberg 60cl | C17: 3 | D17: 8800 | E17: =C17*D17 -> 26400 | F17: ATW | G17: ann-INV381
A18: 46228 | B18: Heineken Bottle 60cl | C18: 1 | D18: 13335 | E18: =C18*D18 -> 13335 | F18: Breakages | G18: Tayo-INV142 | I18: Customer | J18: Amount_NGN | K18: % of Total Revenue | L18: Gross Profit
A19: 46228 | B19: Trophy | C19: 1 | D19: 8500 | E19: =C19*D19 -> 8500 | F19: Breakages | G19: Tayo-INV142 | I19: Mr Godswill | J19: =E2+E3+E6+E7+E25 -> 247500 | K19: =J19/J$31 -> 0.094734122 | L19: 0.053
A20: 46228 | B20: Goldberg 60cl | C20: 1 | D20: 9200 | E20: =C20*D20 -> 9200 | F20: Breakages | G20: Tayo-INV142 | I20: Walk in Customer | J20: =E4+E24+E31 -> 27550 | K20: =J20/J$31 -> 0.010545152 | L20: 0.2894
A21: 46228 | B21: Desperados Can | C21: 1 | D21: 22740 | E21: =C21*D21 -> 22740 | F21: Breakages | G21: Tayo-INV142 | I21: Mr Lekan Ojifini | J21: =E5 -> 1300000 | K21: =J21/J$31 -> 0.49759337 | L21: -0.04
A22: 46228 | B22: Maltina Pet 25cl | C22: 1 | D22: 4200 | E22: =C22*D22 -> 4200 | F22: Breakages | G22: Tayo-INV142 | I22: Taiwo SR | J22: =E8+E9 -> 177210 | K22: =J22/J$31 -> 0.067829632 | L22: 0.0453
A23: 46228 | B23: 33 Export Can | C23: 1 | D23: 16145 | E23: =C23*D23 -> 16145 | F23: Breakages | G23: Tayo-INV142 | I23: Solomon | J23: =E10 -> 92000 | K23: =J23/J$31 -> 0.0352143 | L23: 0.0753
A24: 46228 | B24: Maltina Pet 33cl | C24: 1 | D24: 5300 | E24: =C24*D24 -> 5300 | F24: Walk in Customer | G24: ann-INV382 | I24: Mr Olayinka | J24: =E11 -> 27600 | K24: =J24/J$31 -> 0.01056429 | L24: 0.0591
A25: 46228 | B25: Goldberg Can 50cl | C25: 5 | D25: 16145 | E25: =C25*D25 -> 80725 | F25: Mr Godswill | G25: ann-INV383 | I25: Ameh Mathew | J25: =E12+E13+E14+E15 -> 511475 | K25: =J25/J$31 -> 0.19577428 | L25: 0.0597
A26: 46228 | B26: Goldberg 60cl | C26: 2 | D26: 9200 | E26: =C26*D26 -> 18400 | F26: MRS IK. | G26: ann-INV384 | I26: ATW | J26: =E16+E17 -> 35735 | K26: =J26/J$31 -> 0.013678076 | L26: 0.0477
A27: 46228 | B27: Turbo King Bottle 60cl | C27: 1 | D27: 9200 | E27: =C27*D27 -> 9200 | F27: MRS IK. | G27: ann-INV384 | I27: Breakages | J27: =E18+E19+E20+E21+E22+E23 -> 74120 | K27: =J27/J$31 -> 0.028370477 | L27: 0.0465
A28: 46228 | B28: Trophy | C28: 1 | D28: 9000 | E28: =C28*D28 -> 9000 | F28: MRS IK. | G28: ann-INV384 | I28: MRS IK. | J28: =E26+E27+E28 -> 36600 | K28: =J28/J$31 -> 0.014009167 | L28: 0.0721
A29: 46228 | B29: Goldberg 60cl | C29: 1 | D29: 9500 | E29: =C29*D29 -> 9500 | F29: Remilekun | G29: ann-INV385 | I29: Remilekun | J29: =E29+E30 -> 23450 | K29: =J29/J$31 -> 0.0089758189 | L29: 0.0872
A30: 46228 | B30: Heineken Bottle 60cl | C30: 1 | D30: 13950 | E30: =C30*D30 -> 13950 | F30: Remilekun | G30: ann-INV387 | I30: Jeff SR | J30: =E32+E33+E34 -> 59335 | K30: =J30/J$31 -> 0.02271131 | L30: 0.0445
A31: 46228 | B31: Smirnoff Ice. | C31: 1 | D31: 16950 | E31: =C31*D31 -> 16950 | F31: Walk in Customer | G31: ann-INV388 | I31: Total | J31: =SUM(J19:J30) -> 2612575 | K31: =J31/J$31 -> 1
A32: 46228 | B32: Goldberg 60cl | C32: 3 | D32: 9200 | E32: =C32*D32 -> 27600 | F32: Jeff SR | G32: ann-INV386
A33: 46228 | B33: 33 Export 60cl | C33: 2 | D33: 9200 | E33: =C33*D33 -> 18400 | F33: Jeff SR | G33: ann-INV386 | I33: Invoice No | J33: Amount_NGN | K33: Gross Profit
A34: 46228 | B34: Heineken Bottle 60cl | C34: 1 | D34: 13335 | E34: =C34*D34 -> 13335 | F34: Jeff SR | G34: ann-INV386 | I34: ann-INV372 | J34: 49775 | K34: 0.05
B35: Grand Total | C35: =SUM(C2:C34) -> 384 | D35: =SUM(D2:D34) -> 375890 | E35: =SUM(E2:E34) -> 2612575 | I35: ann-INV373 | J35: 5300 | K35: 0.02
I36: ann-INV374 | J36: 1300000 | K36: -0.04
I37: ann-INV375 | J37: 135000 | K37: 0.05
I38: ann-INV376 | J38: 177210 | K38: 0.05
I39: ann-INV377 | J39: 110000 | K39: 0.08
I40: ann-INV378 | J40: 27600 | K40: 0.06
I41: ann-INV379 | J41: 611475 | K41: 0.06
I42: ann-INV380 | J42: 9335 | K42: 0.07
I43: ann-INV381 | J43: 31800 | K43: 0.04
I44: Tayo-INV142 | J44: 74120 | K44: 0.05
I45: ann-INV382 | J45: 5300 | K45: 0.02
I46: ann-INV383 | J46: 80725 | K46: 0.06
I47: ann-INV384 | J47: 36600 | K47: 0.07
... I51: ann-INV386 | J51: 59335 | K51: 0.04
I52: Total | J52: =SUM(J34:J51) -> 2758975

Sheet July 26th Sales Report
A1: July 26th, 2026
A2: No sales recorded - store closed (Sunday).

Sheet July 27th Sales Report
A1: Date | B1: Product | C1: Cases_Sold | D1: Unit_Price_NGN | E1: Amount_NGN | F1: Customer | G1: Invoice No | I1: Product | J1: Quantity | K1: Revenue | L1: % of Total Revenue | N1: Total Revnue | O1: Total Cases Sold | P1: Total transaction
A2: 46230 | B2: Maltina Pet 33cl | C2: 2 | D2: 5300 | E2: =C2*D2 -> 10600 | F2: Walk in Customer | G2: ann-INV389 | I2: Maltina Pet 33cl | J2: =C2+C9+C18+C23+C31+C32 -> 374 | K2: =E2+E9+E18+E23+E31+E32 -> 1871200 | L2: =K2/K$14 -> 0.23661576 | N2: =K14 -> 7908180 | O2: =J14 -> 971 | P2: =COUNT(J2:J13) -> 12
A3: 46230 | B3: Goldberg Can 50cl | C3: 1 | D3: 16145 | E3: =C3*D3 -> 16145 | F3: Mr Godswill | G3: ann-INV390 | I3: Goldberg Can 50cl | J3: =C3 -> 1 | K3: =E3 -> 16145 | L3: =K3/K$14 -> 0.002041557
A4: 46230 | B4: Legend Bottle 60cl | C4: 10 | D4: 11480 | E4: =C4*D4 -> 114800 | F4: Ameh Mathew | G4: ann-INV391 | I4: Legend Bottle 60cl | J4: =C4 -> 10 | K4: =E4 -> 114800 | L4: =K4/K$14 -> 0.014516614
A5: 46230 | B5: Desperados Bottle | C5: 10 | D5: 21400 | E5: =C5*D5 -> 214000 | F5: Ameh Mathew | G5: ann-INV391 | I5: Desperados Bottle | J5: =C5+C22 -> 15 | K5: =E5+E22 -> 326825 | L5: =K5/K$14 -> 0.041327461
A6: 46230 | B6: Trophy | C6: 3 | D6: 9000 | E6: =C6*D6 -> 27000 | F6: Mr Olayinka | G6: ann-INV392 | I6: Trophy | J6: =C6+C26+C36 -> 6 | K6: =E6+E26+E36 -> 54000 | L6: =K6/K$14 -> 0.0068283726
A7: 46230 | B7: Medium Stout | C7: 1 | D7: 18300 | E7: =C7*D7 -> 18300 | F7: Mr Olayinka | G7: ann-INV392 | I7: Medium Stout | J7: =C7+C13+C30 -> 22 | K7: =E7+E13+E30 -> 390600 | L7: =K7/K$14 -> 0.049391895
A8: 46230 | B8: Heineken Bottle 60cl | C8: 50 | D8: 12930 | E8: =C8*D8 -> 646500 | F8: Delayers | G8: ann-INV394 | I8: Heineken Bottle 60cl | J8: =C8+C12+C17+C19+C25 -> 97 | K8: =E8+E12+E17+E19+E25 -> 1264245 | L8: =K8/K$14 -> 0.15986548
A9: 46230 | B9: Maltina Pet 33cl | C9: 210 | D9: 5000 | E9: =C9*D9 -> 1050000 | F9: Eniola Marketer | G9: ann-INV395 | I9: Goldberg 60cl | J9: =C10+C14+C15+C20+C24+C27 -> 321 | K9: =E10+E14+E15+E20+E24+E27 -> 2757240 | L9: =K9/K$14 -> 0.34865671
A10: 46230 | B10: Goldberg 60cl | C10: 200 | D10: 8500 | E10: =C10*D10 -> 1700000 | F10: Mama Oyin Mowe | G10: ann-INV397 | I10: Turbo King Bottle 60cl | J10: =C11+C29+C35 -> 102 | K10: =E11+E29+E35 -> 906700 | L10: =K10/K$14 -> 0.11465343
A11: 46230 | B11: Turbo King Bottle 60cl | C11: 100 | D11: 8880 | E11: =C11*D11 -> 888000 | F11: Mama Oyin Mowe | G11: ann-INV397 | I11: Maltina Pet 50cl | J11: =C16+C33 -> 18 | K11: =E16+E33 -> 144360 | L11: =K11/K$14 -> 0.018254516
A12: 46230 | B12: Heineken Bottle 60cl | C12: 30 | D12: 12830 | E12: =C12*D12 -> 384900 | F12: Mama Oyin Mowe | G12: ann-INV397 | I12: Maltina Bottle | J12: =C21 -> 3 | K12: =E21 -> 43365 | L12: =K12/K$14 -> 0.0054835626
A13: 46230 | B13: Medium Stout | C13: 20 | D13: 17700 | E13: =C13*D13 -> 354000 | F13: Mama Oyin Mowe | G13: ann-INV397 | I13: 33 Export 60cl | J13: =C28+C34 -> 2 | K13: =E28+E34 -> 18700 | L13: =K13/K$14 -> 0.0023646402
A14: 46230 | B14: Goldberg 60cl | C14: 40 | D14: 9000 | E14: =C14*D14 -> 360000 | F14: Mr Lekan Ojifini | G14: ann-INV396 | I14: Grand Total | J14: =SUM(J2:J13) -> 971 | K14: =SUM(K2:K13) -> 7908180 | L14: =K14/K$14 -> 1
A15: 46230 | B15: Goldberg 60cl | C15: 70 | D15: 8500 | E15: =C15*D15 -> 595000 | F15: Emmycee | G15: ann-INV398
A16: 46230 | B16: Maltina Pet 50cl | C16: 8 | D16: 8020 | E16: =C16*D16 -> 64160 | F16: Eniola Marketer | G16: ann-INV399 | I16: Customer | J16: Amount_NGN | K16: % of Total Revenue | L16: Gross Profit
A17: 46230 | B17: Heineken Bottle 60cl | C17: 5 | D17: 13335 | E17: =C17*D17 -> 66675 | F17: Amandla | G17: ann-INV400 | I17: Walk in Customer | J17: =E2+E18+E34+E35+E36 -> 43900 | K17: =J17/J$30 -> 0.0055512141 | L17: 0.0608
A18: 46230 | B18: Maltina Pet 33cl | C18: 1 | D18: 5300 | E18: =C18*D18 -> 5300 | F18: Walk in Customer | G18: ann-INV401 | I18: Mr Godswill | J18: =E3 -> 16145 | K18: =J18/J$30 -> 0.002041557 | L18: 0.0556
A19: 46230 | B19: Heineken Bottle 60cl | C19: 10 | D19: 13950 | E19: =C19*D19 -> 139500 | F19: XXIII LOUNGE | G19: ann-INV402 | I19: Ameh Mathew | J19: =E4+E5 -> 328800 | K19: =J19/J$30 -> 0.041577202 | L19: 0.1014
A20: 46230 | B20: Goldberg 60cl | C20: 5 | D20: 9300 | E20: =C20*D20 -> 46500 | F20: XXIII LOUNGE | G20: ann-INV402 | I20: Mr Olayinka | J20: =E6+E7 -> 45300 | K20: =J20/J$30 -> 0.0057282459 | L20: 0.0838
A21: 46230 | B21: Maltina Bottle | C21: 3 | D21: 14455 | E21: =C21*D21 -> 43365 | F21: XXIII LOUNGE | G21: ann-INV402 | I21: Delayers | J21: =E8 -> 646500 | K21: =J21/J$30 -> 0.081750795 | L21: 0.1405
A22: 46230 | B22: Desperados Bottle | C22: 5 | D22: 22565 | E22: =C22*D22 -> 112825 | F22: XXIII LOUNGE | G22: ann-INV402 | I22: Eniola Marketer | J22: =E9+E16 -> 1114160 | K22: =J22/J$30 -> 0.14088703 | L22: -0.0353
A23: 46230 | B23: Maltina Pet 33cl | C23: 100 | D23: 5000 | E23: =C23*D23 -> 500000 | F23: Mr Lekan Ojifini | G23: ann-INV403 | I23: Mama Oyin Mowe | J23: =E10+E11+E12+E13 -> 3326900 | K23: =J23/J$30 -> 0.42069098 | L23: 0.0829
A24: 46230 | B24: Goldberg 60cl | C24: 4 | D24: 9335 | E24: =C24*D24 -> 37340 | F24: ATW | G24: ann-INV404 | I24: Mr Lekan Ojifini | J24: =E14+E23+E32+E33 -> 1240200 | K24: =J24/J$30 -> 0.15682496 | L24: 0.0033
A25: 46230 | B25: Heineken Bottle 60cl | C25: 2 | D25: 13335 | E25: =C25*D25 -> 26670 | F25: MAADE HOTEL | G25: ann-INV405 | I25: Emmycee | J25: =E15 -> 595000 | K25: =J25/J$30 -> 0.07523855 | L25: 0.012
A26: 46230 | B26: Trophy | C26: 2 | D26: 9000 | E26: =C26*D26 -> 18000 | F26: MAADE HOTEL | G26: ann-INV405 | I26: Amandla | J26: =E17 -> 66675 | K26: =J26/J$30 -> 0.0084311434 | L26: 0.1632
A27: 46230 | B27: Goldberg 60cl | C27: 2 | D27: 9200 | E27: =C27*D27 -> 18400 | F27: MAADE HOTEL | G27: ann-INV405 | I27: XXIII LOUNGE | J27: =E19+E20+E21+E22 -> 342190 | K27: =J27/J$30 -> 0.043270386 | L27: 0.1589
A28: 46230 | B28: 33 Export 60cl | C28: 1 | D28: 9200 | E28: =C28*D28 -> 9200 | F28: MAADE HOTEL | G28: ann-INV405 | I28: ATW | J28: =E24 -> 37340 | K28: =J28/J$30 -> 0.0047216932 | L28: 0.0861
A29: 46230 | B29: Turbo King Bottle 60cl | C29: 1 | D29: 9200 | E29: =C29*D29 -> 9200 | F29: MAADE HOTEL | G29: ann-INV405 | I29: MAADE HOTEL | J29: =E25+E26+E27+E28+E29+E30+E31 -> 105070 | K29: =J29/J$30 -> 0.013286243 | L29: 0.0587
A30: 46230 | B30: Medium Stout | C30: 1 | D30: 18300 | E30: =C30*D30 -> 18300 | F30: MAADE HOTEL | G30: ann-INV405 | I30: Total | J30: =SUM(J17:J29) -> 7908180 | K30: =J30/J$30 -> 1
A31: 46230 | B31: Maltina Pet 33cl | C31: 1 | D31: 5300 | E31: =C31*D31 -> 5300 | F31: MAADE HOTEL | G31: ann-INV405
A32: 46230 | B32: Maltina Pet 33cl | C32: 60 | D32: 5000 | E32: =C32*D32 -> 300000 | F32: Mr Lekan Ojifini | G32: ann-INV406 | I32: Invoice No | J32: Amount_NGN | K32: Gross Profit
A33: 46230 | B33: Maltina Pet 50cl | C33: 10 | D33: 8020 | E33: =C33*D33 -> 80200 | F33: Mr Lekan Ojifini | G33: ann-INV406 | I33: ann-INV389 | J33: 10600 | K33: 0.02
A34: 46230 | B34: 33 Export 60cl | C34: 1 | D34: 9500 | E34: =C34*D34 -> 9500 | F34: Walk in Customer | G34: ann-INV407 | I34: ann-INV390 | J34: 16145 | K34: 0.06
A35: 46230 | B35: Turbo King Bottle 60cl | C35: 1 | D35: 9500 | E35: =C35*D35 -> 9500 | F35: Walk in Customer | G35: ann-INV407 | I35: ann-INV391 | J35: 366800 | K35: 0.1
A36: 46230 | B36: Trophy | C36: 1 | D36: 9000 | E36: =C36*D36 -> 9000 | F36: Walk in Customer | G36: ann-INV407 | I36: ann-INV392 | J36: 45300 | K36: 0.08
B37: Grand Total | C37: =SUM(C2:C36) -> 971 | D37: =SUM(D2:D36) -> 380780 | E37: =SUM(E2:E36) -> 7908180 | I37: ann-INV394 | J37: 746500 | K37: 0.14
I38: ann-INV395 | J38: 1050000 | K38: -0.04
I39: ann-INV397 | J39: 4026900 | K39: 0.08
I40: ann-INV396 | J40: 440000 | K40: 0.07
I41: ann-INV398 | J41: 721000 | K41: 0.01
I42: ann-INV399 | J42: 64160 | K42: 0.04
I43: ann-INV400 | J43: 76675 | K43: 0.16
I44: ann-INV401 | J44: 5300 | K44: 0.02
I45: ann-INV402 | J45: 386590 | K45: 0.16
I46: ann-INV403 | J46: 500000 | K46: -0.04
I47: ann-INV404 | J47: 44540 | K47: 0.09
I48: ann-INV405 | J48: 105070 | K48: 0.06
I49: ann-INV406 | J49: 380200 | K49: -0.02
I50: ann-INV407 | J50: 28000 | K50: 0.08
I51: Total | J51: =SUM(J33:J50) -> 9013780

Sheet July 28th Sales Report
A1: Date | B1: Product | C1: Cases_Sold | D1: Unit_Price_NGN | E1: Amount_NGN | F1: Customer | G1: Invoice No | I1: Product | J1: Quantity | K1: Revenue | L1: % of Total Revenue | N1: Total Revenue | O1: Total Cases Sold | P1: Total transaction
A2: 46231 | B2: Goldberg 60cl | C2: 4 | D2: 9200 | E2: =C2*D2 -> 36800 | F2: Mr Olayinka | G2: ann-INV408 | I2: Goldberg 60cl | J2: =C2+C18 -> 86 | K2: =E2+E18 -> 802270 | L2: =K2/K$17 -> 0.16069601 | N2: =K17 -> 4992470 | O2: =J17 -> 762 | P2: =COUNT(J2:J16) -> 15
A3: 46231 | B3: 33 Export 60cl | C3: 1 | D3: 9200 | E3: =C3*D3 -> 9200 | F3: Mr Olayinka | G3: ann-INV408 | I3: 33 Export 60cl | J3: =C3+C10+C20 -> 34 | K3: =E3+E10+E20 -> 312800 | L3: =K3/K$17 -> 0.062654357
A4: 46231 | B4: Maltina Pet 33cl | C4: 248 | D4: 4950 | E4: =C4*D4 -> 1227600 | F4: Jeff SR | G4: ann-INV410 | I4: Maltina Pet 33cl | J4: =C4+C6+C7+C9+C15+C19+C26 -> 552 | K4: =E4+E6+E7+E9+E15+E19+E26 -> 2775060 | L4: =K4/K$17 -> 0.55584911
A5: 46231 | B5: Maltina Pet 50cl | C5: 10 | D5: 8020 | E5: =C5*D5 -> 80200 | F5: Jeff SR | G5: ann-INV410 | I5: Maltina Pet 50cl | J5: =C5 -> 10 | K5: =E5 -> 80200 | L5: =K5/K$17 -> 0.016064193
A6: 46231 | B6: Maltina Pet 33cl | C6: 1 | D6: 5300 | E6: =C6*D6 -> 5300 | F6: Walk in Customer | G6: ann-INV409 | I6: Chamdor 75cl | J6: =C8 -> 3 | K6: =E8 -> 85335 | L6: =K6/K$17 -> 0.017092742
A7: 46231 | B7: Maltina Pet 33cl | C7: 248 | D7: 5000 | E7: =C7*D7 -> 1240000 | F7: Eniola Marketer | G7: ann-INV411 | I7: Heineken Bottle 60cl | J7: =C11+C21 -> 29 | K7: =E11+E21 -> 386715 | L7: =K7/K$17 -> 0.077459654
A8: 46231 | B8: Chamdor 75cl | C8: 3 | D8: 28445 | E8: =C8*D8 -> 85335 | F8: Eniola Marketer | G8: ann-INV411 | I8: Turbo King Bottle 60cl | J8: =C12+C22 -> 17 | K8: =E12+E22 -> 150960 | L8: =K8/K$17 -> 0.030237538
A9: 46231 | B9: Maltina Pet 33cl | C9: 15 | D9: 5000 | E9: =C9*D9 -> 75000 | F9: Rita SR | G9: ann-INV412 | I9: Desperados Bottle | J9: =C13+C29 -> 2 | K9: =E13+E29 -> 42885 | L9: =K9/K$17 -> 0.0085899364
A10: 46231 | B10: 33 Export 60cl | C10: 18 | D10: 9200 | E10: =C10*D10 -> 165600 | F10: Ameh Mathew | G10: ann-INV413 | I10: Gulder Bottle | J10: =C14+C25 -> 14 | K10: =E14+E25 -> 166740 | L10: =K10/K$17 -> 0.033398298
A11: 46231 | B11: Heineken Bottle 60cl | C11: 19 | D11: 13335 | E11: =C11*D11 -> 253365 | F11: Ameh Mathew | G11: ann-INV413 | I11: Maltina Can | J11: =C16 -> 1 | K11: =E16 -> 13200 | L11: =K11/K$17 -> 0.0026439818
A12: 46231 | B12: Turbo King Bottle 60cl | C12: 12 | D12: 8880 | E12: =C12*D12 -> 106560 | F12: Ameh Mathew | G12: ann-INV413 | I12: Star Bottle 60cl | J12: =C17+C28 -> 5 | K12: =E17+E28 -> 57075 | L12: =K12/K$17 -> 0.011432217
A13: 46231 | B13: Desperados Bottle | C13: 1 | D13: 21400 | E13: =C13*D13 -> 21400 | F13: Ameh Mathew | G13: ann-INV413 | I13: Legend Bottle 60cl | J13: =C23 -> 3 | K13: =E23 -> 34440 | L13: =K13/K$17 -> 0.006898389
A14: 46231 | B14: Gulder Bottle | C14: 11 | D14: 11910 | E14: =C14*D14 -> 131010 | F14: Ameh Mathew | G14: ann-INV413 | I14: Star Radler 45cl | J14: =C24 -> 3 | K14: =E24 -> 43725 | L14: =K14/K$17 -> 0.0087581898
A15: 46231 | B15: Maltina Pet 33cl | C15: 7 | D15: 5000 | E15: =C15*D15 -> 35000 | F15: Ameh Mathew | G15: ann-INV413 | I15: Fayrouz Can | J15: =C27 -> 2 | K15: =E27 -> 26920 | L15: =K15/K$17 -> 0.0053921205
A16: 46231 | B16: Maltina Can | C16: 1 | D16: 13200 | E16: =C16*D16 -> 13200 | F16: Ameh Mathew | G16: ann-INV413 | I16: Goldberg Black 45cl | J16: =C30 -> 1 | K16: =E30 -> 14145 | L16: =K16/K$17 -> 0.0028332669
A17: 46231 | B17: Star Bottle 60cl | C17: 2 | D17: 11415 | E17: =C17*D17 -> 22830 | F17: Ameh Mathew | G17: ann-INV413 | I17: Grand Total | J17: =SUM(J2:J16) -> 762 | K17: =SUM(K2:K16) -> 4992470 | L17: =K17/K$17 -> 1
A18: 46231 | B18: Goldberg 60cl | C18: 82 | D18: 9335 | E18: =C18*D18 -> 765470 | F18: ATW | G18: ann-INV414
A19: 46231 | B19: Maltina Pet 33cl | C19: 28 | D19: 5970 | E19: =C19*D19 -> 167160 | F19: ATW | G19: ann-INV414 | I19: Customer | J19: Amount_NGN | K19: % of Total Revenue | L19: Gross Profit
A20: 46231 | B20: 33 Export 60cl | C20: 15 | D20: 9200 | E20: =C20*D20 -> 138000 | F20: Ameh Mathew | G20: ann-INV415 | I20: Mr Olayinka | J20: =E2+E3 -> 46000 | K20: =J20/J$28 -> 0.0092138761 | L20: 0.0518
A21: 46231 | B21: Heineken Bottle 60cl | C21: 10 | D21: 13335 | E21: =C21*D21 -> 133350 | F21: Ameh Mathew | G21: ann-INV415 | I21: Jeff SR | J21: =E4+E5 -> 1307800 | K21: =J21/J$28 -> 0.2619545 | L21: -0.0448
A22: 46231 | B22: Turbo King Bottle 60cl | C22: 5 | D22: 8880 | E22: =C22*D22 -> 44400 | F22: Ameh Mathew | G22: ann-INV415 | I22: Walk in Customer | J22: =E6 -> 5300 | K22: =J22/J$28 -> 0.0010615988 | L22: 0.0189
A23: 46231 | B23: Legend Bottle 60cl | C23: 3 | D23: 11480 | E23: =C23*D23 -> 34440 | F23: Ameh Mathew | G23: ann-INV415 | I23: Eniola Marketer | J23: =E7+E8 -> 1325335 | K23: =J23/J$28 -> 0.26546679 | L23: -0.0317
A24: 46231 | B24: Star Radler 45cl | C24: 3 | D24: 14575 | E24: =C24*D24 -> 43725 | F24: Ameh Mathew | G24: ann-INV415 | I24: Rita SR | J24: =E9 -> 75000 | K24: =J24/J$28 -> 0.015022624 | L24: -0.04
A25: 46231 | B25: Gulder Bottle | C25: 3 | D25: 11910 | E25: =C25*D25 -> 35730 | F25: Ameh Mathew | G25: ann-INV415 | I25: Ameh Mathew | J25: =E10+E11+E12+E13+E14+E15+E16+E17+E20+E21+E22+E23+E24+E25+E26+E27+E28 -> 1264775 | K25: =J25/J$28 -> 0.25333652 | L25: 0.082
A26: 46231 | B26: Maltina Pet 33cl | C26: 5 | D26: 5000 | E26: =C26*D26 -> 25000 | F26: Ameh Mathew | G26: ann-INV415 | I26: ATW | J26: =E18+E19 -> 932630 | K26: =J26/J$28 -> 0.18680733 | L26: 0.0928
A27: 46231 | B27: Fayrouz Can | C27: 2 | D27: 13460 | E27: =C27*D27 -> 26920 | F27: Ameh Mathew | G27: ann-INV415 | I27: Mr Godswill | J27: =E29+E30 -> 35630 | K27: =J27/J$28 -> 0.0071367479 | L27: 0.0469
A28: 46231 | B28: Star Bottle 60cl | C28: 3 | D28: 11415 | E28: =C28*D28 -> 34245 | F28: Ameh Mathew | G28: ann-INV415 | I28: Total | J28: =SUM(J20:J27) -> 4992470 | K28: =J28/J$28 -> 1
A29: 46231 | B29: Desperados Bottle | C29: 1 | D29: 21485 | E29: =C29*D29 -> 21485 | F29: Mr Godswill | G29: ann-INV416
A30: 46231 | B30: Goldberg Black 45cl | C30: 1 | D30: 14145 | E30: =C30*D30 -> 14145 | F30: Mr Godswill | G30: ann-INV416 | I30: Invoice No | J30: Amount_NGN | K30: Gross Profit
B31: Grand Total | C31: =SUM(C2:C30) -> 762 | D31: =SUM(D2:D30) -> 319645 | E31: =SUM(E2:E30) -> 4992470 | I31: ann-INV408 | J31: 46000 | K31: 0.05
I32: ann-INV410 | J32: 1307800 | K32: -0.04
I33: ann-INV409 | J33: 5300 | K33: 0.02
I34: ann-INV411 | J34: 1325335 | K34: -0.03
I35: ann-INV412 | J35: 75000 | K35: -0.04
I36: ann-INV413 | J36: 866365 | K36: 0.09
I37: ann-INV414 | J37: 1080230 | K37: 0.09
I38: ann-INV415 | J38: 593410 | K38: 0.07
I39: ann-INV416 | J39: 35630 | K39: 0.05
I40: Total | J40: =SUM(J31:J39) -> 5335070

Sheet 29th Sales Report
A1: Date | B1: Product | C1: Cases_Sold | D1: Unit_Price_NGN | E1: Amount_NGN | F1: Customer | G1: Invoice No | I1: Product | J1: Quantity | K1: Revenue | L1: % of Total Revenue | N1: Total Revnue | O1: Total Cases Sold | P1: Total transaction
A2: 46232 | B2: Goldberg 60cl | C2: 140 | D2: 8500 | E2: =C2*D2 -> 1190000 | F2: WURAOLA | G2: ann-INV417 | I2: Goldberg 60cl | J2: =C2+C11 -> 142 | K2: =E2+E11 -> 1208400 | L2: =K2/K$17 -> 0.12865673 | N2: =K17 -> 9392435 | O2: =J17 -> 842 | P2: =COUNT(J2:J16) -> 15
A3: 46232 | B3: Trophy | C3: 140 | D3: 8100 | E3: =C3*D3 -> 1134000 | F3: WURAOLA | G3: ann-INV417 | I3: Trophy | J3: =C3 -> 140 | K3: =E3 -> 1134000 | L3: =K3/K$17 -> 0.12073546
A4: 46232 | B4: Star Radler 45cl | C4: 30 | D4: 14475 | E4: =C4*D4 -> 434250 | F4: WURAOLA | G4: ann-INV417 | I4: Star Radler 45cl | J4: =C4 -> 30 | K4: =E4 -> 434250 | L4: =K4/K$17 -> 0.046234017
A5: 46232 | B5: TROPHY CAN | C5: 97 | D5: 13500 | E5: =C5*D5 -> 1309500 | F5: WURAOLA | G5: ann-INV417 | I5: TROPHY CAN | J5: =C5 -> 97 | K5: =E5 -> 1309500 | L5: =K5/K$17 -> 0.13942071
A6: 46232 | B6: Goldberg Can 50cl | C6: 96 | D6: 15555 | E6: =C6*D6 -> 1493280 | F6: WURAOLA | G6: ann-INV417 | I6: Goldberg Can 50cl | J6: =C6+C16 -> 97 | K6: =E6+E16 -> 1509425 | L6: =K6/K$17 -> 0.16070646
A7: 46232 | B7: Heineken Sleek Can | C7: 150 | D7: 17100 | E7: =C7*D7 -> 2565000 | F7: WURAOLA | G7: ann-INV417 | I7: Heineken Sleek Can | J7: =C7+C15 -> 152 | K7: =E7+E15 -> 2599200 | L7: =K7/K$17 -> 0.27673335
A8: 46232 | B8: Desperados Bottle | C8: 5 | D8: 21485 | E8: =C8*D8 -> 107425 | F8: ATW | G8: ann-INV418 | I8: Desperados Bottle | J8: =C8 -> 5 | K8: =E8 -> 107425 | L8: =K8/K$17 -> 0.011437396
A9: 46232 | B9: Tiger Bottle | C9: 5 | D9: 15525 | E9: =C9*D9 -> 77625 | F9: ATW | G9: ann-INV418 | I9: Tiger Bottle | J9: =C9+C19 -> 6 | K9: =E9+E19 -> 93150 | L9: =K9/K$17 -> 0.009917556
A10: 46232 | B10: Maltina Can | C10: 1 | D10: 14430 | E10: =C10*D10 -> 14430 | F10: ATW | G10: ann-INV418 | I10: Maltina Can | J10: =C10 -> 1 | K10: =E10 -> 14430 | L10: =K10/K$17 -> 0.0015363428
A11: 46232 | B11: Goldberg 60cl | C11: 2 | D11: 9200 | E11: =C11*D11 -> 18400 | F11: Jeff SR | G11: ann-INV419 | I11: 33 Export 60cl | J11: =C12+C14 -> 17 | K11: =E12+E14 -> 156400 | L11: =K11/K$17 -> 0.016651699
A12: 46232 | B12: 33 Export 60cl | C12: 2 | D12: 9200 | E12: =C12*D12 -> 18400 | F12: Jeff SR | G12: ann-INV419 | I12: Heineken Bottle 60cl | J12: =C13 -> 2 | K12: =E13 -> 26670 | L12: =K12/K$17 -> 0.0028395193
A13: 46232 | B13: Heineken Bottle 60cl | C13: 2 | D13: 13335 | E13: =C13*D13 -> 26670 | F13: Jeff SR | G13: ann-INV419 | I13: Desperados Can | J13: =C17 -> 1 | K13: =E17 -> 21695 | L13: =K13/K$17 -> 0.0023098377
A14: 46232 | B14: 33 Export 60cl | C14: 15 | D14: 9200 | E14: =C14*D14 -> 138000 | F14: Ameh Mathew | G14: ann-INV420 | I14: Amstel Can | J14: =C18 -> 1 | K14: =E18 -> 14430 | L14: =K14/K$17 -> 0.0015363428
A15: 46232 | B15: Heineken Sleek Can | C15: 2 | D15: 17100 | E15: =C15*D15 -> 34200 | F15: Ameh Mathew | G15: ann-INV420 | I15: Fayrouz Can | J15: =C20 -> 1 | K15: =E20 -> 13460 | L15: =K15/K$17 -> 0.0014330682
A16: 46232 | B16: Goldberg Can 50cl | C16: 1 | D16: 16145 | E16: =C16*D16 -> 16145 | F16: Ameh Mathew | G16: ann-INV420 | I16: Maltina Pet 33cl | J16: =C21 -> 150 | K16: =E21 -> 750000 | L16: =K16/K$17 -> 0.079851498
A17: 46232 | B17: Desperados Can | C17: 1 | D17: 21695 | E17: =C17*D17 -> 21695 | F17: Ameh Mathew | G17: ann-INV420 | I17: Grand Total | J17: =SUM(J2:J16) -> 842 | K17: =SUM(K2:K16) -> 9392435 | L17: =K17/K$17 -> 1
